Workbook

Sheet Data Flow Diagram

Sheet User Onboarding Tracker
A1: User Name | B1: Application | C1: LOB | D1: Region | E1: Required Role | F1: Access Status | G1: Date Requested | H1: Date Granted | I1: Notes / Blockers
A2: Alice Johnson | B2: SAP CPQ | C2: Onity | E2: Quotations Admin | F2: Granted | G2: 45901 | H2: 45903 | I2: –
A3: Alice Johnson | B3: CRM - SFDC | C3: Lenel S2 | D3: NA | E3: Sales Ops User | F3: Pending | G3: 45901 | H3: – | I3: Approval received; awaiting IT action
A4: Alice Johnson | B4: Sub Billing - Zuora | C4: Onity | D4: EMEA | E4: Billing Read-Only | F4: Granted | G4: 45901 | H4: 45902 | I4: –
A5: Alice Johnson | B5: LMS | E5: Learner | F5: Granted | G5: 45901 | H5: 45901 | I5: Auto-provisioned via HR system
A6: Bob Martinez | B6: SAP CPQ | E6: Sales Rep | F6: Pending | G6: 45905 | H6: – | I6: Missing manager approval
A7: Bob Martinez | B7: CRM- SFDC | E7: Sales Rep | F7: Pending | G7: 45905 | H7: – | I7: –
A8: Bob Martinez | B8: Sub Billing - Zuora | E8: – (N/A) | F8: N/A | G8: – | H8: – | I8: Not required for role
A9: Bob Martinez | B9: LMS | E9: Learner | F9: Granted
B10: Contact Centre
B11: AMS EAM - SFDC
B12: FSL - SFDC
B13: EDW
B14: CORA PPM

Sheet CCEX (Critical Data Elements)
A1: S.No | B1: Key Data Objects | C1: Source | D1: Destination | E1: Master Data / Transactional Data | F1: Architect Focal (Setup) | G1: Comments | H1: Critical Data Elements (To be loaded into Target System
A2: 1 | B2: Contacts | C2: GDM SFDC | D2: Contact Center | E2: Master Data | F2: Divya HV / Nagendra | G2: Phone | H2: Email
A3: 2 | B3: Material | C3: ERP | D3: CPQ | E3: Master Data | F3: Ashutosh Mishra | H3: SKU | I3: Product System ID | J3: Part Number | K3: Description | L3: Product Type | M3: Category | N3: Pricing Mechanism | O3: Description | P3: Product Catalogue | Q3: Product Hierarchy | R3: Catalogue Hierarchy | S3: Labor Cost | T3: Material Cost | U3: Sales Text | V3: Inclusion Exclusion List
A4: 3 | B4: Price | C4: ERP | D4: CPQ | E4: Master Data | F4: Ashutosh Mishra | H4: Involved_Parties | I4: Transaction_Type | J4: Sales_Org | K4: Buying_Method | L4: Product_SystemId | M4: Division | N4: Plant | O4: Price_Group | P4: Material_Price_Group
A5: 4 | B5: Region Mapping (CT_OGC_REGION_MAPPING) | C5: Business/ Manual | D5: CPQ | E5: Master Data | F5: Ashutosh Mishra | H5: SOR | I5: SALES_OFFICE | J5: ADR_LN1 | K5: ADR_LN2 | L5: ADR_LN3 | M5: ADR_LN4 | N5: ADR_LN5 | O5: PURCHASE | P5: SUSP | Q5: TRAINING
A6: 5 | B6: Contract (CT_AS_CONTRACT_ZA_ZL) | C6: Business/ Manual | D6: CPQ | E6: Master Data | F6: Ashutosh Mishra | H6: Country | I6: SalesOrg | J6: SKU | K6: ZA_Custcare_Advocate | L6: ZL_FSL
A7: 6 | B7: Accounts (Buying) | C7: ERP | D7: E-Commerce | E7: Master Data | F7: Sonam Kumari | H7: Ship-To ID | I7: Bill-To ID | J7: Sales Org | K7: Partner
A8: 7 | B8: Price | C8: ERP | D8: E-Commerce | E8: Master Data | F8: Sonam Kumari | H8: List Price | I8: Sales Org | J8: Currency | K8: UOM | L8: Valid From | M8: Valid To | N8: Price Territory
A9: 8 | B9: Credit Card MID | C9: NA | D9: E-Commerce | E9: Master Data | F9: Sonam Kumari | G9: Merchant id for credit card | H9: CompanyCode | I9: DocummentCurrency | J9: PaymentCardType | K9: accountNumber | L9: sapMID | M9: routingMID
A10: 9 | B10: Material/Product | C10: ERP / EPIM | D10: E-Commerce | E10: Master Data | F10: Sonam Kumari | H10: SKU ID | I10: Channel Status | J10: Category | K10: Item Plant | L10: Images | M10: Media / Documents | N10: Product Reference | O10: Classification | P10: UOM | Q10: Product Availability
A11: 10 | B11: Material/Product | C11: ERP | D11: ELMS (Lenel APAC) | E11: Master Data | F11: Sreeram Girish | H11: Material Number | I11: Description | J11: Sales Organization | K11: Item Category Group | L11: Product Hierarchy
A12: 11 | B12: Price | C12: ERP | D12: ELMS (Lenel APAC) | E12: Master Data | F12: Sreeram Girish | H12: Currency | I12: Unit Price | J12: Net Unit Price
A13: 12 | B13: Contacts (Portal) | C13: GDM SFDC | D13: ELMS (Lenel APAC) | E13: Master Data | F13: Sreeram Girish | H13: SFDC Contact ID | I13: Training ID | J13: Email Address | K13: Account.Product_Line__c
A14: 13 | B14: Training | C14: GDM SFDC | D14: ELMS (Lenel APAC) | E14: Transactional Data | F14: Sreeram Girish | H14: Certification Level | I14: Expiry Date | J14: Version | K14: Type | L14: Certificate Number
A15: 14 | B15: Leads | C15: HubSpot | D15: GDM Marketo | E15: Transactional Data | F15: Rawat Devendra Singh | G15: This is fine. | H15: First Name | I15: Email Address | J15: Company Name | K15: Job Title | L15: Country | M15: State | N15: City | O15: Postal Code | P15: Region | Q15: Email opt-in(Yes or No) | R15: Division | S15: Brand
A16: 15 | B16: Accounts (Buying) | C16: Source SFDC | D16: GDM SFDC | E16: Master Data | F16: Yaswanth\Divya | H16: BillingCity | I16: BillingCountry | J16: BillingPostalCode | K16: BillingState | L16: BillingStreet | M16: Industry | N16: Key_Account__c | O16: Name | P16: Phone | Q16: Product_Line__c | R16: ShippingCity | S16: ShippingCountry | T16: ShippingPostalCode | U16: ShippingState | V16: ShippingStreet | W16: Type | X16: Website | Y16: Region__c | Z16: Sub_Region__c | AA16: Hotel Chain | AB16: Hotel Brand | AC16: Hirarchy Type | AQ16: GBE__c | AR16: Brand2__c | AS16: Brand__c | AT16: Account_Status__c | AU16: Sales_Region__c | AV16: SBU__c | AW16: SBX__c
A17: 16 | B17: Accounts (Non-Buying) | C17: Source SFDC | D17: GDM SFDC | E17: Master Data | F17: Yaswanth\Divya | H17: BillingCity | I17: BillingCountry | J17: BillingPostalCode | K17: BillingState | L17: BillingStreet | M17: Industry | N17: Key_Account__c | O17: Name | P17: Phone | Q17: Product_Line__c | R17: ShippingCity | S17: ShippingCountry | T17: ShippingPostalCode | U17: ShippingState | V17: ShippingStreet | W17: Type | X17: Website | Y17: Region__c | Z17: Sub_Region__c | AA17: Hotel Chain | AB17: Hotel Brand | AC17: Hirarchy Type | AQ17: GBE__c | AR17: Brand2__c | AS17: Brand__c | AT17: Account_Status__c | AU17: Sales_Region__c | AV17: SBU__c | AW17: SBX__c
A18: 17 | B18: Source systems | C18: Source SFDC | D18: GDM SFDC | E18: Master Data | F18: Yaswanth\Divya | H18: Account__c | I18: Company_Code__c | J18: Credit_Freeze__c | K18: Credit_Limit__c | L18: Customer_Classification__c | M18: Customer_Order_Block__c | N18: Customer_Price_Group__c | O18: Distribution_Channel__c | P18: Division2__c | Q18: Source_System_Company_Id__c | R18: GBE2__c | S18: Industry__c | T18: Payment_Terms__c | U18: Sales_Area__c | V18: Sales_Group__c | W18: Sales_Office__c | X18: Sales_Organization__c | Y18: Sales_Org_Dist_Chan_Sales_Office__c | Z18: SBU__c | AQ18: Type__c | AR18: Source_System_Account_Name__c | AS18: Vertical_Market_Description__c | AT18: Street__c | AU18: City__c | AV18: State_Province__c | AW18: Postal_Code__c | AX18: Country__c | AY18: Source__c | AZ18: Source_Id__c | BA18: Instance_Name__c | BB18: Customer_Group_1__c | BC18: Customer_Sales_Category_1__c | BD18: Vertical_Market_Code__c | BE18: Sales_Group__c | BF18: Customer_Classification__c | BG18: Industry__c
A19: 18 | B19: Contact | C19: Source SFDC | D19: GDM SFDC | E19: Master Data | F19: Yaswanth\Divya | H19: AccountId | I19: Phone | J19: Department | K19: HasOptedOutOfEmail | L19: Email | M19: Fax | N19: HomePhone | O19: Training ID | P19: LeadSource | Q19: Mailingstreet | R19: Mailingcity | S19: MailingState | T19: mailingcountry | U19: Mailingpostalcode | V19: MobilePhone | W19: Name | X19: Salutation | Y19: FirstName | Z19: Alternate Email | AQ19: LastName | AR19: Personal_E_mail__c | AS19: Certification Hold | AT19: Title | AU19: Brand2__c | AV19: Product_Line__c | AW19: Region__c | AX19: SBU__c | AY19: SBX__c | AZ19: Contact Role
A20: 19 | B20: Account Team | C20: Source SFDC | D20: GDM SFDC | E20: Master Data | F20: Yaswanth\Divya | H20: AccountId | I20: AccountAccessLevel | J20: CaseAccessLevel | K20: ContactAccessLevel | L20: OpportunityAccessLevel | M20: UserId | N20: TeamMemberRole | O20: GBE | P20: Division | Q20: Primary | R20: Title | S20: Active
A21: 20 | B21: Product | C21: Source SFDC | D21: GDM SFDC | E21: Master Data | F21: Yaswanth\Divya | H21: IsActive | I21: ProductCode | J21: Product Description | K21: Name | L21: Brand | M21: Product_Family__c | N21: Product_Hierarchy__c
A22: 21 | B22: Account contact relationship | C22: Source SFDC | D22: GDM SFDC | E22: Transactional Data | F22: Yaswanth\Divya | H22: Account Name | I22: Active | J22: Direct | K22: E-Comm Active | L22: Account Status | M22: GBE | N22: Division | O22: Billing State/Province | P22: Billing Country | Q22: Billing City | R22: ContactId | S22: Contact_Name_Email__c | T22: Contact_Titan_Portal_Status__c | U22: E_Comm_Active__c
A23: 22 | B23: Lead | C23: Source SFDC | D23: GDM SFDC | E23: Transactional Data | F23: Yaswanth\Divya | H23: First Name | I23: Description | J23: Industry | K23: Email Opt Out | L23: IsUnreadByOwner | M23: GBE | N23: Region | O23: Division | P23: Division Detail | Q23: Brand | R23: Sales Region | S23: Product Line
A24: 23 | B24: Opportunity | C24: Source SFDC | D24: GDM SFDC | E24: Transactional Data | F24: Yaswanth\Divya | H24: AccountId | I24: Amount | J24: CloseDate | K24: Demo Presented | L24: Description | M24: Product Line | N24: End User Company | O24: First Shipment Date | P24: Forecast Category | Q24: Customer Industry | R24: LeadSource | S24: Win/Loss Reason (Primary) | T24: Win/Loss Comments | U24: NextStep | V24: Opportunity Name | W24: Opportunity Owner | X24: PO_Number__c | Y24: StageName | Z24: AssetId | AQ24: Customer Type | AR24: BillToSS | AS24: End User Company | AT24: Opportunity Type | AU24: Opportunity Sub Type | AV24: Go % | AW24: Win % | AX24: Probability (%) | AY24: Recommended Forecast Status | AZ24: Sold To Summary | BA24: Ship To Summary | BB24: Customer Type | BC24: Opportunity Vertical | BD24: Construction Type | BE24: Specification | BF24: GBE | BG24: Region | BH24: Division | BI24: Brand | BJ24: Product Line
A25: 24 | B25: Opportunity team | C25: Source SFDC | D25: GDM SFDC | E25: Transactional Data | F25: Yaswanth\Divya | H25: OpportunityId | I25: OpportunityAccessLevel | J25: TeamMemberRole | K25: UserId
A26: 25 | B26: Contract | C26: Source SFDC | D26: GDM SFDC | E26: Transactional Data | F26: Yaswanth\Divya | H26: Account Name | I26: Activated By | J26: Activated Date | K26: Contract Number | L26: Contract Owner | M26: Contract Name | N26: Contract Record Type | O26: Contract Start Date | P26: Created By | Q26: Customer Signed By | R26: Customer Signed Date | S26: Total Contract Amount | T26: Description | U26: Contract End Date | V26: Government VAR | W26: Company Signed By | X26: Company Signed Date | Y26: Named Accounts | Z26: Special Terms | AQ26: Recordtype Name | AR26: SLX Id | AS26: Status | AT26: Territory Description | AU26: Total Quota Rollup | AV26: Agreement Type | AW26: Legacy ID | AX26: Legacy Source
A27: 26 | B27: Cases | C27: Source SFDC | D27: GDM SFDC | E27: Transactional Data | F27: Yaswanth\Divya | H27: Description | I27: Notes__c | J27: Topic__c | K27: Issues__c | L27: AccountId | M27: SubRegion__c | N27: Notes__c | O27: Approver_Comments__c | P27: Approval_Status__c | Q27: AssetId | R27: Assigned_Timestamp__c | S27: Black_Support__c | T27: BusinessHoursId | U27: ContactId | V27: Reason | W27: Case_Reason_Subtype__c | X27: Status | Y27: Internal_Status__c | Z27: Subject | AQ27: Close_Reason__c
A28: 27 | B28: Knowledge articles | C28: Source SFDC | D28: GDM SFDC | E28: Transactional Data | F28: Yaswanth\Divya | H28: Answer_Solution__c | I28: RecordTypeId | J28: Language | K28: Question_Problem__c | L28: Summary | M28: Title | N28: UrlName | O28: IsVisibleInApp | P28: IsVisibleInPkb | Q28: IsVisibleInCsp | R28: IsVisibleInPrm | S28: GBE__c | T28: Status__c | U28: Type__c | V28: VersionNumber
A29: 28 | B29: Account Configuration | C29: Source SFDC | D29: GDM SFDC | E29: Transactional Data | F29: Yaswanth\Divya | H29: Account__c | I29: Affiliation__c | J29: Chain_ID__c | K29: Chain_Scale__c | L29: Class_Onity__c | M29: Customer_Class__c | N29: Floors_Onity__c | O29: Inn_MARSHA_Code__c | P29: OnPortal_Backup_Computer_Name__c | Q29: OnPortal_Software_Version__c | R29: Open_Date__c | S29: Operation_Onity__c | T29: Rooms__c | U29: Year_Affiliated_Onity__c | V29: Corporate_Billing__c | W29: API_ID__c | X29: Third_Party_App__c | Y29: DirectKey_Live__c | Z29: DirectKey_SaaS_Agreement_Effective_Date__c | AA29: DirectKey_SaaS_Agreement_Effective_Date__c | AB29: DirectKey_SaaS_Agreement_End_Date__c | AC29: Fee_per_lock_per_year__c
A30: 29 | B30: Accounts (Buying & Non-Buying) | C30: GDM SFDC | D30: Portal | E30: Master Data | F30: Kaustav | H30: Account | I30: Account Address (address, Postal Code, Zip Code, Country, Region ) | J30: Relationship of Buying & Non Buying Account (Partner, Role, Type) | K30: Product Lines | L30: Brand | M30: ERP Account Type
A31: 30 | B31: Contact | C31: GDM SFDC | D31: Portal | E31: Master Data | F31: Kaustav | H31: Honeywell_ID | I31: WPHID | J31: PURID | K31: Titan Portal Status | L31: ACR-Ecomm flag (E_Comm_Active__c) | M31: Email | N31: acr_id | O31: Address
A32: 31 | B32: Contact (Portal) - WPHID | C32: GDM SFDC | D32: Portal | E32: Master Data | F32: Kaustav | H32: Email Address | I32: Portal Status | J32: Persona
A33: 32 | B33: Contact (Portal) - PURID | C33: GDM SFDC | D33: Portal | E33: Master Data | F33: Kaustav | H33: Portal User Name | I33: EmailAddress | J33: Honeywell ID
A34: 33 | B34: Material/Product | C34: EPIM | D34: Portal | E34: Master Data | F34: Sunny Pachnanda | H34: AEM Catalog Rollout | I34: Elastic Product | J34: Elastic SKU | K34: Target Market
A35: 34 | B35: Software Metadata | C35: Azure Blob | D35: Portal | E35: Master Data | F35: Sunny Pachnanda | H35: Software Name | I35: Software file type | J35: Software Target audience (Public / Private) | K35: Software Searchable (Yes/No) | L35: Software Visible (Yes/No) | M35: SKU | N35: Sku Description | O35: Product Family | P35: Product Category | Q35: Region (If Any) | R35: Software Description | S35: Brand | T35: File Size | U35: Version | V35: Pre-requsite | W35: FileName | X35: File Type | Y35: File Size | Z35: Country | AA35: Region
A36: 35 | B36: Var Agreements | C36: GDM SFDC | D36: Portal | E36: Transactional Data | F36: Sunny Pachnanda | H36: Agreement_Type__c | I36: Status | J36: EndDate | K36: AccountId
A37: 36 | B37: Cases | C37: GDM SFDC | D37: Portal | E37: Transactional Data | F37: Sunny Pachnanda | H37: Case Type | I37: Case origin | J37: Case Owner | K37: Case End User Account | L37: System ID | M37: Description | N37: Type | O37: Status | P37: Reason
A38: 37 | B38: Orders | C38: ERP | D38: Portal | E38: Transactional Data | F38: Sunny Pachnanda | H38: Invoice ID | I38: Order Id | J38: Order Number | K38: Sold To Number , Name & Address | L38: PO Number | M38: Order Type | N38: Total Amount | O38: Currency | P38: Ship To Number , Name & Address | Q38: Sales Org | R38: Division | S38: Dist. Channel | T38: Status | U38: Profit Center | V38: Part Number | W38: Bill To Number , Name & Address | X38: Credit Block | Y38: Order Tax and Net Value | Z38: Order Date | AA38: lineItemNumber | AB38: catalogNumber | AC38: conditionRate | AD38: line Item Net Price and Net Value | AE38: lineItemOrderStatus | AF38: Line Item Tax | AG38: estimatedDeliveryDate | AH38: shippingDate | AI38: Line item Currency | AJ38: Product Number & Description | AK38: Profit Center | AL38: quantity | AM38: unitOfMeasure | AN38: quantityDue | AO38: quantityShipped | AP38: Deliveries
A39: 38 | B39: Material/Product | C39: ERP | D39: Pros | E39: Master Data | F39: Vimal Kumar | H39: SKU | I39: Sales Org | J39: Plant
A40: 39 | B40: Price | C40: Business/ Manual | D40: Pros | E40: Master Data | F40: Vimal Kumar | H40: SKU | I40: MSRP - Not applicable | J40: List price | K40: Standard Discount | L40: Negotiated Disc Net Price - Not applicable | M40: Negotiated Discount % - Not applicable | N40: Promotional Discounts % - Not applicable | O40: Volume Discounts % - Not applicable | P40: Transfer Prices
A41: 40 | B41: Material/Product | C41: ERP | D41: Zuora (Onity) | E41: Master Data | F41: Channa Bassava / Dumpala, Sudhakar | G41: No Change in the Materials | H41: SKU ID | I41: SKU Description | J41: Offering | K41: Charge Type
A42: 42 | B42: Accounts (Buying) | C42: ERP | D42: Zuora (LS2 APAC & Onity) | E42: Master Data | F42: Channa Bassava / Dumpala, Sudhakar | G42: Sold To and Ship To Accounts gets loaded into Zuora as part of ETL jobs | H42: Account Name | I42: ERP Account Number | J42: Sales Org | K42: Currency
A43: 43 | B43: End user accounts | C43: SFDC | D43: Zuora (LS2 APAC & Onity) | E43: Master Data | F43: Channa Bassava / Dumpala, Sudhakar | G43: Not Applicable for Onity | H43: Account Name | I43: SFDC Account ID | J43: Country | K43: State | L43: Pincode
A44: 44 | B44: Subscriptions (Assets) - Blue Diamond | C44: GDM SFDC (AMS) | D44: Zuora (LS2 APAC) | E44: Transactional Data | F44: Channa Bassava / Dumpala, Sudhakar | G44: Applicable | H44: End Customer Account Id | I44: Renewal Month | J44: VAR Account ID | K44: Technology Type | L44: Method | M44: VAR ERP Account Number
A45: 45 | B45: Subscriptions - OnPortal Renewal Subscriptions(EMEA) | C45: OnityNET | D45: Zuora (Onity) | E45: Transactional Data | F45: Channa Bassava / Dumpala, Sudhakar | H45: Sold To Account | I45: Ship To | J45: SKU | K45: Renewal Date
A46: 46 | B46: Subscriptions - OnPortal Renewal Subscriptions(APAC) | C46: OnityNET | D46: Zuora (Onity) | E46: Transactional Data | F46: Channa Bassava / Dumpala, Sudhakar | H46: Sold To Account | I46: Ship To | J46: SKU | K46: Renewal Date
A47: 47 | B47: Subscriptions - Direct Key (NA Region) | C47: Dkey CoreAPI | D47: Zuora (Onity) | E47: Transactional Data | F47: Channa Bassava / Dumpala, Sudhakar | H47: Sold To Account | I47: Ship To | J47: SKU | K47: Renewal Date
A48: 48 | B48: Subscriptions - Direct Key (EMEA Region) | C48: Dkey CoreAPI | D48: Zuora (Onity) | E48: Transactional Data | F48: Channa Bassava / Dumpala, Sudhakar | H48: Sold To Account | I48: Ship To | J48: SKU | K48: Renewal Date
A49: 49 | B49: Subscriptions - Direct Key (APAC Region) | C49: Dkey CoreAPI | D49: Zuora (Onity) | E49: Transactional Data | F49: Channa Bassava / Dumpala, Sudhakar | H49: Sold To Account | I49: Ship To | J49: SKU | K49: Renewal Date
A50: 50 | B50: SMS - Price Book Entry | C50: SAP | D50: SMS SFDC | E50: Transactional Data | F50: Geetanjali | H50: Price Book | I50: Product
A51: 51 | B51: SMS - Skill | C51: SFDC | D51: SMS SFDC | E51: Transactional Data | F51: Geetanjali
A52: 52 | B52: SMS - Subcontractor Contacts | C52: SFDC | D52: SMS SFDC | E52: Transactional Data | F52: Geetanjali
A53: 53 | B53: SMS - Service Resources (Subcontractors and internal) | C53: SFDC | D53: SMS SFDC | E53: Transactional Data | F53: Geetanjali
A54: 54 | B54: SMS - Work Type | C54: SFDC | D54: SMS SFDC | E54: Transactional Data | F54: Geetanjali
A55: 55 | B55: SMS - Skill Requirmenet | C55: SFDC | D55: SMS SFDC | E55: Transactional Data | F55: Geetanjali
A56: 56 | B56: SMS - Discipline | C56: SFDC | D56: SMS SFDC | E56: Transactional Data | F56: Geetanjali
A57: 57 | B57: SMS - Work Type GAR | C57: SFDC | D57: SMS SFDC | E57: Transactional Data | F57: Geetanjali
A58: 58 | B58: SMS - Maintenance Template GAR | C58: SFDC | D58: SMS SFDC | E58: Transactional Data | F58: Geetanjali
A59: 59 | B59: SMS - Work Plan Template GAR | C59: SFDC | D59: SMS SFDC | E59: Transactional Data | F59: Geetanjali
A60: 60 | B60: SMS - Work Step Template GAR | C60: SFDC | D60: SMS SFDC | E60: Transactional Data | F60: Geetanjali
A61: 61 | B61: SMS - WorkPlan TemplateEntry GAR | C61: SFDC | D61: SMS SFDC | E61: Transactional Data | F61: Geetanjali
A62: 62 | B62: SMS - Work Plan Selection Rule GAR | C62: SFDC | D62: SMS SFDC | E62: Transactional Data | F62: Geetanjali
... A75: 75 | B75: SMS - Agreement Level | C75: SFDC | D75: SMS SFDC | E75: Transactional Data | F75: Geetanjali

Sheet CCEX Data Score Card - UAT
B1: System | C1: Data Object Type | D1: Data Object | E1: Region | F1: Business Focal | G1: Identify CDE | H1: Prep Data | I1: Load | J1: Validation | K1: Status % | L1: Progress | M1: ETA for Validation | N1: Expected Records (UAT) | O1: Loaded Records (UAT) | P1: % Loaded (UAT) | Q1: Missed Records (UAT) | R1: % Problem (UAT) | S1: Remarks / Comments during UAT
A2: 1 | B2: Salesforce | C2: Master Data | D2: Account (Buying) | E2: Onity NA | F2: Anne Kelly - CS Chris Taylor - TC | G2: TRUE | H2: TRUE | I2: TRUE | J2: TRUE | K2: =REPT("|||||||||||||||||||||||",COUNTIF(G2:J2,TRUE)) -> |||||||||||||||||||||||||||||||||||||||||||||||||||||||||||||||||||||||||||||||||||||||||||| | L2: =TEXT(COUNTIF(G2:J2,TRUE)/COLUMNS(G2:J2),"0%") -> 100% | M2: 45918 | N2: 19378 | O2: 19378 | P2: =IFERROR(O2/N2,0) -> 1 | Q2: =IFERROR(N2-O2,0) -> 0 | R2: =IFERROR(Q2/N2,0) -> 0
A3: 2 | B3: Salesforce | C3: Master Data | D3: Account (Non-Buying) | E3: Onity NA | G3: TRUE | H3: TRUE | I3: TRUE | J3: TRUE | K3: =REPT("|||||||||||||||||||||||",COUNTIF(G3:J3,TRUE)) -> |||||||||||||||||||||||||||||||||||||||||||||||||||||||||||||||||||||||||||||||||||||||||||| | L3: =TEXT(COUNTIF(G3:J3,TRUE)/COLUMNS(G3:J3),"0%") -> 100% | M3: 45918 | N3: 114057 | O3: 114057 | P3: =IFERROR(O3/N3,0) -> 1 | Q3: =IFERROR(N3-O3,0) -> 0 | R3: =IFERROR(Q3/N3,0) -> 0
A4: 3 | B4: Salesforce | C4: Master Data | D4: Contact | E4: Onity NA | G4: TRUE | H4: TRUE | I4: TRUE | J4: TRUE | K4: =REPT("|||||||||||||||||||||||",COUNTIF(G4:J4,TRUE)) -> |||||||||||||||||||||||||||||||||||||||||||||||||||||||||||||||||||||||||||||||||||||||||||| | L4: =TEXT(COUNTIF(G4:J4,TRUE)/COLUMNS(G4:J4),"0%") -> 100% | M4: 45918 | N4: 194312 | O4: 194312 | P4: =IFERROR(O4/N4,0) -> 1 | Q4: =IFERROR(N4-O4,0) -> 0 | R4: =IFERROR(Q4/N4,0) -> 0
A5: 4 | B5: Salesforce | C5: Master Data | D5: Product | E5: Onity NA | G5: TRUE | H5: TRUE | I5: TRUE | J5: TRUE | K5: =REPT("|||||||||||||||||||||||",COUNTIF(G5:J5,TRUE)) -> |||||||||||||||||||||||||||||||||||||||||||||||||||||||||||||||||||||||||||||||||||||||||||| | L5: =TEXT(COUNTIF(G5:J5,TRUE)/COLUMNS(G5:J5),"0%") -> 100% | M5: 45918 | N5: 13812 | O5: 13812 | P5: =IFERROR(O5/N5,0) -> 1 | Q5: =IFERROR(N5-O5,0) -> 0 | R5: =IFERROR(Q5/N5,0) -> 0
A6: 5 | B6: Salesforce | C6: Transactional Data | D6: Opportunity | E6: Onity NA | G6: TRUE | H6: TRUE | I6: TRUE | J6: TRUE | K6: =REPT("|||||||||||||||||||||||",COUNTIF(G6:J6,TRUE)) -> |||||||||||||||||||||||||||||||||||||||||||||||||||||||||||||||||||||||||||||||||||||||||||| | L6: =TEXT(COUNTIF(G6:J6,TRUE)/COLUMNS(G6:J6),"0%") -> 100% | M6: 45918 | N6: 11067 | O6: 11067 | P6: =IFERROR(O6/N6,0) -> 1 | Q6: =IFERROR(N6-O6,0) -> 0 | R6: =IFERROR(Q6/N6,0) -> 0
A7: 6 | B7: Salesforce | C7: Transactional Data | D7: Lead | E7: Onity NA | G7: TRUE | H7: TRUE | I7: TRUE | J7: TRUE | K7: =REPT("|||||||||||||||||||||||",COUNTIF(G7:J7,TRUE)) -> |||||||||||||||||||||||||||||||||||||||||||||||||||||||||||||||||||||||||||||||||||||||||||| | L7: =TEXT(COUNTIF(G7:J7,TRUE)/COLUMNS(G7:J7),"0%") -> 100% | M7: 45918 | N7: 352 | O7: 352 | P7: =IFERROR(O7/N7,0) -> 1 | Q7: =IFERROR(N7-O7,0) -> 0 | R7: =IFERROR(Q7/N7,0) -> 0
A8: 7 | B8: Salesforce | C8: Transactional Data | D8: Contract | E8: Onity NA | G8: TRUE | H8: TRUE | I8: TRUE | J8: TRUE | K8: =REPT("|||||||||||||||||||||||",COUNTIF(G8:J8,TRUE)) -> |||||||||||||||||||||||||||||||||||||||||||||||||||||||||||||||||||||||||||||||||||||||||||| | L8: =TEXT(COUNTIF(G8:J8,TRUE)/COLUMNS(G8:J8),"0%") -> 100% | M8: 45918 | N8: 5491 | O8: 5491 | P8: =IFERROR(O8/N8,0) -> 1 | Q8: =IFERROR(N8-O8,0) -> 0 | R8: =IFERROR(Q8/N8,0) -> 0
A9: 8 | B9: Salesforce | C9: Transactional Data | D9: Service Contract | E9: Onity NA | G9: TRUE | H9: TRUE | I9: TRUE | J9: TRUE | K9: =REPT("|||||||||||||||||||||||",COUNTIF(G9:J9,TRUE)) -> |||||||||||||||||||||||||||||||||||||||||||||||||||||||||||||||||||||||||||||||||||||||||||| | L9: =TEXT(COUNTIF(G9:J9,TRUE)/COLUMNS(G9:J9),"0%") -> 100% | M9: 45943 | N9: 803 | O9: 803 | P9: =IFERROR(O9/N9,0) -> 1 | Q9: 0 | R9: =IFERROR(Q9/N9,0) -> 0
A10: 9 | B10: Salesforce | C10: Transactional Data | D10: Case | E10: Onity NA | G10: TRUE | H10: TRUE | I10: TRUE | J10: TRUE | K10: =REPT("|||||||||||||||||||||||",COUNTIF(G10:J10,TRUE)) -> |||||||||||||||||||||||||||||||||||||||||||||||||||||||||||||||||||||||||||||||||||||||||||| | L10: =TEXT(COUNTIF(G10:J10,TRUE)/COLUMNS(G10:J10),"0%") -> 100% | M10: 45918 | N10: 102614 | O10: 102614 | P10: =IFERROR(O10/N10,0) -> 1 | Q10: =IFERROR(N10-O10,0) -> 0 | R10: =IFERROR(Q10/N10,0) -> 0
A11: 10 | B11: Salesforce | C11: Transactional Data | D11: Knowledge Articles | E11: Onity NA | G11: TRUE | H11: TRUE | I11: TRUE | J11: TRUE | K11: =REPT("|||||||||||||||||||||||",COUNTIF(G11:J11,TRUE)) -> |||||||||||||||||||||||||||||||||||||||||||||||||||||||||||||||||||||||||||||||||||||||||||| | L11: =TEXT(COUNTIF(G11:J11,TRUE)/COLUMNS(G11:J11),"0%") -> 100% | M11: 45939 | N11: 344 | O11: 344 | P11: =IFERROR(O11/N11,0) -> 1 | Q11: =IFERROR(N11-O11,0) -> 0 | R11: =IFERROR(Q11/N11,0) -> 0
A12: 11 | B12: Salesforce | C12: Master Data | D12: Account (Buying) | E12: Onity EMEA | F12: Piorno Abelardo Sonia Estrada | G12: TRUE | H12: TRUE | I12: TRUE | J12: TRUE | K12: =REPT("|||||||||||||||||||||||",COUNTIF(G12:J12,TRUE)) -> |||||||||||||||||||||||||||||||||||||||||||||||||||||||||||||||||||||||||||||||||||||||||||| | L12: =TEXT(COUNTIF(G12:J12,TRUE)/COLUMNS(G12:J12),"0%") -> 100% | M12: 45939 | N12: 19478 | O12: 19478 | P12: =IFERROR(O12/N12,0) -> 1 | Q12: =IFERROR(N12-O12,0) -> 0 | R12: =IFERROR(Q12/N12,0) -> 0
A13: 12 | B13: Salesforce | C13: Master Data | D13: Account (Non-Buying) | E13: Onity EMEA | G13: TRUE | H13: TRUE | I13: TRUE | J13: TRUE | K13: =REPT("|||||||||||||||||||||||",COUNTIF(G13:J13,TRUE)) -> |||||||||||||||||||||||||||||||||||||||||||||||||||||||||||||||||||||||||||||||||||||||||||| | L13: =TEXT(COUNTIF(G13:J13,TRUE)/COLUMNS(G13:J13),"0%") -> 100% | M13: 45939 | N13: 25438 | O13: 25438 | P13: =IFERROR(O13/N13,0) -> 1 | Q13: =IFERROR(N13-O13,0) -> 0 | R13: =IFERROR(Q13/N13,0) -> 0
A14: 13 | B14: Salesforce | C14: Master Data | D14: Contact | E14: Onity EMEA | G14: TRUE | H14: TRUE | I14: TRUE | J14: TRUE | K14: =REPT("|||||||||||||||||||||||",COUNTIF(G14:J14,TRUE)) -> |||||||||||||||||||||||||||||||||||||||||||||||||||||||||||||||||||||||||||||||||||||||||||| | L14: =TEXT(COUNTIF(G14:J14,TRUE)/COLUMNS(G14:J14),"0%") -> 100% | M14: 45939 | N14: 23800 | O14: 23800 | P14: =IFERROR(O14/N14,0) -> 1 | Q14: =IFERROR(N14-O14,0) -> 0 | R14: =IFERROR(Q14/N14,0) -> 0
A15: 14 | B15: Salesforce | C15: Master Data | D15: Product | E15: Onity EMEA | G15: TRUE | H15: TRUE | I15: TRUE | J15: TRUE | K15: =REPT("|||||||||||||||||||||||",COUNTIF(G15:J15,TRUE)) -> |||||||||||||||||||||||||||||||||||||||||||||||||||||||||||||||||||||||||||||||||||||||||||| | L15: =TEXT(COUNTIF(G15:J15,TRUE)/COLUMNS(G15:J15),"0%") -> 100% | M15: 45939 | N15: 13812 | O15: 13812 | P15: =IFERROR(O15/N15,0) -> 1 | Q15: =IFERROR(N15-O15,0) -> 0 | R15: =IFERROR(Q15/N15,0) -> 0
A16: 15 | B16: Salesforce | C16: Transactional Data | D16: Opportunity | E16: Onity EMEA | G16: TRUE | H16: TRUE | I16: TRUE | J16: TRUE | K16: =REPT("|||||||||||||||||||||||",COUNTIF(G16:J16,TRUE)) -> |||||||||||||||||||||||||||||||||||||||||||||||||||||||||||||||||||||||||||||||||||||||||||| | L16: =TEXT(COUNTIF(G16:J16,TRUE)/COLUMNS(G16:J16),"0%") -> 100% | M16: 45939 | N16: 31155 | O16: 31155 | P16: =IFERROR(O16/N16,0) -> 1 | Q16: =IFERROR(N16-O16,0) -> 0 | R16: =IFERROR(Q16/N16,0) -> 0
A17: 16 | B17: Salesforce | C17: Transactional Data | D17: Service Contract | E17: Onity EMEA | G17: TRUE | H17: TRUE | I17: TRUE | J17: TRUE | K17: =REPT("|||||||||||||||||||||||",COUNTIF(G17:J17,TRUE)) -> |||||||||||||||||||||||||||||||||||||||||||||||||||||||||||||||||||||||||||||||||||||||||||| | L17: =TEXT(COUNTIF(G17:J17,TRUE)/COLUMNS(G17:J17),"0%") -> 100% | M17: 45943 | N17: 289 | O17: 289 | P17: =IFERROR(O17/N17,0) -> 1 | Q17: 0 | R17: =IFERROR(Q17/N17,0) -> 0
A18: 17 | B18: Salesforce | C18: Transactional Data | D18: Case | E18: Onity EMEA | G18: TRUE | H18: TRUE | I18: TRUE | J18: TRUE | K18: =REPT("|||||||||||||||||||||||",COUNTIF(G18:J18,TRUE)) -> |||||||||||||||||||||||||||||||||||||||||||||||||||||||||||||||||||||||||||||||||||||||||||| | L18: =TEXT(COUNTIF(G18:J18,TRUE)/COLUMNS(G18:J18),"0%") -> 100% | M18: 45943 | N18: 1968 | O18: 1968 | P18: =IFERROR(O18/N18,0) -> 1 | Q18: =IFERROR(N18-O18,0) -> 0 | R18: =IFERROR(Q18/N18,0) -> 0
A19: 18 | B19: Salesforce | C19: Transactional Data | D19: Quote | E19: Onity EMEA | G19: TRUE | H19: TRUE | I19: TRUE | J19: TRUE | K19: =REPT("|||||||||||||||||||||||",COUNTIF(G19:J19,TRUE)) -> |||||||||||||||||||||||||||||||||||||||||||||||||||||||||||||||||||||||||||||||||||||||||||| | L19: =TEXT(COUNTIF(G19:J19,TRUE)/COLUMNS(G19:J19),"0%") -> 100% | M19: 45943 | N19: 8195 | O19: 8195 | P19: =IFERROR(O19/N19,0) -> 1 | Q19: =IFERROR(N19-O19,0) -> 0 | R19: =IFERROR(Q19/N19,0) -> 0
A20: 19 | B20: Salesforce | C20: Master Data | D20: Account (Buying) | E20: Onity APAC | F20: Chin Edmond- RoA Suriati Nur- GC, RoA David Carran- Ken Ong - ANZ James Eapen- Ind | G20: TRUE | H20: TRUE | I20: TRUE | J20: TRUE | K20: =REPT("|||||||||||||||||||||||",COUNTIF(G20:J20,TRUE)) -> |||||||||||||||||||||||||||||||||||||||||||||||||||||||||||||||||||||||||||||||||||||||||||| | L20: =TEXT(COUNTIF(G20:J20,TRUE)/COLUMNS(G20:J20),"0%") -> 100% | M20: 45939 | N20: 6267 | O20: 6267 | P20: =IFERROR(O20/N20,0) -> 1 | Q20: =IFERROR(N20-O20,0) -> 0 | R20: =IFERROR(Q20/N20,0) -> 0
A21: 20 | B21: Salesforce | C21: Master Data | D21: Contact | E21: Onity APAC | G21: TRUE | H21: TRUE | I21: TRUE | J21: TRUE | K21: =REPT("|||||||||||||||||||||||",COUNTIF(G21:J21,TRUE)) -> |||||||||||||||||||||||||||||||||||||||||||||||||||||||||||||||||||||||||||||||||||||||||||| | L21: =TEXT(COUNTIF(G21:J21,TRUE)/COLUMNS(G21:J21),"0%") -> 100% | M21: 45939 | N21: 25 | O21: 25 | P21: =IFERROR(O21/N21,0) -> 1 | Q21: =IFERROR(N21-O21,0) -> 0 | R21: =IFERROR(Q21/N21,0) -> 0
A22: 21 | B22: Salesforce | C22: Master Data | D22: Product | E22: Onity APAC | G22: TRUE | H22: TRUE | I22: TRUE | J22: TRUE | K22: =REPT("|||||||||||||||||||||||",COUNTIF(G22:J22,TRUE)) -> |||||||||||||||||||||||||||||||||||||||||||||||||||||||||||||||||||||||||||||||||||||||||||| | L22: =TEXT(COUNTIF(G22:J22,TRUE)/COLUMNS(G22:J22),"0%") -> 100% | M22: 45939 | N22: 4149 | O22: 4149 | P22: =IFERROR(O22/N22,0) -> 1 | Q22: =IFERROR(N22-O22,0) -> 0 | R22: =IFERROR(Q22/N22,0) -> 0
A23: 22 | B23: Salesforce | C23: Master Data | D23: Account (Buying) | E23: Lenel APAC | F23: Suriati Nur- RoA, GC Ken Ong - ANZ James Eapen- Ind | G23: TRUE | H23: TRUE | I23: TRUE | J23: TRUE | K23: =REPT("|||||||||||||||||||||||",COUNTIF(G23:J23,TRUE)) -> |||||||||||||||||||||||||||||||||||||||||||||||||||||||||||||||||||||||||||||||||||||||||||| | L23: =TEXT(COUNTIF(G23:J23,TRUE)/COLUMNS(G23:J23),"0%") -> 100% | M23: 45939 | N23: 300 | O23: 300 | P23: =IFERROR(O23/N23,0) -> 1 | Q23: =IFERROR(N23-O23,0) -> 0 | R23: =IFERROR(Q23/N23,0) -> 0
A24: 23 | B24: Salesforce | C24: Master Data | D24: Account (Non-Buying) | E24: Lenel APAC | G24: TRUE | H24: TRUE | I24: TRUE | J24: TRUE | K24: =REPT("|||||||||||||||||||||||",COUNTIF(G24:J24,TRUE)) -> |||||||||||||||||||||||||||||||||||||||||||||||||||||||||||||||||||||||||||||||||||||||||||| | L24: =TEXT(COUNTIF(G24:J24,TRUE)/COLUMNS(G24:J24),"0%") -> 100% | M24: 45939 | N24: 9832 | O24: 9832 | P24: =IFERROR(O24/N24,0) -> 1 | Q24: =IFERROR(N24-O24,0) -> 0 | R24: =IFERROR(Q24/N24,0) -> 0
A25: 24 | B25: Salesforce | C25: Master Data | D25: Contact | E25: Lenel APAC | G25: TRUE | H25: TRUE | I25: TRUE | J25: TRUE | K25: =REPT("|||||||||||||||||||||||",COUNTIF(G25:J25,TRUE)) -> |||||||||||||||||||||||||||||||||||||||||||||||||||||||||||||||||||||||||||||||||||||||||||| | L25: =TEXT(COUNTIF(G25:J25,TRUE)/COLUMNS(G25:J25),"0%") -> 100% | M25: 45939 | N25: 4936 | O25: 4936 | P25: =IFERROR(O25/N25,0) -> 1 | Q25: =IFERROR(N25-O25,0) -> 0 | R25: =IFERROR(Q25/N25,0) -> 0
A26: 25 | B26: Salesforce | C26: Master Data | D26: Product | E26: Lenel APAC | G26: TRUE | H26: TRUE | I26: TRUE | J26: TRUE | K26: =REPT("|||||||||||||||||||||||",COUNTIF(G26:J26,TRUE)) -> |||||||||||||||||||||||||||||||||||||||||||||||||||||||||||||||||||||||||||||||||||||||||||| | L26: =TEXT(COUNTIF(G26:J26,TRUE)/COLUMNS(G26:J26),"0%") -> 100% | M26: 45939 | N26: 2275 | O26: 2275 | P26: =IFERROR(O26/N26,0) -> 1 | Q26: =IFERROR(N26-O26,0) -> 0 | R26: =IFERROR(Q26/N26,0) -> 0
A27: 26 | B27: Salesforce | C27: Transactional Data | D27: Opportunity | E27: Lenel APAC | G27: TRUE | H27: TRUE | I27: TRUE | J27: TRUE | K27: =REPT("|||||||||||||||||||||||",COUNTIF(G27:J27,TRUE)) -> |||||||||||||||||||||||||||||||||||||||||||||||||||||||||||||||||||||||||||||||||||||||||||| | L27: =TEXT(COUNTIF(G27:J27,TRUE)/COLUMNS(G27:J27),"0%") -> 100% | M27: 45940 | N27: 1168 | O27: 1168 | P27: =IFERROR(O27/N27,0) -> 1 | Q27: =IFERROR(N27-O27,0) -> 0 | R27: =IFERROR(Q27/N27,0) -> 0
A28: 27 | B28: Salesforce | C28: Transactional Data | D28: Service Contract | E28: Lenel APAC | G28: TRUE | H28: TRUE | I28: TRUE | J28: TRUE | K28: =REPT("|||||||||||||||||||||||",COUNTIF(G28:J28,TRUE)) -> |||||||||||||||||||||||||||||||||||||||||||||||||||||||||||||||||||||||||||||||||||||||||||| | L28: =TEXT(COUNTIF(G28:J28,TRUE)/COLUMNS(G28:J28),"0%") -> 100% | M28: 45940 | N28: 34 | O28: 34 | P28: =IFERROR(O28/N28,0) -> 1 | Q28: =IFERROR(N28-O28,0) -> 0 | R28: =IFERROR(Q28/N28,0) -> 0
A29: 28 | B29: SMS SFDC | C29: Transactional Data | D29: Service Contract | E29: Onity NA | F29: Kathleen | G29: TRUE | H29: TRUE | I29: TRUE | J29: TRUE | K29: =REPT("|||||||||||||||||||||||",COUNTIF(G29:J29,TRUE)) -> |||||||||||||||||||||||||||||||||||||||||||||||||||||||||||||||||||||||||||||||||||||||||||| | L29: =TEXT(COUNTIF(G29:J29,TRUE)/COLUMNS(G29:J29),"0%") -> 100% | M29: 45945 | N29: 2488 | O29: 2488 | P29: =IFERROR(O29/N29,0) -> 1 | Q29: 0 | R29: =IFERROR(Q29/N29,0) -> 0
A30: 29 | B30: SMS SFDC | C30: Master Data | D30: SMS - Subcontractors and internal | E30: Onity NA | G30: TRUE | H30: TRUE | I30: TRUE | J30: TRUE | K30: =REPT("|||||||||||||||||||||||",COUNTIF(G30:J30,TRUE)) -> |||||||||||||||||||||||||||||||||||||||||||||||||||||||||||||||||||||||||||||||||||||||||||| | L30: =TEXT(COUNTIF(G30:J30,TRUE)/COLUMNS(G30:J30),"0%") -> 100% | M30: 45939 | N30: 44 | O30: 44 | P30: =IFERROR(O30/N30,0) -> 1 | Q30: 0 | R30: =IFERROR(Q30/N30,0) -> 0
A31: 30 | B31: SMS SFDC | C31: Master Data | D31: SMS - Work Type Setup | E31: Onity NA | G31: TRUE | H31: TRUE | I31: TRUE | J31: TRUE | K31: =REPT("|||||||||||||||||||||||",COUNTIF(G31:J31,TRUE)) -> |||||||||||||||||||||||||||||||||||||||||||||||||||||||||||||||||||||||||||||||||||||||||||| | L31: =TEXT(COUNTIF(G31:J31,TRUE)/COLUMNS(G31:J31),"0%") -> 100% | M31: 45945 | N31: 48 | O31: 48 | P31: =IFERROR(O31/N31,0) -> 1 | Q31: =IFERROR(N31-O31,0) -> 0 | R31: =IFERROR(Q31/N31,0) -> 0
A32: 31 | B32: SMS SFDC | C32: Master Data | D32: SMS - Service Territory | E32: Onity NA | G32: TRUE | H32: TRUE | I32: TRUE | J32: TRUE | K32: =REPT("|||||||||||||||||||||||",COUNTIF(G32:J32,TRUE)) -> |||||||||||||||||||||||||||||||||||||||||||||||||||||||||||||||||||||||||||||||||||||||||||| | L32: =TEXT(COUNTIF(G32:J32,TRUE)/COLUMNS(G32:J32),"0%") -> 100% | M32: 45939 | N32: 4 | O32: 4 | P32: =IFERROR(O32/N32,0) -> 1 | Q32: =IFERROR(N32-O32,0) -> 0 | R32: =IFERROR(Q32/N32,0) -> 0
A33: 32 | B33: SMS SFDC | C33: Master Data | D33: SMS - Profit Center | E33: Onity NA | G33: TRUE | H33: TRUE | I33: TRUE | J33: TRUE | K33: =REPT("|||||||||||||||||||||||",COUNTIF(G33:J33,TRUE)) -> |||||||||||||||||||||||||||||||||||||||||||||||||||||||||||||||||||||||||||||||||||||||||||| | L33: =TEXT(COUNTIF(G33:J33,TRUE)/COLUMNS(G33:J33),"0%") -> 100% | M33: 45939 | N33: 8 | O33: 8 | P33: =IFERROR(O33/N33,0) -> 1 | Q33: =IFERROR(N33-O33,0) -> 0 | R33: =IFERROR(Q33/N33,0) -> 0
A34: 33 | B34: SMS SFDC | C34: Master Data | D34: SMS - Service Resource Setup | E34: Onity NA | G34: TRUE | H34: TRUE | I34: TRUE | J34: TRUE | K34: =REPT("|||||||||||||||||||||||",COUNTIF(G34:J34,TRUE)) -> |||||||||||||||||||||||||||||||||||||||||||||||||||||||||||||||||||||||||||||||||||||||||||| | L34: =TEXT(COUNTIF(G34:J34,TRUE)/COLUMNS(G34:J34),"0%") -> 100% | M34: 45939 | N34: 122 | O34: 122 | P34: =IFERROR(O34/N34,0) -> 1 | Q34: 0 | R34: =IFERROR(Q34/N34,0) -> 0
A35: 34 | B35: SMS SFDC | C35: Master Data | D35: SMS - Asset | E35: Onity NA | G35: TRUE | H35: TRUE | I35: TRUE | J35: FALSE | K35: =REPT("|||||||||||||||||||||||",COUNTIF(G35:J35,TRUE)) -> ||||||||||||||||||||||||||||||||||||||||||||||||||||||||||||||||||||| | L35: =TEXT(COUNTIF(G35:J35,TRUE)/COLUMNS(G35:J35),"0%") -> 75% | M35: 45945 | N35: 698763 | O35: 698763 | P35: =IFERROR(O35/N35,0) -> 1 | Q35: =IFERROR(N35-O35,0) -> 0 | R35: =IFERROR(Q35/N35,0) -> 0 | S35: Pending Load (Awaiting Ship-To Data)
A36: 35 | B36: SMS SFDC | C36: Master Data | D36: SMS - Location | E36: Onity NA | G36: TRUE | H36: TRUE | I36: TRUE | J36: TRUE | K36: =REPT("|||||||||||||||||||||||",COUNTIF(G36:J36,TRUE)) -> |||||||||||||||||||||||||||||||||||||||||||||||||||||||||||||||||||||||||||||||||||||||||||| | L36: =TEXT(COUNTIF(G36:J36,TRUE)/COLUMNS(G36:J36),"0%") -> 100% | M36: 45939 | N36: 12070 | O36: 12070 | P36: =IFERROR(O36/N36,0) -> 1 | Q36: =IFERROR(N36-O36,0) -> 0 | R36: =IFERROR(Q36/N36,0) -> 0 | S36: Sudhanshu to load this from ERP
A37: 36 | B37: SMS SFDC | C37: Transactional Data | D37: Service Contract | E37: Onity EMEA | F37: Aberlardo / Sonia | G37: TRUE | H37: TRUE | I37: TRUE | J37: FALSE | K37: =REPT("|||||||||||||||||||||||",COUNTIF(G37:J37,TRUE)) -> ||||||||||||||||||||||||||||||||||||||||||||||||||||||||||||||||||||| | L37: =TEXT(COUNTIF(G37:J37,TRUE)/COLUMNS(G37:J37),"0%") -> 75% | M37: 45945 | N37: 289 | O37: 289 | P37: =IFERROR(O37/N37,0) -> 1 | Q37: 0 | R37: =IFERROR(Q37/N37,0) -> 0
A38: 37 | B38: SMS SFDC | C38: Master Data | D38: SMS - Service Resources (Subcontractors and internal) | E38: Onity EMEA | G38: TRUE | H38: TRUE | I38: TRUE | J38: FALSE | K38: =REPT("|||||||||||||||||||||||",COUNTIF(G38:J38,TRUE)) -> ||||||||||||||||||||||||||||||||||||||||||||||||||||||||||||||||||||| | L38: =TEXT(COUNTIF(G38:J38,TRUE)/COLUMNS(G38:J38),"0%") -> 75% | M38: 45945 | N38: 14 | O38: 14 | P38: =IFERROR(O38/N38,0) -> 1 | Q38: 0 | R38: =IFERROR(Q38/N38,0) -> 0
A39: 38 | B39: SMS SFDC | C39: Master Data | D39: SMS - Work Type Setup | E39: Onity EMEA | G39: TRUE | H39: TRUE | I39: TRUE | J39: FALSE | K39: =REPT("|||||||||||||||||||||||",COUNTIF(G39:J39,TRUE)) -> ||||||||||||||||||||||||||||||||||||||||||||||||||||||||||||||||||||| | L39: =TEXT(COUNTIF(G39:J39,TRUE)/COLUMNS(G39:J39),"0%") -> 75% | M39: 45945 | N39: 48 | O39: 48 | P39: =IFERROR(O39/N39,0) -> 1 | Q39: =IFERROR(N39-O39,0) -> 0 | R39: =IFERROR(Q39/N39,0) -> 0
A40: 39 | B40: SMS SFDC | C40: Master Data | D40: SMS - Service Territory | E40: Onity EMEA | G40: TRUE | H40: TRUE | I40: TRUE | J40: TRUE | K40: =REPT("|||||||||||||||||||||||",COUNTIF(G40:J40,TRUE)) -> |||||||||||||||||||||||||||||||||||||||||||||||||||||||||||||||||||||||||||||||||||||||||||| | L40: =TEXT(COUNTIF(G40:J40,TRUE)/COLUMNS(G40:J40),"0%") -> 100% | M40: 45945 | N40: 3 | O40: 3 | P40: =IFERROR(O40/N40,0) -> 1 | Q40: =IFERROR(N40-O40,0) -> 0 | R40: =IFERROR(Q40/N40,0) -> 0
A41: 40 | B41: SMS SFDC | C41: Master Data | D41: SMS - Profit Center | E41: Onity EMEA | G41: TRUE | H41: TRUE | I41: TRUE | J41: TRUE | K41: =REPT("|||||||||||||||||||||||",COUNTIF(G41:J41,TRUE)) -> |||||||||||||||||||||||||||||||||||||||||||||||||||||||||||||||||||||||||||||||||||||||||||| | L41: =TEXT(COUNTIF(G41:J41,TRUE)/COLUMNS(G41:J41),"0%") -> 100% | M41: 45945 | N41: 8 | O41: 8 | P41: =IFERROR(O41/N41,0) -> 1 | Q41: =IFERROR(N41-O41,0) -> 0 | R41: =IFERROR(Q41/N41,0) -> 0
A42: 41 | B42: SMS SFDC | C42: Master Data | D42: SMS - Service Resource Setup | E42: Onity EMEA | G42: TRUE | H42: TRUE | I42: TRUE | J42: TRUE | K42: =REPT("|||||||||||||||||||||||",COUNTIF(G42:J42,TRUE)) -> |||||||||||||||||||||||||||||||||||||||||||||||||||||||||||||||||||||||||||||||||||||||||||| | L42: =TEXT(COUNTIF(G42:J42,TRUE)/COLUMNS(G42:J42),"0%") -> 100% | M42: 45945 | N42: 14 | O42: 14 | P42: =IFERROR(O42/N42,0) -> 1 | Q42: 0 | R42: =IFERROR(Q42/N42,0) -> 0
A43: 42 | B43: SMS SFDC | C43: Master Data | D43: SMS - Asset | E43: Onity EMEA | G43: TRUE | H43: TRUE | I43: TRUE | J43: FALSE | K43: =REPT("|||||||||||||||||||||||",COUNTIF(G43:J43,TRUE)) -> ||||||||||||||||||||||||||||||||||||||||||||||||||||||||||||||||||||| | L43: =TEXT(COUNTIF(G43:J43,TRUE)/COLUMNS(G43:J43),"0%") -> 75% | M43: 45945 | N43: 29734 | O43: 471 | P43: =IFERROR(O43/N43,0) -> 0.015840452 | Q43: =IFERROR(N43-O43,0) -> 29263 | R43: =IFERROR(Q43/N43,0) -> 0.98415955 | S43: Pending Load (Awaiting Ship-To Data)
A44: 43 | B44: SMS SFDC | C44: Master Data | D44: SMS - Location | E44: Onity EMEA | G44: TRUE | H44: TRUE | I44: TRUE | J44: FALSE | K44: =REPT("|||||||||||||||||||||||",COUNTIF(G44:J44,TRUE)) -> ||||||||||||||||||||||||||||||||||||||||||||||||||||||||||||||||||||| | L44: =TEXT(COUNTIF(G44:J44,TRUE)/COLUMNS(G44:J44),"0%") -> 75% | M44: 45945 | N44: 7351 | O44: 7351 | P44: =IFERROR(O44/N44,0) -> 1 | Q44: =IFERROR(N44-O44,0) -> 0 | R44: =IFERROR(Q44/N44,0) -> 0 | S44: Sudhanshu to load this from ERP
A45: 44 | B45: SMS SFDC | C45: Transactional Data | D45: SMS - Maintenance Plan | E45: Onity EMEA | G45: TRUE | H45: FALSE | I45: TRUE | J45: FALSE | K45: =REPT("|||||||||||||||||||||||",COUNTIF(G45:J45,TRUE)) -> |||||||||||||||||||||||||||||||||||||||||||||| | L45: =TEXT(COUNTIF(G45:J45,TRUE)/COLUMNS(G45:J45),"0%") -> 50% | M45: 45945 | N45: 289 | O45: 8 | P45: =IFERROR(O45/N45,0) -> 0.027681661 | Q45: =IFERROR(N45-O45,0) -> 281 | R45: =IFERROR(Q45/N45,0) -> 0.97231834 | S45: Chrisitine to work with Abe
A46: 45 | B46: SMS SFDC | C46: Transactional Data | D46: SMS - Maintenance Asset | E46: Onity EMEA | G46: TRUE | H46: FALSE | I46: TRUE | J46: FALSE | K46: =REPT("|||||||||||||||||||||||",COUNTIF(G46:J46,TRUE)) -> |||||||||||||||||||||||||||||||||||||||||||||| | L46: =TEXT(COUNTIF(G46:J46,TRUE)/COLUMNS(G46:J46),"0%") -> 50% | M46: 45945 | N46: 728 | O46: 28 | P46: =IFERROR(O46/N46,0) -> 0.038461538 | Q46: =IFERROR(N46-O46,0) -> 700 | R46: =IFERROR(Q46/N46,0) -> 0.96153846 | S46: Chrisitine to work with Abe
A47: 46 | B47: SMS SFDC | C47: Transactional Data | D47: SMS - CLI | E47: Onity EMEA | G47: TRUE | H47: FALSE | I47: TRUE | J47: FALSE | K47: =REPT("|||||||||||||||||||||||",COUNTIF(G47:J47,TRUE)) -> |||||||||||||||||||||||||||||||||||||||||||||| | L47: =TEXT(COUNTIF(G47:J47,TRUE)/COLUMNS(G47:J47),"0%") -> 50% | M47: 45945 | N47: 728 | O47: 28 | P47: =IFERROR(O47/N47,0) -> 0.038461538 | Q47: =IFERROR(N47-O47,0) -> 700 | R47: =IFERROR(Q47/N47,0) -> 0.96153846 | S47: Chrisitine to work with Abe
A48: 47 | B48: SMS SFDC | C48: Transactional Data | D48: SMS - Work Order | E48: Onity EMEA | G48: TRUE | H48: TRUE | I48: TRUE | J48: FALSE | K48: =REPT("|||||||||||||||||||||||",COUNTIF(G48:J48,TRUE)) -> ||||||||||||||||||||||||||||||||||||||||||||||||||||||||||||||||||||| | L48: =TEXT(COUNTIF(G48:J48,TRUE)/COLUMNS(G48:J48),"0%") -> 75% | M48: 45945 | N48: 48 | O48: 48 | P48: =IFERROR(O48/N48,0) -> 1 | Q48: =IFERROR(N48-O48,0) -> 0 | R48: =IFERROR(Q48/N48,0) -> 0
A49: 48 | B49: CPQ | C49: Master Data | D49: Price | E49: Onity NA | F49: Nicole Shedd Piorno Abelardo Sonia Estrada | G49: TRUE | H49: TRUE | I49: TRUE | J49: TRUE | K49: =REPT("|||||||||||||||||||||||",COUNTIF(G49:J49,TRUE)) -> |||||||||||||||||||||||||||||||||||||||||||||||||||||||||||||||||||||||||||||||||||||||||||| | L49: =TEXT(COUNTIF(G49:J49,TRUE)/COLUMNS(G49:J49),"0%") -> 100% | M49: 45940 | N49: 4365 | O49: 4365 | P49: =IFERROR(O49/N49,0) -> 1 | Q49: =IFERROR(N49-O49,0) -> 0 | R49: =IFERROR(Q49/N49,0) -> 0 | S49: Product Price data looks good. Need to validate project pricing data.
A50: 49 | B50: CPQ | C50: Master Data | D50: Material | E50: Onity NA | G50: TRUE | H50: TRUE | I50: TRUE | J50: TRUE | K50: =REPT("|||||||||||||||||||||||",COUNTIF(G50:J50,TRUE)) -> |||||||||||||||||||||||||||||||||||||||||||||||||||||||||||||||||||||||||||||||||||||||||||| | L50: =TEXT(COUNTIF(G50:J50,TRUE)/COLUMNS(G50:J50),"0%") -> 100% | M50: 45939 | N50: 4365 | O50: 4365 | P50: =IFERROR(O50/N50,0) -> 1 | Q50: =IFERROR(N50-O50,0) -> 0 | R50: =IFERROR(Q50/N50,0) -> 0
A51: 50 | B51: CPQ | C51: Master Data | D51: Price | E51: Onity EMEA | G51: TRUE | H51: TRUE | I51: TRUE | J51: TRUE | K51: =REPT("|||||||||||||||||||||||",COUNTIF(G51:J51,TRUE)) -> |||||||||||||||||||||||||||||||||||||||||||||||||||||||||||||||||||||||||||||||||||||||||||| | L51: =TEXT(COUNTIF(G51:J51,TRUE)/COLUMNS(G51:J51),"0%") -> 100% | M51: 45943 | N51: 11138 | O51: 11138 | P51: =IFERROR(O51/N51,0) -> 1 | Q51: =IFERROR(N51-O51,0) -> 0 | R51: =IFERROR(Q51/N51,0) -> 0
A52: 51 | B52: CPQ | C52: Master Data | D52: Material | E52: Onity EMEA | G52: TRUE | H52: TRUE | I52: TRUE | J52: TRUE | K52: =REPT("|||||||||||||||||||||||",COUNTIF(G52:J52,TRUE)) -> |||||||||||||||||||||||||||||||||||||||||||||||||||||||||||||||||||||||||||||||||||||||||||| | L52: =TEXT(COUNTIF(G52:J52,TRUE)/COLUMNS(G52:J52),"0%") -> 100% | M52: 45943 | N52: 11138 | O52: 11138 | P52: =IFERROR(O52/N52,0) -> 1 | Q52: =IFERROR(N52-O52,0) -> 0 | R52: =IFERROR(Q52/N52,0) -> 0
A53: 52 | B53: CPQ | C53: Master Data | D53: Price | E53: Onity APAC | G53: TRUE | H53: TRUE | I53: TRUE | J53: TRUE | K53: =REPT("|||||||||||||||||||||||",COUNTIF(G53:J53,TRUE)) -> |||||||||||||||||||||||||||||||||||||||||||||||||||||||||||||||||||||||||||||||||||||||||||| | L53: =TEXT(COUNTIF(G53:J53,TRUE)/COLUMNS(G53:J53),"0%") -> 100% | M53: 45945 | N53: 16495 | O53: 16495 | P53: =IFERROR(O53/N53,0) -> 1 | Q53: =IFERROR(N53-O53,0) -> 0 | R53: =IFERROR(Q53/N53,0) -> 0
A54: 53 | B54: CPQ | C54: Master Data | D54: Material | E54: Onity APAC | G54: TRUE | H54: TRUE | I54: TRUE | J54: TRUE | K54: =REPT("|||||||||||||||||||||||",COUNTIF(G54:J54,TRUE)) -> |||||||||||||||||||||||||||||||||||||||||||||||||||||||||||||||||||||||||||||||||||||||||||| | L54: =TEXT(COUNTIF(G54:J54,TRUE)/COLUMNS(G54:J54),"0%") -> 100% | M54: 45945 | N54: 16495 | O54: 16495 | P54: =IFERROR(O54/N54,0) -> 1 | Q54: =IFERROR(N54-O54,0) -> 0 | R54: =IFERROR(Q54/N54,0) -> 0
A55: 54 | B55: CPQ | C55: Master Data | D55: Price | E55: Lenel APAC | G55: TRUE | H55: TRUE | I55: TRUE | J55: TRUE | K55: =REPT("|||||||||||||||||||||||",COUNTIF(G55:J55,TRUE)) -> |||||||||||||||||||||||||||||||||||||||||||||||||||||||||||||||||||||||||||||||||||||||||||| | L55: =TEXT(COUNTIF(G55:J55,TRUE)/COLUMNS(G55:J55),"0%") -> 100% | M55: 45945 | N55: 11607 | O55: 11607 | P55: =IFERROR(O55/N55,0) -> 1 | Q55: =IFERROR(N55-O55,0) -> 0 | R55: =IFERROR(Q55/N55,0) -> 0
A56: 55 | B56: CPQ | C56: Master Data | D56: Material | E56: Lenel APAC | G56: TRUE | H56: TRUE | I56: TRUE | J56: TRUE | K56: =REPT("|||||||||||||||||||||||",COUNTIF(G56:J56,TRUE)) -> |||||||||||||||||||||||||||||||||||||||||||||||||||||||||||||||||||||||||||||||||||||||||||| | L56: =TEXT(COUNTIF(G56:J56,TRUE)/COLUMNS(G56:J56),"0%") -> 100% | M56: 45932 | N56: 11607 | O56: 11607 | P56: =IFERROR(O56/N56,0) -> 1 | Q56: =IFERROR(N56-O56,0) -> 0 | R56: =IFERROR(Q56/N56,0) -> 0
A57: 56 | B57: eCommerce | C57: Master Data | D57: Account (Buying) | E57: Onity NA | F57: Nicole | G57: TRUE | H57: TRUE | I57: TRUE | J57: TRUE | K57: =REPT("|||||||||||||||||||||||",COUNTIF(G57:J57,TRUE)) -> |||||||||||||||||||||||||||||||||||||||||||||||||||||||||||||||||||||||||||||||||||||||||||| | L57: =TEXT(COUNTIF(G57:J57,TRUE)/COLUMNS(G57:J57),"0%") -> 100% | M57: 45940 | N57: 19856 | O57: 19856 | P57: =IFERROR(O57/N57,0) -> 1 | Q57: 0 | R57: =IFERROR(Q57/N57,0) -> 0
A58: 57 | B58: eCommerce | C58: Master Data | D58: Material | E58: Onity NA | G58: TRUE | H58: TRUE | I58: TRUE | J58: TRUE | K58: =REPT("|||||||||||||||||||||||",COUNTIF(G58:J58,TRUE)) -> |||||||||||||||||||||||||||||||||||||||||||||||||||||||||||||||||||||||||||||||||||||||||||| | L58: =TEXT(COUNTIF(G58:J58,TRUE)/COLUMNS(G58:J58),"0%") -> 100% | M58: 45940 | N58: 1806 | O58: 1526 | P58: =IFERROR(O58/N58,0) -> 0.84496124 | Q58: 0 | R58: =IFERROR(Q58/N58,0) -> 0 | S58: 62 records have Price & Channel status issue
A59: 58 | B59: eCommerce | C59: Master Data | D59: Price | E59: Onity NA | G59: TRUE | H59: TRUE | I59: TRUE | J59: TRUE | K59: =REPT("|||||||||||||||||||||||",COUNTIF(G59:J59,TRUE)) -> |||||||||||||||||||||||||||||||||||||||||||||||||||||||||||||||||||||||||||||||||||||||||||| | L59: =TEXT(COUNTIF(G59:J59,TRUE)/COLUMNS(G59:J59),"0%") -> 100% | M59: 45940 | N59: 1806 | O59: =1526-38 -> 1488 | P59: =IFERROR(O59/N59,0) -> 0.82392027 | Q59: 0 | R59: =IFERROR(Q59/N59,0) -> 0
A60: 59 | B60: AEM | C60: Master Data | D60: Material | E60: Onity NA | G60: TRUE | H60: TRUE | I60: TRUE | J60: TRUE | K60: =REPT("|||||||||||||||||||||||",COUNTIF(G60:J60,TRUE)) -> |||||||||||||||||||||||||||||||||||||||||||||||||||||||||||||||||||||||||||||||||||||||||||| | L60: =TEXT(COUNTIF(G60:J60,TRUE)/COLUMNS(G60:J60),"0%") -> 100% | M60: 45940 | N60: 1806 | O60: 1526 | P60: =IFERROR(O60/N60,0) -> 0.84496124 | Q60: 0 | R60: =IFERROR(Q60/N60,0) -> 0
A61: 60 | B61: Zuora | C61: Master Data | D61: Account (Buying) | E61: Onity APAC | F61: Nicole Shedd Piorno Abelardo Sonia Estrada | G61: TRUE | H61: TRUE | I61: TRUE | J61: TRUE | K61: =REPT("|||||||||||||||||||||||",COUNTIF(G61:J61,TRUE)) -> |||||||||||||||||||||||||||||||||||||||||||||||||||||||||||||||||||||||||||||||||||||||||||| | L61: =TEXT(COUNTIF(G61:J61,TRUE)/COLUMNS(G61:J61),"0%") -> 100% | M61: 45945 | N61: 4240 | O61: 4221 | P61: =IFERROR(O61/N61,0) -> 0.99551887 | Q61: =IFERROR(N61-O61,0) -> 19 | R61: =IFERROR(Q61/N61,0) -> 0.0044811321 | S61: 10/10 : Updated success count in both Expected & loaded, Confirmed and validated with ETL Team
A62: 61 | B62: Zuora | C62: Master Data | D62: Account (Buying) | E62: Onity NA | G62: TRUE | H62: TRUE | I62: TRUE | J62: TRUE | K62: =REPT("|||||||||||||||||||||||",COUNTIF(G62:J62,TRUE)) -> |||||||||||||||||||||||||||||||||||||||||||||||||||||||||||||||||||||||||||||||||||||||||||| | L62: =TEXT(COUNTIF(G62:J62,TRUE)/COLUMNS(G62:J62),"0%") -> 100% | M62: 45940 | N62: 19414 | O62: 19350 | P62: =IFERROR(O62/N62,0) -> 0.99670341 | Q62: =IFERROR(N62-O62,0) -> 64 | R62: =IFERROR(Q62/N62,0) -> 0.0032965901
A63: 62 | B63: Zuora | C63: Master Data | D63: Account (Buying) | E63: Onity EMEA | G63: TRUE | H63: TRUE | I63: TRUE | J63: TRUE | K63: =REPT("|||||||||||||||||||||||",COUNTIF(G63:J63,TRUE)) -> |||||||||||||||||||||||||||||||||||||||||||||||||||||||||||||||||||||||||||||||||||||||||||| | L63: =TEXT(COUNTIF(G63:J63,TRUE)/COLUMNS(G63:J63),"0%") -> 100% | M63: 45943 | N63: 16451 | O63: 16314 | P63: =IFERROR(O63/N63,0) -> 0.99167224 | Q63: =IFERROR(N63-O63,0) -> 137 | R63: =IFERROR(Q63/N63,0) -> 0.0083277612 | S63: 10/10 : ~220 records in Exception
A64: 63 | B64: Zuora | C64: Master Data | D64: Product | E64: Onity APAC | G64: TRUE | H64: TRUE | I64: TRUE | J64: TRUE | K64: =REPT("|||||||||||||||||||||||",COUNTIF(G64:J64,TRUE)) -> |||||||||||||||||||||||||||||||||||||||||||||||||||||||||||||||||||||||||||||||||||||||||||| | L64: =TEXT(COUNTIF(G64:J64,TRUE)/COLUMNS(G64:J64),"0%") -> 100% | M64: 45945 | N64: 19 | O64: 19 | P64: =IFERROR(O64/N64,0) -> 1 | Q64: =IFERROR(N64-O64,0) -> 0 | R64: =IFERROR(Q64/N64,0) -> 0 | S64: Exceptions Observation : 1]malformed payload due to double quotes in city , address 2] empty currency from SAP 3] invalid email ids from SAP
A65: 64 | B65: Zuora | C65: Master Data | D65: Product | E65: Onity NA | G65: TRUE | H65: TRUE | I65: TRUE | J65: TRUE | K65: =REPT("|||||||||||||||||||||||",COUNTIF(G65:J65,TRUE)) -> |||||||||||||||||||||||||||||||||||||||||||||||||||||||||||||||||||||||||||||||||||||||||||| | L65: =TEXT(COUNTIF(G65:J65,TRUE)/COLUMNS(G65:J65),"0%") -> 100% | M65: 45940 | N65: 19 | O65: 19 | P65: =IFERROR(O65/N65,0) -> 1 | Q65: =IFERROR(N65-O65,0) -> 0 | R65: =IFERROR(Q65/N65,0) -> 0
A66: 65 | B66: Zuora | C66: Master Data | D66: Product | E66: Onity EMEA | G66: TRUE | H66: TRUE | I66: TRUE | J66: TRUE | K66: =REPT("|||||||||||||||||||||||",COUNTIF(G66:J66,TRUE)) -> |||||||||||||||||||||||||||||||||||||||||||||||||||||||||||||||||||||||||||||||||||||||||||| | L66: =TEXT(COUNTIF(G66:J66,TRUE)/COLUMNS(G66:J66),"0%") -> 100% | M66: 45943 | N66: 19 | O66: 19 | P66: =IFERROR(O66/N66,0) -> 1 | Q66: =IFERROR(N66-O66,0) -> 0 | R66: =IFERROR(Q66/N66,0) -> 0
A67: 66 | B67: Pros | C67: Master Data | D67: Material/Product | E67: Lenel APAC | F67: Nicole Piorno Abelardo Sonia Estrada | G67: TRUE | H67: TRUE | I67: TRUE | J67: TRUE | K67: =REPT("|||||||||||||||||||||||",COUNTIF(G67:J67,TRUE)) -> |||||||||||||||||||||||||||||||||||||||||||||||||||||||||||||||||||||||||||||||||||||||||||| | L67: =TEXT(COUNTIF(G67:J67,TRUE)/COLUMNS(G67:J67),"0%") -> 100% | M67: 45945 | N67: 1623 | O67: 1623 | P67: =IFERROR(O67/N67,0) -> 1 | Q67: =IFERROR(N67-O67,0) -> 0 | R67: =IFERROR(Q67/N67,0) -> 0
A68: 67 | B68: Pros | C68: Master Data | D68: Price | E68: Lenel APAC | G68: TRUE | H68: TRUE | I68: TRUE | J68: TRUE | K68: =REPT("|||||||||||||||||||||||",COUNTIF(G68:J68,TRUE)) -> |||||||||||||||||||||||||||||||||||||||||||||||||||||||||||||||||||||||||||||||||||||||||||| | L68: =TEXT(COUNTIF(G68:J68,TRUE)/COLUMNS(G68:J68),"0%") -> 100% | M68: 45945 | N68: 2270 | O68: 2270 | P68: =IFERROR(O68/N68,0) -> 1 | Q68: =IFERROR(N68-O68,0) -> 0 | R68: =IFERROR(Q68/N68,0) -> 0
A69: 68 | B69: Pros | C69: Master Data | D69: Material/Product | E69: Onity NA | G69: TRUE | H69: TRUE | I69: TRUE | J69: TRUE | K69: =REPT("|||||||||||||||||||||||",COUNTIF(G69:J69,TRUE)) -> |||||||||||||||||||||||||||||||||||||||||||||||||||||||||||||||||||||||||||||||||||||||||||| | L69: =TEXT(COUNTIF(G69:J69,TRUE)/COLUMNS(G69:J69),"0%") -> 100% | M69: 45939 | N69: 5153 | O69: 5153 | P69: =IFERROR(O69/N69,0) -> 1 | Q69: =IFERROR(N69-O69,0) -> 0 | R69: =IFERROR(Q69/N69,0) -> 0 | S69: Brain validated pricing and materials as Nicole is OOO
A70: 69 | B70: Pros | C70: Master Data | D70: Price | E70: Onity NA | G70: TRUE | H70: TRUE | I70: TRUE | J70: TRUE | K70: =REPT("|||||||||||||||||||||||",COUNTIF(G70:J70,TRUE)) -> |||||||||||||||||||||||||||||||||||||||||||||||||||||||||||||||||||||||||||||||||||||||||||| | L70: =TEXT(COUNTIF(G70:J70,TRUE)/COLUMNS(G70:J70),"0%") -> 100% | M70: 45939 | N70: 5153 | O70: 5153 | P70: =IFERROR(O70/N70,0) -> 1 | Q70: =IFERROR(N70-O70,0) -> 0 | R70: =IFERROR(Q70/N70,0) -> 0 | S70: Brain validated pricing and materials as Nicole is OOO
A71: 70 | B71: Pros | C71: Master Data | D71: Material/Product | E71: Onity EMEA | G71: TRUE | H71: TRUE | I71: TRUE | J71: TRUE | K71: =REPT("|||||||||||||||||||||||",COUNTIF(G71:J71,TRUE)) -> |||||||||||||||||||||||||||||||||||||||||||||||||||||||||||||||||||||||||||||||||||||||||||| | L71: =TEXT(COUNTIF(G71:J71,TRUE)/COLUMNS(G71:J71),"0%") -> 100% | M71: 45943 | N71: 2632 | O71: 2632 | P71: =IFERROR(O71/N71,0) -> 1 | Q71: =IFERROR(N71-O71,0) -> 0 | R71: =IFERROR(Q71/N71,0) -> 0
A72: 71 | B72: Pros | C72: Master Data | D72: Price | E72: Onity EMEA | G72: TRUE | H72: TRUE | I72: TRUE | J72: TRUE | K72: =REPT("|||||||||||||||||||||||",COUNTIF(G72:J72,TRUE)) -> |||||||||||||||||||||||||||||||||||||||||||||||||||||||||||||||||||||||||||||||||||||||||||| | L72: =TEXT(COUNTIF(G72:J72,TRUE)/COLUMNS(G72:J72),"0%") -> 100% | M72: 45943 | N72: 34364 | O72: 34364 | P72: =IFERROR(O72/N72,0) -> 1 | Q72: =IFERROR(N72-O72,0) -> 0 | R72: =IFERROR(Q72/N72,0) -> 0
A73: 72 | B73: Pros | C73: Master Data | D73: Material/Product | E73: Onity APAC | G73: TRUE | H73: TRUE | I73: TRUE | J73: TRUE | K73: =REPT("|||||||||||||||||||||||",COUNTIF(G73:J73,TRUE)) -> |||||||||||||||||||||||||||||||||||||||||||||||||||||||||||||||||||||||||||||||||||||||||||| | L73: =TEXT(COUNTIF(G73:J73,TRUE)/COLUMNS(G73:J73),"0%") -> 100% | M73: 45945 | N73: 1623 | O73: 1623 | P73: =IFERROR(O73/N73,0) -> 1 | Q73: =IFERROR(N73-O73,0) -> 0 | R73: =IFERROR(Q73/N73,0) -> 0
A74: 73 | B74: Pros | C74: Master Data | D74: Price | E74: Onity APAC | G74: TRUE | H74: TRUE | I74: TRUE | J74: TRUE | K74: =REPT("|||||||||||||||||||||||",COUNTIF(G74:J74,TRUE)) -> |||||||||||||||||||||||||||||||||||||||||||||||||||||||||||||||||||||||||||||||||||||||||||| | L74: =TEXT(COUNTIF(G74:J74,TRUE)/COLUMNS(G74:J74),"0%") -> 100% | M74: 45945 | N74: 2270 | O74: 2270 | P74: =IFERROR(O74/N74,0) -> 1 | Q74: =IFERROR(N74-O74,0) -> 0 | R74: =IFERROR(Q74/N74,0) -> 0
A75: 74 | B75: Portal | C75: Master Data | D75: Account (Buying) | E75: Onity NA | F75: Anne Kelly - CS | G75: TRUE | H75: TRUE | I75: TRUE | J75: TRUE | K75: =REPT("|||||||||||||||||||||||",COUNTIF(G75:J75,TRUE)) -> |||||||||||||||||||||||||||||||||||||||||||||||||||||||||||||||||||||||||||||||||||||||||||| | L75: =TEXT(COUNTIF(G75:J75,TRUE)/COLUMNS(G75:J75),"0%") -> 100% | M75: 45940 | N75: 19856 | O75: 19856 | P75: =IFERROR(O75/N75,0) -> 1 | Q75: 0 | R75: =IFERROR(Q75/N75,0) -> 0
A76: 75 | B76: Portal | C76: Master Data | D76: Contact | E76: Onity NA | G76: TRUE | H76: TRUE | I76: TRUE | J76: TRUE | K76: =REPT("|||||||||||||||||||||||",COUNTIF(G76:J76,TRUE)) -> |||||||||||||||||||||||||||||||||||||||||||||||||||||||||||||||||||||||||||||||||||||||||||| | L76: =TEXT(COUNTIF(G76:J76,TRUE)/COLUMNS(G76:J76),"0%") -> 100% | M76: 45940 | N76: 8 | O76: 8 | P76: =IFERROR(O76/N76,0) -> 1 | Q76: 0 | R76: =IFERROR(Q76/N76,0) -> 0
A77: 76 | B77: Portal | C77: Master Data | D77: Contact (Portal) - WPHID | E77: Onity NA | G77: TRUE | H77: TRUE | I77: TRUE | J77: TRUE | K77: =REPT("|||||||||||||||||||||||",COUNTIF(G77:J77,TRUE)) -> |||||||||||||||||||||||||||||||||||||||||||||||||||||||||||||||||||||||||||||||||||||||||||| | L77: =TEXT(COUNTIF(G77:J77,TRUE)/COLUMNS(G77:J77),"0%") -> 100% | M77: 45940 | N77: 8 | O77: 8 | P77: =IFERROR(O77/N77,0) -> 1 | Q77: 0 | R77: =IFERROR(Q77/N77,0) -> 0
A78: 77 | B78: Portal | C78: Master Data | D78: Contact (Portal) - PURID | E78: Onity NA | G78: TRUE | H78: TRUE | I78: TRUE | J78: TRUE | K78: =REPT("|||||||||||||||||||||||",COUNTIF(G78:J78,TRUE)) -> |||||||||||||||||||||||||||||||||||||||||||||||||||||||||||||||||||||||||||||||||||||||||||| | L78: =TEXT(COUNTIF(G78:J78,TRUE)/COLUMNS(G78:J78),"0%") -> 100% | M78: 45940 | N78: 8 | O78: 8 | P78: =IFERROR(O78/N78,0) -> 1 | Q78: 0 | R78: =IFERROR(Q78/N78,0) -> 0
A79: 78 | B79: Portal | C79: Master Data | D79: Material/Product | E79: Onity NA | G79: TRUE | H79: TRUE | I79: TRUE | J79: TRUE | K79: =REPT("|||||||||||||||||||||||",COUNTIF(G79:J79,TRUE)) -> |||||||||||||||||||||||||||||||||||||||||||||||||||||||||||||||||||||||||||||||||||||||||||| | L79: =TEXT(COUNTIF(G79:J79,TRUE)/COLUMNS(G79:J79),"0%") -> 100% | M79: 45940 | N79: 1525 | O79: 1463 | P79: =IFERROR(O79/N79,0) -> 0.95934426 | Q79: 0 | R79: =IFERROR(Q79/N79,0) -> 0 | S79: This is the ETL Job from ERP to AEM for Marketing information.
A80: 79 | B80: Portal | C80: Transactional Data | D80: Orders | E80: Onity NA | G80: TRUE | H80: TRUE | I80: TRUE | J80: FALSE | K80: =REPT("|||||||||||||||||||||||",COUNTIF(G80:J80,TRUE)) -> ||||||||||||||||||||||||||||||||||||||||||||||||||||||||||||||||||||| | L80: =TEXT(COUNTIF(G80:J80,TRUE)/COLUMNS(G80:J80),"0%") -> 75% | M80: 45944 | N80: 3259 | O80: 3259 | P80: =IFERROR(O80/N80,0) -> 1 | Q80: =IFERROR(N80-O80,0) -> 0 | R80: =IFERROR(Q80/N80,0) -> 0 | S80: Sunny will cross check with SAP team on count discrepency
A81: 80 | B81: ELMS | C81: Master Data | D81: Material/Product | E81: Lenel APAC | F81: John H Debora Simson | G81: TRUE | H81: TRUE | I81: TRUE | J81: TRUE | K81: =REPT("|||||||||||||||||||||||",COUNTIF(G81:J81,TRUE)) -> |||||||||||||||||||||||||||||||||||||||||||||||||||||||||||||||||||||||||||||||||||||||||||| | L81: =TEXT(COUNTIF(G81:J81,TRUE)/COLUMNS(G81:J81),"0%") -> 100% | M81: 45944 | N81: 17 | O81: 17 | P81: =IFERROR(O81/N81,0) -> 1 | Q81: =IFERROR(N81-O81,0) -> 0 | R81: =IFERROR(Q81/N81,0) -> 0
A82: 81 | B82: ELMS | C82: Master Data | D82: Price | E82: Lenel APAC | G82: TRUE | H82: TRUE | I82: TRUE | J82: TRUE | K82: =REPT("|||||||||||||||||||||||",COUNTIF(G82:J82,TRUE)) -> |||||||||||||||||||||||||||||||||||||||||||||||||||||||||||||||||||||||||||||||||||||||||||| | L82: =TEXT(COUNTIF(G82:J82,TRUE)/COLUMNS(G82:J82),"0%") -> 100% | M82: 45944 | N82: 17 | O82: 11 | P82: =IFERROR(O82/N82,0) -> 0.64705882 | Q82: =IFERROR(N82-O82,0) -> 6 | R82: =IFERROR(Q82/N82,0) -> 0.35294118
A83: 82 | B83: ELMS | C83: Master Data | D83: Contact (Portal) | E83: Lenel APAC | G83: TRUE | H83: TRUE | I83: TRUE | J83: TRUE | K83: =REPT("|||||||||||||||||||||||",COUNTIF(G83:J83,TRUE)) -> |||||||||||||||||||||||||||||||||||||||||||||||||||||||||||||||||||||||||||||||||||||||||||| | L83: =TEXT(COUNTIF(G83:J83,TRUE)/COLUMNS(G83:J83),"0%") -> 100% | M83: 45944 | N83: 19 | O83: 19 | P83: =IFERROR(O83/N83,0) -> 1 | Q83: =IFERROR(N83-O83,0) -> 0 | R83: =IFERROR(Q83/N83,0) -> 0
A84: 83 | B84: Contact Center | C84: Master Data | D84: Contacts | E84: GDM SFDC | F84: Anne Kelly | G84: TRUE | H84: TRUE | I84: TRUE | J84: TRUE | K84: =REPT("|||||||||||||||||||||||",COUNTIF(G84:J84,TRUE)) -> |||||||||||||||||||||||||||||||||||||||||||||||||||||||||||||||||||||||||||||||||||||||||||| | L84: =TEXT(COUNTIF(G84:J84,TRUE)/COLUMNS(G84:J84),"0%") -> 100% | M84: 45919 | N84: 124402 | O84: 124402 | P84: =IFERROR(O84/N84,0) -> 1 | Q84: =IFERROR(N84-O84,0) -> 0 | R84: =IFERROR(Q84/N84,0) -> 0

Sheet CCEX Data Score Card - Prod
A1: S.No | B1: System | C1: Data Object Type | D1: Data Object | E1: Region | F1: Business Focal | G1: Identify CDE | H1: Prep Data | I1: Load | J1: Validation | K1: Status % | L1: Progress | M1: ETA for Load | N1: Expected Records (PROD) | O1: Loaded Records (PROD) | P1: % Loaded (PROD) | Q1: Missed Records (PROD) | R1: % Problem (PROD | S1: Remarks / Comments during PROD
A2: 1 | B2: Salesforce | C2: Master Data | D2: Account (Buying) | E2: Onity NA | F2: Brian Bevins - Sales, Anne Kelly - CS Chris Taylor - TC | G2: TRUE | H2: TRUE | I2: TRUE | J2: TRUE | K2: =REPT("|||||||||||||||||||||||",COUNTIF(G2:J2,TRUE)) -> |||||||||||||||||||||||||||||||||||||||||||||||||||||||||||||||||||||||||||||||||||||||||||| | L2: =TEXT(COUNTIF(G2:J2,TRUE)/COLUMNS(G2:J2),"0%") -> 100% | M2: 45938 | N2: 36574 | O2: 36574 | P2: =IFERROR(O2/N2,0) -> 1 | Q2: =N2-(IF(ISBLANK(O2),N2,O2)) -> 0 | R2: =IFERROR(Q2/N2,0) -> 0
A3: 2 | B3: Salesforce | C3: Master Data | D3: Account (Non-Buying) | E3: Onity NA | G3: TRUE | H3: TRUE | I3: TRUE | J3: TRUE | K3: =REPT("|||||||||||||||||||||||",COUNTIF(G3:J3,TRUE)) -> |||||||||||||||||||||||||||||||||||||||||||||||||||||||||||||||||||||||||||||||||||||||||||| | L3: =TEXT(COUNTIF(G3:J3,TRUE)/COLUMNS(G3:J3),"0%") -> 100% | M3: 45954 | N3: 112614 | O3: 112614 | P3: =IFERROR(O3/N3,0) -> 1 | Q3: =N3-(IF(ISBLANK(O3),N3,O3)) -> 0 | R3: =IFERROR(Q3/N3,0) -> 0
A4: 3 | B4: Salesforce | C4: Master Data | D4: Contact | E4: Onity NA | G4: TRUE | H4: TRUE | I4: TRUE | J4: TRUE | K4: =REPT("|||||||||||||||||||||||",COUNTIF(G4:J4,TRUE)) -> |||||||||||||||||||||||||||||||||||||||||||||||||||||||||||||||||||||||||||||||||||||||||||| | L4: =TEXT(COUNTIF(G4:J4,TRUE)/COLUMNS(G4:J4),"0%") -> 100% | M4: 45958 | N4: 153580 | O4: 153580 | P4: =IFERROR(O4/N4,0) -> 1 | Q4: =N4-(IF(ISBLANK(O4),N4,O4)) -> 0 | R4: =IFERROR(Q4/N4,0) -> 0 | S4: 40727 (duplicate)
A5: 4 | B5: Salesforce | C5: Master Data | D5: Product | E5: Onity NA | G5: TRUE | H5: TRUE | I5: TRUE | J5: TRUE | K5: =REPT("|||||||||||||||||||||||",COUNTIF(G5:J5,TRUE)) -> |||||||||||||||||||||||||||||||||||||||||||||||||||||||||||||||||||||||||||||||||||||||||||| | L5: =TEXT(COUNTIF(G5:J5,TRUE)/COLUMNS(G5:J5),"0%") -> 100% | M5: 45938 | N5: 6094 | O5: 6094 | P5: =IFERROR(O5/N5,0) -> 1 | Q5: =N5-(IF(ISBLANK(O5),N5,O5)) -> 0 | R5: =IFERROR(Q5/N5,0) -> 0 | S5: 1 product and 4 prices are not correct with data validated.
A6: 5 | B6: Salesforce | C6: Transactional Data | D6: Opportunity | E6: Onity NA | G6: TRUE | H6: TRUE | I6: TRUE | J6: TRUE | K6: =REPT("|||||||||||||||||||||||",COUNTIF(G6:J6,TRUE)) -> |||||||||||||||||||||||||||||||||||||||||||||||||||||||||||||||||||||||||||||||||||||||||||| | L6: =TEXT(COUNTIF(G6:J6,TRUE)/COLUMNS(G6:J6),"0%") -> 100% | M6: 45963 | N6: 13665 | O6: 13665 | P6: =IFERROR(O6/N6,0) -> 1 | Q6: =N6-(IF(ISBLANK(O6),N6,O6)) -> 0 | R6: =IFERROR(Q6/N6,0) -> 0
A7: 6 | B7: Salesforce | C7: Transactional Data | D7: Lead | E7: Onity NA | G7: TRUE | H7: TRUE | I7: TRUE | J7: TRUE | K7: =REPT("|||||||||||||||||||||||",COUNTIF(G7:J7,TRUE)) -> |||||||||||||||||||||||||||||||||||||||||||||||||||||||||||||||||||||||||||||||||||||||||||| | L7: =TEXT(COUNTIF(G7:J7,TRUE)/COLUMNS(G7:J7),"0%") -> 100% | M7: 45962 | N7: 352 | O7: 352 | P7: =IFERROR(O7/N7,0) -> 1 | Q7: =N7-(IF(ISBLANK(O7),N7,O7)) -> 0 | R7: =IFERROR(Q7/N7,0) -> 0
A8: 7 | B8: Salesforce | C8: Transactional Data | D8: Contract | E8: Onity NA | G8: TRUE | H8: TRUE | I8: TRUE | J8: TRUE | K8: =REPT("|||||||||||||||||||||||",COUNTIF(G8:J8,TRUE)) -> |||||||||||||||||||||||||||||||||||||||||||||||||||||||||||||||||||||||||||||||||||||||||||| | L8: =TEXT(COUNTIF(G8:J8,TRUE)/COLUMNS(G8:J8),"0%") -> 100% | M8: 45969 | N8: 5904 | O8: 5836 | P8: =IFERROR(O8/N8,0) -> 0.98848238 | Q8: =N8-(IF(ISBLANK(O8),N8,O8)) -> 68 | R8: =IFERROR(Q8/N8,0) -> 0.011517615
A9: 8 | B9: Salesforce | C9: Transactional Data | D9: Case | E9: Onity NA | G9: TRUE | H9: TRUE | I9: TRUE | J9: TRUE | K9: =REPT("|||||||||||||||||||||||",COUNTIF(G9:J9,TRUE)) -> |||||||||||||||||||||||||||||||||||||||||||||||||||||||||||||||||||||||||||||||||||||||||||| | L9: =TEXT(COUNTIF(G9:J9,TRUE)/COLUMNS(G9:J9),"0%") -> 100% | M9: 45962 | N9: 100979 | O9: 100979 | P9: =IFERROR(O9/N9,0) -> 1 | Q9: =N9-(IF(ISBLANK(O9),N9,O9)) -> 0 | R9: =IFERROR(Q9/N9,0) -> 0 | S9: child cases getting created.
A10: 9 | B10: Salesforce | C10: Transactional Data | D10: Knowledge Articles | E10: Onity NA | G10: TRUE | H10: TRUE | I10: TRUE | J10: TRUE | K10: =REPT("|||||||||||||||||||||||",COUNTIF(G10:J10,TRUE)) -> |||||||||||||||||||||||||||||||||||||||||||||||||||||||||||||||||||||||||||||||||||||||||||| | L10: =TEXT(COUNTIF(G10:J10,TRUE)/COLUMNS(G10:J10),"0%") -> 100% | M10: 45964 | N10: 345 | O10: 345 | P10: =IFERROR(O10/N10,0) -> 1 | Q10: =N10-(IF(ISBLANK(O10),N10,O10)) -> 0 | R10: =IFERROR(Q10/N10,0) -> 0 | S10: Don't have the catagories brought over from BTFull and that they were all still in draft form becuase the pictures / attachments hadnt migrated over yet.
A11: 10 | B11: Salesforce | C11: Master Data | D11: Account (Buying) | E11: Onity EMEA | F11: Piorno Abelardo Sonia Estrada | G11: TRUE | H11: TRUE | I11: TRUE | J11: TRUE | K11: =REPT("|||||||||||||||||||||||",COUNTIF(G11:J11,TRUE)) -> |||||||||||||||||||||||||||||||||||||||||||||||||||||||||||||||||||||||||||||||||||||||||||| | L11: =TEXT(COUNTIF(G11:J11,TRUE)/COLUMNS(G11:J11),"0%") -> 100% | M11: 45938 | N11: 17078 | O11: 17078 | P11: =IFERROR(O11/N11,0) -> 1 | Q11: =N11-(IF(ISBLANK(O11),N11,O11)) -> 0 | R11: =IFERROR(Q11/N11,0) -> 0
A12: 11 | B12: Salesforce | C12: Master Data | D12: Account (Non-Buying) | E12: Onity EMEA | G12: TRUE | H12: TRUE | I12: TRUE | J12: TRUE | K12: =REPT("|||||||||||||||||||||||",COUNTIF(G12:J12,TRUE)) -> |||||||||||||||||||||||||||||||||||||||||||||||||||||||||||||||||||||||||||||||||||||||||||| | L12: =TEXT(COUNTIF(G12:J12,TRUE)/COLUMNS(G12:J12),"0%") -> 100% | M12: 45953 | N12: 12621 | O12: 12621 | P12: =IFERROR(O12/N12,0) -> 1 | Q12: =N12-(IF(ISBLANK(O12),N12,O12)) -> 0 | R12: =IFERROR(Q12/N12,0) -> 0
A13: 12 | B13: Salesforce | C13: Master Data | D13: Contact | E13: Onity EMEA | G13: TRUE | H13: TRUE | I13: TRUE | J13: TRUE | K13: =REPT("|||||||||||||||||||||||",COUNTIF(G13:J13,TRUE)) -> |||||||||||||||||||||||||||||||||||||||||||||||||||||||||||||||||||||||||||||||||||||||||||| | L13: =TEXT(COUNTIF(G13:J13,TRUE)/COLUMNS(G13:J13),"0%") -> 100% | M13: 45958 | N13: 21914 | O13: 21914 | P13: =IFERROR(O13/N13,0) -> 1 | Q13: =N13-(IF(ISBLANK(O13),N13,O13)) -> 0 | R13: =IFERROR(Q13/N13,0) -> 0 | S13: 855 (Duplicate)
A14: 13 | B14: Salesforce | C14: Master Data | D14: Product | E14: Onity EMEA | G14: TRUE | H14: TRUE | I14: TRUE | J14: TRUE | K14: =REPT("|||||||||||||||||||||||",COUNTIF(G14:J14,TRUE)) -> |||||||||||||||||||||||||||||||||||||||||||||||||||||||||||||||||||||||||||||||||||||||||||| | L14: =TEXT(COUNTIF(G14:J14,TRUE)/COLUMNS(G14:J14),"0%") -> 100% | M14: 45938 | N14: 18718 | O14: 18718 | P14: =IFERROR(O14/N14,0) -> 1 | Q14: =N14-(IF(ISBLANK(O14),N14,O14)) -> 0 | R14: =IFERROR(Q14/N14,0) -> 0
A15: 14 | B15: Salesforce | C15: Transactional Data | D15: Opportunity | E15: Onity EMEA | G15: TRUE | H15: TRUE | I15: TRUE | J15: TRUE | K15: =REPT("|||||||||||||||||||||||",COUNTIF(G15:J15,TRUE)) -> |||||||||||||||||||||||||||||||||||||||||||||||||||||||||||||||||||||||||||||||||||||||||||| | L15: =TEXT(COUNTIF(G15:J15,TRUE)/COLUMNS(G15:J15),"0%") -> 100% | M15: 45962 | N15: 32144 | O15: 32144 | P15: =IFERROR(O15/N15,0) -> 1 | Q15: =N15-(IF(ISBLANK(O15),N15,O15)) -> 0 | R15: =IFERROR(Q15/N15,0) -> 0
A16: 15 | B16: Salesforce | C16: Transactional Data | D16: Case | E16: Onity EMEA | G16: TRUE | H16: TRUE | I16: TRUE | J16: TRUE | K16: =REPT("|||||||||||||||||||||||",COUNTIF(G16:J16,TRUE)) -> |||||||||||||||||||||||||||||||||||||||||||||||||||||||||||||||||||||||||||||||||||||||||||| | L16: =TEXT(COUNTIF(G16:J16,TRUE)/COLUMNS(G16:J16),"0%") -> 100% | M16: 45963 | N16: 2134 | O16: 2134 | P16: =IFERROR(O16/N16,0) -> 1 | Q16: =N16-(IF(ISBLANK(O16),N16,O16)) -> 0 | R16: =IFERROR(Q16/N16,0) -> 0
A17: 16 | B17: Salesforce | C17: Transactional Data | D17: Quote | E17: Onity EMEA | G17: TRUE | H17: TRUE | I17: TRUE | J17: TRUE | K17: =REPT("|||||||||||||||||||||||",COUNTIF(G17:J17,TRUE)) -> |||||||||||||||||||||||||||||||||||||||||||||||||||||||||||||||||||||||||||||||||||||||||||| | L17: =TEXT(COUNTIF(G17:J17,TRUE)/COLUMNS(G17:J17),"0%") -> 100% | M17: 45968 | N17: 8508 | O17: 8508 | P17: =IFERROR(O17/N17,0) -> 1 | Q17: =N17-(IF(ISBLANK(O17),N17,O17)) -> 0 | R17: =IFERROR(Q17/N17,0) -> 0
A18: 17 | B18: Salesforce | C18: Master Data | D18: Account (Buying) | E18: Onity APAC | F18: Chin Edmond- RoA Suriati Nur- GC, RoA David Carran- Ken Ong - ANZ James Eapen- Ind | G18: TRUE | H18: TRUE | I18: TRUE | J18: TRUE | K18: =REPT("|||||||||||||||||||||||",COUNTIF(G18:J18,TRUE)) -> |||||||||||||||||||||||||||||||||||||||||||||||||||||||||||||||||||||||||||||||||||||||||||| | L18: =TEXT(COUNTIF(G18:J18,TRUE)/COLUMNS(G18:J18),"0%") -> 100% | M18: 45938 | N18: 1061 | O18: 1061 | P18: =IFERROR(O18/N18,0) -> 1 | Q18: =N18-(IF(ISBLANK(O18),N18,O18)) -> 0 | R18: =IFERROR(Q18/N18,0) -> 0
A19: 18 | B19: Salesforce | C19: Master Data | D19: Contact | E19: Onity APAC | G19: TRUE | H19: TRUE | I19: TRUE | J19: TRUE | K19: =REPT("|||||||||||||||||||||||",COUNTIF(G19:J19,TRUE)) -> |||||||||||||||||||||||||||||||||||||||||||||||||||||||||||||||||||||||||||||||||||||||||||| | L19: =TEXT(COUNTIF(G19:J19,TRUE)/COLUMNS(G19:J19),"0%") -> 100% | M19: 45955 | N19: 25 | O19: 25 | P19: =IFERROR(O19/N19,0) -> 1 | Q19: =N19-(IF(ISBLANK(O19),N19,O19)) -> 0 | R19: =IFERROR(Q19/N19,0) -> 0
A20: 19 | B20: Salesforce | C20: Master Data | D20: Product | E20: Onity APAC | G20: TRUE | H20: TRUE | I20: TRUE | J20: TRUE | K20: =REPT("|||||||||||||||||||||||",COUNTIF(G20:J20,TRUE)) -> |||||||||||||||||||||||||||||||||||||||||||||||||||||||||||||||||||||||||||||||||||||||||||| | L20: =TEXT(COUNTIF(G20:J20,TRUE)/COLUMNS(G20:J20),"0%") -> 100% | M20: 45938 | N20: 23291 | O20: 23291 | P20: =IFERROR(O20/N20,0) -> 1 | Q20: =N20-(IF(ISBLANK(O20),N20,O20)) -> 0 | R20: =IFERROR(Q20/N20,0) -> 0
A21: 20 | B21: Salesforce | C21: Master Data | D21: Account (Buying) | E21: Lenel APAC | F21: Suriati Nur- RoA, GC Ken Ong - ANZ James Eapen- Ind | G21: TRUE | H21: TRUE | I21: TRUE | J21: TRUE | K21: =REPT("|||||||||||||||||||||||",COUNTIF(G21:J21,TRUE)) -> |||||||||||||||||||||||||||||||||||||||||||||||||||||||||||||||||||||||||||||||||||||||||||| | L21: =TEXT(COUNTIF(G21:J21,TRUE)/COLUMNS(G21:J21),"0%") -> 100% | M21: 45938 | N21: 144 | O21: 144 | P21: =IFERROR(O21/N21,0) -> 1 | Q21: =N21-(IF(ISBLANK(O21),N21,O21)) -> 0 | R21: =IFERROR(Q21/N21,0) -> 0
A22: 21 | B22: Salesforce | C22: Master Data | D22: Account (Non-Buying) | E22: Lenel APAC | G22: TRUE | H22: TRUE | I22: TRUE | J22: TRUE | K22: =REPT("|||||||||||||||||||||||",COUNTIF(G22:J22,TRUE)) -> |||||||||||||||||||||||||||||||||||||||||||||||||||||||||||||||||||||||||||||||||||||||||||| | L22: =TEXT(COUNTIF(G22:J22,TRUE)/COLUMNS(G22:J22),"0%") -> 100% | M22: 45938 | N22: 9832 | O22: 9832 | P22: =IFERROR(O22/N22,0) -> 1 | Q22: =N22-(IF(ISBLANK(O22),N22,O22)) -> 0 | R22: =IFERROR(Q22/N22,0) -> 0
A23: 22 | B23: Salesforce | C23: Master Data | D23: Contact | E23: Lenel APAC | G23: TRUE | H23: TRUE | I23: TRUE | J23: TRUE | K23: =REPT("|||||||||||||||||||||||",COUNTIF(G23:J23,TRUE)) -> |||||||||||||||||||||||||||||||||||||||||||||||||||||||||||||||||||||||||||||||||||||||||||| | L23: =TEXT(COUNTIF(G23:J23,TRUE)/COLUMNS(G23:J23),"0%") -> 100% | M23: 45938 | N23: 4936 | O23: 4936 | P23: =IFERROR(O23/N23,0) -> 1 | Q23: =N23-(IF(ISBLANK(O23),N23,O23)) -> 0 | R23: =IFERROR(Q23/N23,0) -> 0
A24: 23 | B24: Salesforce | C24: Master Data | D24: Product | E24: Lenel APAC | G24: TRUE | H24: TRUE | I24: TRUE | J24: TRUE | K24: =REPT("|||||||||||||||||||||||",COUNTIF(G24:J24,TRUE)) -> |||||||||||||||||||||||||||||||||||||||||||||||||||||||||||||||||||||||||||||||||||||||||||| | L24: =TEXT(COUNTIF(G24:J24,TRUE)/COLUMNS(G24:J24),"0%") -> 100% | M24: 45938 | N24: 3736 | O24: 3736 | P24: =IFERROR(O24/N24,0) -> 1 | Q24: =N24-(IF(ISBLANK(O24),N24,O24)) -> 0 | R24: =IFERROR(Q24/N24,0) -> 0
A25: 24 | B25: Salesforce | C25: Transactional Data | D25: Opportunity | E25: Lenel APAC | G25: TRUE | H25: TRUE | I25: TRUE | J25: TRUE | K25: =REPT("|||||||||||||||||||||||",COUNTIF(G25:J25,TRUE)) -> |||||||||||||||||||||||||||||||||||||||||||||||||||||||||||||||||||||||||||||||||||||||||||| | L25: =TEXT(COUNTIF(G25:J25,TRUE)/COLUMNS(G25:J25),"0%") -> 100% | M25: 45938 | N25: 1168 | O25: 1168 | P25: =IFERROR(O25/N25,0) -> 1 | Q25: =N25-(IF(ISBLANK(O25),N25,O25)) -> 0 | R25: =IFERROR(Q25/N25,0) -> 0
A26: 25 | B26: SMS SFDC | C26: Transactional Data | D26: SMS -Service Contract | E26: Lenel APAC | G26: TRUE | H26: TRUE | I26: TRUE | J26: TRUE | K26: =REPT("|||||||||||||||||||||||",COUNTIF(G26:J26,TRUE)) -> |||||||||||||||||||||||||||||||||||||||||||||||||||||||||||||||||||||||||||||||||||||||||||| | L26: =TEXT(COUNTIF(G26:J26,TRUE)/COLUMNS(G26:J26),"0%") -> 100% | M26: 45938 | N26: 34 | O26: 34 | P26: =IFERROR(O26/N26,0) -> 1 | Q26: =N26-(IF(ISBLANK(O26),N26,O26)) -> 0 | R26: =IFERROR(Q26/N26,0) -> 0
A27: 26 | B27: SMS SFDC | C27: Master Data | D27: SMS - Service Resources (Subcontractors and internal) | E27: Onity NA | F27: Kathleen / Marianne | G27: TRUE | H27: TRUE | I27: TRUE | J27: TRUE | K27: =REPT("|||||||||||||||||||||||",COUNTIF(G27:J27,TRUE)) -> |||||||||||||||||||||||||||||||||||||||||||||||||||||||||||||||||||||||||||||||||||||||||||| | L27: =TEXT(COUNTIF(G27:J27,TRUE)/COLUMNS(G27:J27),"0%") -> 100% | M27: 45959 | N27: 44 | O27: 44 | P27: =IFERROR(O27/N27,0) -> 1 | Q27: =N27-(IF(ISBLANK(O27),N27,O27)) -> 0 | R27: =IFERROR(Q27/N27,0) -> 0
A28: 27 | B28: SMS SFDC | C28: Master Data | D28: SMS - Work Type Setup | E28: Onity NA | G28: TRUE | H28: TRUE | I28: TRUE | J28: TRUE | K28: =REPT("|||||||||||||||||||||||",COUNTIF(G28:J28,TRUE)) -> |||||||||||||||||||||||||||||||||||||||||||||||||||||||||||||||||||||||||||||||||||||||||||| | L28: =TEXT(COUNTIF(G28:J28,TRUE)/COLUMNS(G28:J28),"0%") -> 100% | M28: 45954 | N28: 124 | O28: 124 | P28: =IFERROR(O28/N28,0) -> 1 | Q28: =N28-(IF(ISBLANK(O28),N28,O28)) -> 0 | R28: =IFERROR(Q28/N28,0) -> 0
A29: 28 | B29: SMS SFDC | C29: Transactional Data | D29: SMS -Service Contract | E29: Onity NA | G29: TRUE | H29: TRUE | I29: TRUE | J29: TRUE | K29: =REPT("|||||||||||||||||||||||",COUNTIF(G29:J29,TRUE)) -> |||||||||||||||||||||||||||||||||||||||||||||||||||||||||||||||||||||||||||||||||||||||||||| | L29: =TEXT(COUNTIF(G29:J29,TRUE)/COLUMNS(G29:J29),"0%") -> 100% | M29: 45968 | N29: 3513 | O29: 3513 | P29: =IFERROR(O29/N29,0) -> 1 | Q29: =N29-(IF(ISBLANK(O29),N29,O29)) -> 0 | R29: =IFERROR(Q29/N29,0) -> 0 | S29: Missing extended warranty/service contracts on some accounts, especially those created after initial ERP load.
A30: 29 | B30: SMS SFDC | C30: Master Data | D30: SMS - Service Territory | E30: Onity NA | G30: TRUE | H30: TRUE | I30: TRUE | J30: TRUE | K30: =REPT("|||||||||||||||||||||||",COUNTIF(G30:J30,TRUE)) -> |||||||||||||||||||||||||||||||||||||||||||||||||||||||||||||||||||||||||||||||||||||||||||| | L30: =TEXT(COUNTIF(G30:J30,TRUE)/COLUMNS(G30:J30),"0%") -> 100% | M30: 45951 | N30: 4 | O30: 4 | P30: =IFERROR(O30/N30,0) -> 1 | Q30: =N30-(IF(ISBLANK(O30),N30,O30)) -> 0 | R30: =IFERROR(Q30/N30,0) -> 0
A31: 30 | B31: SMS SFDC | C31: Master Data | D31: SMS - Profit Center | E31: Onity NA | G31: TRUE | H31: TRUE | I31: TRUE | J31: TRUE | K31: =REPT("|||||||||||||||||||||||",COUNTIF(G31:J31,TRUE)) -> |||||||||||||||||||||||||||||||||||||||||||||||||||||||||||||||||||||||||||||||||||||||||||| | L31: =TEXT(COUNTIF(G31:J31,TRUE)/COLUMNS(G31:J31),"0%") -> 100% | M31: 45952 | N31: 8 | O31: 8 | P31: =IFERROR(O31/N31,0) -> 1 | Q31: =N31-(IF(ISBLANK(O31),N31,O31)) -> 0 | R31: =IFERROR(Q31/N31,0) -> 0
A32: 31 | B32: SMS SFDC | C32: Master Data | D32: SMS - Service Resource Setup | E32: Onity NA | G32: TRUE | H32: TRUE | I32: TRUE | J32: TRUE | K32: =REPT("|||||||||||||||||||||||",COUNTIF(G32:J32,TRUE)) -> |||||||||||||||||||||||||||||||||||||||||||||||||||||||||||||||||||||||||||||||||||||||||||| | L32: =TEXT(COUNTIF(G32:J32,TRUE)/COLUMNS(G32:J32),"0%") -> 100% | M32: 45960 | N32: 122 | O32: 122 | P32: =IFERROR(O32/N32,0) -> 1 | Q32: =N32-(IF(ISBLANK(O32),N32,O32)) -> 0 | R32: =IFERROR(Q32/N32,0) -> 0
A33: 32 | B33: SMS SFDC | C33: Master Data | D33: SMS - Asset | E33: Onity NA | G33: TRUE | H33: TRUE | I33: TRUE | J33: TRUE | K33: =REPT("|||||||||||||||||||||||",COUNTIF(G33:J33,TRUE)) -> |||||||||||||||||||||||||||||||||||||||||||||||||||||||||||||||||||||||||||||||||||||||||||| | L33: =TEXT(COUNTIF(G33:J33,TRUE)/COLUMNS(G33:J33),"0%") -> 100% | M33: 45968 | N33: 683000 | O33: 557149 | P33: =IFERROR(O33/N33,0) -> 0.81573792 | Q33: =N33-(IF(ISBLANK(O33),N33,O33)) -> 125851 | R33: =IFERROR(Q33/N33,0) -> 0.18426208 | S33: Nitesh will share the record count (expected and loaded)
A34: 33 | B34: SMS SFDC | C34: Master Data | D34: SMS - Location | E34: Onity NA | G34: TRUE | H34: TRUE | I34: TRUE | J34: TRUE | K34: =REPT("|||||||||||||||||||||||",COUNTIF(G34:J34,TRUE)) -> |||||||||||||||||||||||||||||||||||||||||||||||||||||||||||||||||||||||||||||||||||||||||||| | L34: =TEXT(COUNTIF(G34:J34,TRUE)/COLUMNS(G34:J34),"0%") -> 100% | M34: 45951 | N34: 12070 | O34: 12070 | P34: =IFERROR(O34/N34,0) -> 1 | Q34: =N34-(IF(ISBLANK(O34),N34,O34)) -> 0 | R34: =IFERROR(Q34/N34,0) -> 0
A35: 34 | B35: SMS SFDC | C35: Master Data | D35: SMS - Service Resources (Subcontractors and internal) | E35: Onity EMEA | G35: TRUE | H35: TRUE | I35: TRUE | J35: TRUE | K35: =REPT("|||||||||||||||||||||||",COUNTIF(G35:J35,TRUE)) -> |||||||||||||||||||||||||||||||||||||||||||||||||||||||||||||||||||||||||||||||||||||||||||| | L35: =TEXT(COUNTIF(G35:J35,TRUE)/COLUMNS(G35:J35),"0%") -> 100% | M35: 45959 | N35: 25 | O35: 25 | P35: =IFERROR(O35/N35,0) -> 1 | Q35: =N35-(IF(ISBLANK(O35),N35,O35)) -> 0 | R35: =IFERROR(Q35/N35,0) -> 0
A36: 35 | B36: SMS SFDC | C36: Master Data | D36: SMS - Work Type Setup | E36: Onity EMEA | G36: TRUE | H36: TRUE | I36: TRUE | J36: TRUE | K36: =REPT("|||||||||||||||||||||||",COUNTIF(G36:J36,TRUE)) -> |||||||||||||||||||||||||||||||||||||||||||||||||||||||||||||||||||||||||||||||||||||||||||| | L36: =TEXT(COUNTIF(G36:J36,TRUE)/COLUMNS(G36:J36),"0%") -> 100% | M36: 45954 | N36: 124 | O36: 124 | P36: =IFERROR(O36/N36,0) -> 1 | Q36: =N36-(IF(ISBLANK(O36),N36,O36)) -> 0 | R36: =IFERROR(Q36/N36,0) -> 0
A37: 36 | B37: SMS SFDC | C37: Master Data | D37: SMS - Service Territory | E37: Onity EMEA | G37: TRUE | H37: TRUE | I37: TRUE | J37: TRUE | K37: =REPT("|||||||||||||||||||||||",COUNTIF(G37:J37,TRUE)) -> |||||||||||||||||||||||||||||||||||||||||||||||||||||||||||||||||||||||||||||||||||||||||||| | L37: =TEXT(COUNTIF(G37:J37,TRUE)/COLUMNS(G37:J37),"0%") -> 100% | M37: 45951 | N37: 3 | O37: 3 | P37: =IFERROR(O37/N37,0) -> 1 | Q37: =N37-(IF(ISBLANK(O37),N37,O37)) -> 0 | R37: =IFERROR(Q37/N37,0) -> 0
A38: 37 | B38: SMS SFDC | C38: Transactional Data | D38: SMS -Service Contract | E38: Onity EMEA | G38: TRUE | H38: TRUE | I38: TRUE | J38: TRUE | K38: =REPT("|||||||||||||||||||||||",COUNTIF(G38:J38,TRUE)) -> |||||||||||||||||||||||||||||||||||||||||||||||||||||||||||||||||||||||||||||||||||||||||||| | L38: =TEXT(COUNTIF(G38:J38,TRUE)/COLUMNS(G38:J38),"0%") -> 100% | M38: 45968 | N38: 247 | O38: 247 | P38: =IFERROR(O38/N38,0) -> 1 | Q38: =N38-(IF(ISBLANK(O38),N38,O38)) -> 0 | R38: =IFERROR(Q38/N38,0) -> 0
A39: 38 | B39: SMS SFDC | C39: Master Data | D39: SMS - Profit Center | E39: Onity EMEA | G39: TRUE | H39: TRUE | I39: TRUE | J39: TRUE | K39: =REPT("|||||||||||||||||||||||",COUNTIF(G39:J39,TRUE)) -> |||||||||||||||||||||||||||||||||||||||||||||||||||||||||||||||||||||||||||||||||||||||||||| | L39: =TEXT(COUNTIF(G39:J39,TRUE)/COLUMNS(G39:J39),"0%") -> 100% | M39: 45952 | N39: 8 | O39: 8 | P39: =IFERROR(O39/N39,0) -> 1 | Q39: =N39-(IF(ISBLANK(O39),N39,O39)) -> 0 | R39: =IFERROR(Q39/N39,0) -> 0
A40: 39 | B40: SMS SFDC | C40: Master Data | D40: SMS - Service Resource Setup | E40: Onity EMEA | G40: TRUE | H40: TRUE | I40: TRUE | J40: TRUE | K40: =REPT("|||||||||||||||||||||||",COUNTIF(G40:J40,TRUE)) -> |||||||||||||||||||||||||||||||||||||||||||||||||||||||||||||||||||||||||||||||||||||||||||| | L40: =TEXT(COUNTIF(G40:J40,TRUE)/COLUMNS(G40:J40),"0%") -> 100% | M40: 45960 | N40: 67 | O40: 67 | P40: =IFERROR(O40/N40,0) -> 1 | Q40: =N40-(IF(ISBLANK(O40),N40,O40)) -> 0 | R40: =IFERROR(Q40/N40,0) -> 0
A41: 40 | B41: SMS SFDC | C41: Master Data | D41: SMS - Asset | E41: Onity EMEA | G41: TRUE | H41: TRUE | I41: TRUE | J41: TRUE | K41: =REPT("|||||||||||||||||||||||",COUNTIF(G41:J41,TRUE)) -> |||||||||||||||||||||||||||||||||||||||||||||||||||||||||||||||||||||||||||||||||||||||||||| | L41: =TEXT(COUNTIF(G41:J41,TRUE)/COLUMNS(G41:J41),"0%") -> 100% | M41: 45968 | N41: 29680 | O41: 28812 | P41: =IFERROR(O41/N41,0) -> 0.97075472 | Q41: =N41-(IF(ISBLANK(O41),N41,O41)) -> 868 | R41: =IFERROR(Q41/N41,0) -> 0.029245283 | S41: Bindu will check with Christine and provide the record count (expected and loaded)
A42: 41 | B42: SMS SFDC | C42: Master Data | D42: SMS - Location | E42: Onity EMEA | G42: TRUE | H42: TRUE | I42: TRUE | J42: TRUE | K42: =REPT("|||||||||||||||||||||||",COUNTIF(G42:J42,TRUE)) -> |||||||||||||||||||||||||||||||||||||||||||||||||||||||||||||||||||||||||||||||||||||||||||| | L42: =TEXT(COUNTIF(G42:J42,TRUE)/COLUMNS(G42:J42),"0%") -> 100% | M42: 45951 | N42: 7351 | O42: 7351 | P42: =IFERROR(O42/N42,0) -> 1 | Q42: =N42-(IF(ISBLANK(O42),N42,O42)) -> 0 | R42: =IFERROR(Q42/N42,0) -> 0
A43: 42 | B43: SMS SFDC | C43: Transactional Data | D43: SMS - Maintenance Plan | E43: Onity EMEA | G43: TRUE | H43: TRUE | I43: TRUE | J43: FALSE | K43: =REPT("|||||||||||||||||||||||",COUNTIF(G43:J43,TRUE)) -> ||||||||||||||||||||||||||||||||||||||||||||||||||||||||||||||||||||| | L43: =TEXT(COUNTIF(G43:J43,TRUE)/COLUMNS(G43:J43),"0%") -> 75% | M43: 45968 | N43: 148 | O43: 54 | P43: =IFERROR(O43/N43,0) -> 0.36486486 | Q43: =N43-(IF(ISBLANK(O43),N43,O43)) -> 94 | R43: =IFERROR(Q43/N43,0) -> 0.63513514
A44: 43 | B44: SMS SFDC | C44: Transactional Data | D44: SMS - Maintenance Asset | E44: Onity EMEA | G44: TRUE | H44: TRUE | I44: TRUE | J44: FALSE | K44: =REPT("|||||||||||||||||||||||",COUNTIF(G44:J44,TRUE)) -> ||||||||||||||||||||||||||||||||||||||||||||||||||||||||||||||||||||| | L44: =TEXT(COUNTIF(G44:J44,TRUE)/COLUMNS(G44:J44),"0%") -> 75% | M44: 45968 | N44: 471 | O44: 98 | P44: =IFERROR(O44/N44,0) -> 0.20806794 | Q44: =N44-(IF(ISBLANK(O44),N44,O44)) -> 373 | R44: =IFERROR(Q44/N44,0) -> 0.79193206 | S44: Bindu will check with Christine and provide the record count (expected and loaded)
A45: 44 | B45: SMS SFDC | C45: Transactional Data | D45: SMS - CLI | E45: Onity EMEA | G45: TRUE | H45: TRUE | I45: FALSE | J45: FALSE | K45: =REPT("|||||||||||||||||||||||",COUNTIF(G45:J45,TRUE)) -> |||||||||||||||||||||||||||||||||||||||||||||| | L45: =TEXT(COUNTIF(G45:J45,TRUE)/COLUMNS(G45:J45),"0%") -> 50% | M45: 45968 | N45: 1093 | O45: 0 | P45: =IFERROR(O45/N45,0) -> 0 | Q45: =N45-(IF(ISBLANK(O45),N45,O45)) -> 1093 | R45: =IFERROR(Q45/N45,0) -> 1 | S45: Bindu will check with Christine and provide the record count (expected and loaded)
A46: 45 | B46: SMS SFDC | C46: Transactional Data | D46: SMS - Work Order | E46: Onity EMEA | G46: TRUE | H46: TRUE | I46: TRUE | J46: TRUE | K46: =REPT("|||||||||||||||||||||||",COUNTIF(G46:J46,TRUE)) -> |||||||||||||||||||||||||||||||||||||||||||||||||||||||||||||||||||||||||||||||||||||||||||| | L46: =TEXT(COUNTIF(G46:J46,TRUE)/COLUMNS(G46:J46),"0%") -> 100% | M46: 45968 | N46: 2409 | O46: 2409 | P46: =IFERROR(O46/N46,0) -> 1 | Q46: =N46-(IF(ISBLANK(O46),N46,O46)) -> 0 | R46: =IFERROR(Q46/N46,0) -> 0 | S46: Data Migration team will be loading on 7th Nov
A47: 46 | B47: CPQ | C47: Master Data | D47: Price | E47: Onity NA | F47: Nicole/ Brian/ David (NA) Ander/ Julian (EMEA) | G47: TRUE | H47: TRUE | I47: TRUE | J47: TRUE | K47: =REPT("|||||||||||||||||||||||",COUNTIF(G47:J47,TRUE)) -> |||||||||||||||||||||||||||||||||||||||||||||||||||||||||||||||||||||||||||||||||||||||||||| | L47: =TEXT(COUNTIF(G47:J47,TRUE)/COLUMNS(G47:J47),"0%") -> 100% | M47: 45961 | N47: 4529 | O47: 4463 | P47: =IFERROR(O47/N47,0) -> 0.98542725 | Q47: =N47-(IF(ISBLANK(O47),N47,O47)) -> 66 | R47: =IFERROR(Q47/N47,0) -> 0.014572753 | S47: Investigation in progress on missing record
A48: 47 | B48: CPQ | C48: Master Data | D48: Material | E48: Onity NA | G48: TRUE | H48: TRUE | I48: TRUE | J48: TRUE | K48: =REPT("|||||||||||||||||||||||",COUNTIF(G48:J48,TRUE)) -> |||||||||||||||||||||||||||||||||||||||||||||||||||||||||||||||||||||||||||||||||||||||||||| | L48: =TEXT(COUNTIF(G48:J48,TRUE)/COLUMNS(G48:J48),"0%") -> 100% | M48: 45961 | N48: 4229 | O48: 3948 | P48: =IFERROR(O48/N48,0) -> 0.93355403 | Q48: =N48-(IF(ISBLANK(O48),N48,O48)) -> 281 | R48: =IFERROR(Q48/N48,0) -> 0.066445968 | S48: Investigation in progress on missing record
A49: 48 | B49: CPQ | C49: Master Data | D49: Price | E49: Onity EMEA | G49: TRUE | H49: TRUE | I49: TRUE | J49: TRUE | K49: =REPT("|||||||||||||||||||||||",COUNTIF(G49:J49,TRUE)) -> |||||||||||||||||||||||||||||||||||||||||||||||||||||||||||||||||||||||||||||||||||||||||||| | L49: =TEXT(COUNTIF(G49:J49,TRUE)/COLUMNS(G49:J49),"0%") -> 100% | M49: 45961 | N49: 4539 | O49: 4539 | P49: =IFERROR(O49/N49,0) -> 1 | Q49: =N49-(IF(ISBLANK(O49),N49,O49)) -> 0 | R49: =IFERROR(Q49/N49,0) -> 0
A50: 49 | B50: CPQ | C50: Master Data | D50: Material | E50: Onity EMEA | G50: TRUE | H50: TRUE | I50: TRUE | J50: TRUE | K50: =REPT("|||||||||||||||||||||||",COUNTIF(G50:J50,TRUE)) -> |||||||||||||||||||||||||||||||||||||||||||||||||||||||||||||||||||||||||||||||||||||||||||| | L50: =TEXT(COUNTIF(G50:J50,TRUE)/COLUMNS(G50:J50),"0%") -> 100% | M50: 45961 | N50: 6519 | O50: 6149 | P50: =IFERROR(O50/N50,0) -> 0.94324283 | Q50: =N50-(IF(ISBLANK(O50),N50,O50)) -> 370 | R50: =IFERROR(Q50/N50,0) -> 0.056757171 | S50: Investigation in progress on missing record
A51: 50 | B51: CPQ | C51: Master Data | D51: Price | E51: Onity APAC | G51: TRUE | H51: TRUE | I51: TRUE | J51: TRUE | K51: =REPT("|||||||||||||||||||||||",COUNTIF(G51:J51,TRUE)) -> |||||||||||||||||||||||||||||||||||||||||||||||||||||||||||||||||||||||||||||||||||||||||||| | L51: =TEXT(COUNTIF(G51:J51,TRUE)/COLUMNS(G51:J51),"0%") -> 100% | M51: 45961 | N51: 4948 | O51: 3981 | P51: =IFERROR(O51/N51,0) -> 0.8045675 | Q51: =N51-(IF(ISBLANK(O51),N51,O51)) -> 967 | R51: =IFERROR(Q51/N51,0) -> 0.1954325 | S51: Investigation in progress on missing record
A52: 51 | B52: CPQ | C52: Master Data | D52: Material | E52: Onity APAC | G52: TRUE | H52: TRUE | I52: TRUE | J52: TRUE | K52: =REPT("|||||||||||||||||||||||",COUNTIF(G52:J52,TRUE)) -> |||||||||||||||||||||||||||||||||||||||||||||||||||||||||||||||||||||||||||||||||||||||||||| | L52: =TEXT(COUNTIF(G52:J52,TRUE)/COLUMNS(G52:J52),"0%") -> 100% | M52: 45961 | N52: 4321 | O52: 3373 | P52: =IFERROR(O52/N52,0) -> 0.78060634 | Q52: =N52-(IF(ISBLANK(O52),N52,O52)) -> 948 | R52: =IFERROR(Q52/N52,0) -> 0.21939366 | S52: Investigation in progress on missing record
A53: 52 | B53: CPQ | C53: Master Data | D53: Price | E53: Lenel APAC | G53: TRUE | H53: TRUE | I53: TRUE | J53: TRUE | K53: =REPT("|||||||||||||||||||||||",COUNTIF(G53:J53,TRUE)) -> |||||||||||||||||||||||||||||||||||||||||||||||||||||||||||||||||||||||||||||||||||||||||||| | L53: =TEXT(COUNTIF(G53:J53,TRUE)/COLUMNS(G53:J53),"0%") -> 100% | M53: 45961 | N53: 4948 | O53: 3981 | P53: =IFERROR(O53/N53,0) -> 0.8045675 | Q53: =N53-(IF(ISBLANK(O53),N53,O53)) -> 967 | R53: =IFERROR(Q53/N53,0) -> 0.1954325 | S53: Investigation in progress on missing record
A54: 53 | B54: CPQ | C54: Master Data | D54: Material | E54: Lenel APAC | G54: TRUE | H54: TRUE | I54: TRUE | J54: TRUE | K54: =REPT("|||||||||||||||||||||||",COUNTIF(G54:J54,TRUE)) -> |||||||||||||||||||||||||||||||||||||||||||||||||||||||||||||||||||||||||||||||||||||||||||| | L54: =TEXT(COUNTIF(G54:J54,TRUE)/COLUMNS(G54:J54),"0%") -> 100% | M54: 45961 | N54: 4321 | O54: 3373 | P54: =IFERROR(O54/N54,0) -> 0.78060634 | Q54: =N54-(IF(ISBLANK(O54),N54,O54)) -> 948 | R54: =IFERROR(Q54/N54,0) -> 0.21939366 | S54: Investigation in progress on missing record
A55: 54 | B55: eCommerce | C55: Master Data | D55: Account (Buying) | E55: Onity NA | F55: Nicole / Anne Kelly (NA) | G55: TRUE | H55: TRUE | I55: TRUE | J55: TRUE | K55: =REPT("|||||||||||||||||||||||",COUNTIF(G55:J55,TRUE)) -> |||||||||||||||||||||||||||||||||||||||||||||||||||||||||||||||||||||||||||||||||||||||||||| | L55: =TEXT(COUNTIF(G55:J55,TRUE)/COLUMNS(G55:J55),"0%") -> 100% | M55: 45961 | N55: 37145 | O55: 37145 | P55: =IFERROR(O55/N55,0) -> 1 | Q55: =N55-(IF(ISBLANK(O55),N55,O55)) -> 0 | R55: =IFERROR(Q55/N55,0) -> 0
A56: 55 | B56: eCommerce | C56: Master Data | D56: Material | E56: Onity NA | G56: TRUE | H56: TRUE | I56: TRUE | J56: TRUE | K56: =REPT("|||||||||||||||||||||||",COUNTIF(G56:J56,TRUE)) -> |||||||||||||||||||||||||||||||||||||||||||||||||||||||||||||||||||||||||||||||||||||||||||| | L56: =TEXT(COUNTIF(G56:J56,TRUE)/COLUMNS(G56:J56),"0%") -> 100% | M56: 45961 | N56: 1806 | O56: 1806 | P56: =IFERROR(O56/N56,0) -> 1 | Q56: =N56-(IF(ISBLANK(O56),N56,O56)) -> 0 | R56: =IFERROR(Q56/N56,0) -> 0
A57: 56 | B57: eCommerce | C57: Master Data | D57: Price | E57: Onity NA | G57: TRUE | H57: TRUE | I57: TRUE | J57: TRUE | K57: =REPT("|||||||||||||||||||||||",COUNTIF(G57:J57,TRUE)) -> |||||||||||||||||||||||||||||||||||||||||||||||||||||||||||||||||||||||||||||||||||||||||||| | L57: =TEXT(COUNTIF(G57:J57,TRUE)/COLUMNS(G57:J57),"0%") -> 100% | M57: 45961 | N57: 1806 | O57: 1806 | P57: =IFERROR(O57/N57,0) -> 1 | Q57: =N57-(IF(ISBLANK(O57),N57,O57)) -> 0 | R57: =IFERROR(Q57/N57,0) -> 0
A58: 57 | B58: AEM | C58: Master Data | D58: Material | E58: Onity NA | G58: TRUE | H58: TRUE | I58: TRUE | J58: TRUE | K58: =REPT("|||||||||||||||||||||||",COUNTIF(G58:J58,TRUE)) -> |||||||||||||||||||||||||||||||||||||||||||||||||||||||||||||||||||||||||||||||||||||||||||| | L58: =TEXT(COUNTIF(G58:J58,TRUE)/COLUMNS(G58:J58),"0%") -> 100% | M58: 45968 | N58: 1806 | O58: 1806 | P58: =IFERROR(O58/N58,0) -> 1 | Q58: =N58-(IF(ISBLANK(O58),N58,O58)) -> 0 | R58: =IFERROR(Q58/N58,0) -> 0
A59: 58 | B59: Zuora | C59: Master Data | D59: Account (Buying) | E59: Onity APAC | F59: Nicole (NA) Abelardo / Sonia (EMEA) | G59: TRUE | H59: TRUE | I59: TRUE | J59: TRUE | K59: =REPT("|||||||||||||||||||||||",COUNTIF(G59:J59,TRUE)) -> |||||||||||||||||||||||||||||||||||||||||||||||||||||||||||||||||||||||||||||||||||||||||||| | L59: =TEXT(COUNTIF(G59:J59,TRUE)/COLUMNS(G59:J59),"0%") -> 100% | M59: 45961 | N59: 4296 | O59: 4282 | P59: =IFERROR(O59/N59,0) -> 0.99674115 | Q59: =N59-(IF(ISBLANK(O59),N59,O59)) -> 14 | R59: =IFERROR(Q59/N59,0) -> 0.0032588454
A60: 59 | B60: Zuora | C60: Master Data | D60: Account (Buying) | E60: Onity NA | G60: TRUE | H60: TRUE | I60: TRUE | J60: TRUE | K60: =REPT("|||||||||||||||||||||||",COUNTIF(G60:J60,TRUE)) -> |||||||||||||||||||||||||||||||||||||||||||||||||||||||||||||||||||||||||||||||||||||||||||| | L60: =TEXT(COUNTIF(G60:J60,TRUE)/COLUMNS(G60:J60),"0%") -> 100% | M60: 45961 | N60: 37835 | O60: 37423 | P60: =IFERROR(O60/N60,0) -> 0.98911061 | Q60: =N60-(IF(ISBLANK(O60),N60,O60)) -> 412 | R60: =IFERROR(Q60/N60,0) -> 0.010889388
A61: 60 | B61: Zuora | C61: Master Data | D61: Account (Buying) | E61: Onity EMEA | G61: TRUE | H61: TRUE | I61: TRUE | J61: TRUE | K61: =REPT("|||||||||||||||||||||||",COUNTIF(G61:J61,TRUE)) -> |||||||||||||||||||||||||||||||||||||||||||||||||||||||||||||||||||||||||||||||||||||||||||| | L61: =TEXT(COUNTIF(G61:J61,TRUE)/COLUMNS(G61:J61),"0%") -> 100% | M61: 45961 | N61: 27183 | O61: 27049 | P61: =IFERROR(O61/N61,0) -> 0.99507045 | Q61: =N61-(IF(ISBLANK(O61),N61,O61)) -> 134 | R61: =IFERROR(Q61/N61,0) -> 0.0049295516
A62: 61 | B62: Zuora | C62: Master Data | D62: Subscription Data | E62: Onity EMEA | G62: TRUE | H62: TRUE | I62: TRUE | J62: TRUE | K62: =REPT("|||||||||||||||||||||||",COUNTIF(G62:J62,TRUE)) -> |||||||||||||||||||||||||||||||||||||||||||||||||||||||||||||||||||||||||||||||||||||||||||| | L62: =TEXT(COUNTIF(G62:J62,TRUE)/COLUMNS(G62:J62),"0%") -> 100% | M62: 45968 | N62: 3913 | O62: 3810 | P62: =IFERROR(O62/N62,0) -> 0.97367749 | Q62: =N62-(IF(ISBLANK(O62),N62,O62)) -> 103 | R62: =IFERROR(Q62/N62,0) -> 0.026322515
A63: 62 | B63: Zuora | C63: Master Data | D63: Property Accounts (End User Accounts in Zuora) | E63: Onity EMEA | G63: TRUE | H63: TRUE | I63: TRUE | J63: TRUE | K63: =REPT("|||||||||||||||||||||||",COUNTIF(G63:J63,TRUE)) -> |||||||||||||||||||||||||||||||||||||||||||||||||||||||||||||||||||||||||||||||||||||||||||| | L63: =TEXT(COUNTIF(G63:J63,TRUE)/COLUMNS(G63:J63),"0%") -> 100% | M63: 45961 | N63: 2037 | O63: 1964 | P63: =IFERROR(O63/N63,0) -> 0.96416298 | Q63: =N63-(IF(ISBLANK(O63),N63,O63)) -> 73 | R63: =IFERROR(Q63/N63,0) -> 0.035837015 | S63: Cleaned Property Accounts as much as we can : Needed to be reviewed by business team before Billing/Invoicing
A64: 63 | B64: Zuora | C64: Master Data | D64: Product | E64: Onity APAC | G64: TRUE | H64: TRUE | I64: TRUE | J64: TRUE | K64: =REPT("|||||||||||||||||||||||",COUNTIF(G64:J64,TRUE)) -> |||||||||||||||||||||||||||||||||||||||||||||||||||||||||||||||||||||||||||||||||||||||||||| | L64: =TEXT(COUNTIF(G64:J64,TRUE)/COLUMNS(G64:J64),"0%") -> 100% | M64: 45961 | N64: 12 | O64: 12 | P64: =IFERROR(O64/N64,0) -> 1 | Q64: =N64-(IF(ISBLANK(O64),N64,O64)) -> 0 | R64: =IFERROR(Q64/N64,0) -> 0
A65: 64 | B65: Zuora | C65: Master Data | D65: Product | E65: Onity NA | G65: TRUE | H65: TRUE | I65: TRUE | J65: TRUE | K65: =REPT("|||||||||||||||||||||||",COUNTIF(G65:J65,TRUE)) -> |||||||||||||||||||||||||||||||||||||||||||||||||||||||||||||||||||||||||||||||||||||||||||| | L65: =TEXT(COUNTIF(G65:J65,TRUE)/COLUMNS(G65:J65),"0%") -> 100% | M65: 45961 | N65: 12 | O65: 12 | P65: =IFERROR(O65/N65,0) -> 1 | Q65: =N65-(IF(ISBLANK(O65),N65,O65)) -> 0 | R65: =IFERROR(Q65/N65,0) -> 0
A66: 65 | B66: Zuora | C66: Master Data | D66: Product | E66: Onity EMEA | G66: TRUE | H66: TRUE | I66: TRUE | J66: TRUE | K66: =REPT("|||||||||||||||||||||||",COUNTIF(G66:J66,TRUE)) -> |||||||||||||||||||||||||||||||||||||||||||||||||||||||||||||||||||||||||||||||||||||||||||| | L66: =TEXT(COUNTIF(G66:J66,TRUE)/COLUMNS(G66:J66),"0%") -> 100% | M66: 45961 | N66: 12 | O66: 12 | P66: =IFERROR(O66/N66,0) -> 1 | Q66: =N66-(IF(ISBLANK(O66),N66,O66)) -> 0 | R66: =IFERROR(Q66/N66,0) -> 0
A67: 66 | B67: Pros | C67: Master Data | D67: Material/Product | E67: Lenel APAC | F67: James Eapen Michael Xu Ken Ong Nicole Shedd Camilo Ruiz Julian Nieto Ander Maneiro Edmond Chin William Tang | G67: TRUE | H67: TRUE | I67: TRUE | J67: TRUE | K67: =REPT("|||||||||||||||||||||||",COUNTIF(G67:J67,TRUE)) -> |||||||||||||||||||||||||||||||||||||||||||||||||||||||||||||||||||||||||||||||||||||||||||| | L67: =TEXT(COUNTIF(G67:J67,TRUE)/COLUMNS(G67:J67),"0%") -> 100% | M67: 45961 | N67: 1623 | O67: 1623 | P67: =IFERROR(O67/N67,0) -> 1 | Q67: =N67-(IF(ISBLANK(O67),N67,O67)) -> 0 | R67: =IFERROR(Q67/N67,0) -> 0
A68: 67 | B68: Pros | C68: Master Data | D68: Price | E68: Lenel APAC | G68: TRUE | H68: TRUE | I68: TRUE | J68: TRUE | K68: =REPT("|||||||||||||||||||||||",COUNTIF(G68:J68,TRUE)) -> |||||||||||||||||||||||||||||||||||||||||||||||||||||||||||||||||||||||||||||||||||||||||||| | L68: =TEXT(COUNTIF(G68:J68,TRUE)/COLUMNS(G68:J68),"0%") -> 100% | M68: 45961 | N68: 8667 | O68: 8667 | P68: =IFERROR(O68/N68,0) -> 1 | Q68: =N68-(IF(ISBLANK(O68),N68,O68)) -> 0 | R68: =IFERROR(Q68/N68,0) -> 0
A69: 68 | B69: Pros | C69: Master Data | D69: Material/Product | E69: Onity NA | G69: TRUE | H69: TRUE | I69: TRUE | J69: TRUE | K69: =REPT("|||||||||||||||||||||||",COUNTIF(G69:J69,TRUE)) -> |||||||||||||||||||||||||||||||||||||||||||||||||||||||||||||||||||||||||||||||||||||||||||| | L69: =TEXT(COUNTIF(G69:J69,TRUE)/COLUMNS(G69:J69),"0%") -> 100% | M69: 45961 | N69: 5022 | O69: 5022 | P69: =IFERROR(O69/N69,0) -> 1 | Q69: =N69-(IF(ISBLANK(O69),N69,O69)) -> 0 | R69: =IFERROR(Q69/N69,0) -> 0
A70: 69 | B70: Pros | C70: Master Data | D70: Price | E70: Onity NA | G70: TRUE | H70: TRUE | I70: TRUE | J70: TRUE | K70: =REPT("|||||||||||||||||||||||",COUNTIF(G70:J70,TRUE)) -> |||||||||||||||||||||||||||||||||||||||||||||||||||||||||||||||||||||||||||||||||||||||||||| | L70: =TEXT(COUNTIF(G70:J70,TRUE)/COLUMNS(G70:J70),"0%") -> 100% | M70: 45961 | N70: 4374 | O70: 4374 | P70: =IFERROR(O70/N70,0) -> 1 | Q70: =N70-(IF(ISBLANK(O70),N70,O70)) -> 0 | R70: =IFERROR(Q70/N70,0) -> 0
A71: 70 | B71: Pros | C71: Master Data | D71: Material/Product | E71: Onity EMEA | G71: TRUE | H71: TRUE | I71: TRUE | J71: TRUE | K71: =REPT("|||||||||||||||||||||||",COUNTIF(G71:J71,TRUE)) -> |||||||||||||||||||||||||||||||||||||||||||||||||||||||||||||||||||||||||||||||||||||||||||| | L71: =TEXT(COUNTIF(G71:J71,TRUE)/COLUMNS(G71:J71),"0%") -> 100% | M71: 45961 | N71: 2632 | O71: 2632 | P71: =IFERROR(O71/N71,0) -> 1 | Q71: =N71-(IF(ISBLANK(O71),N71,O71)) -> 0 | R71: =IFERROR(Q71/N71,0) -> 0
A72: 71 | B72: Pros | C72: Master Data | D72: Price | E72: Onity EMEA | G72: TRUE | H72: TRUE | I72: TRUE | J72: TRUE | K72: =REPT("|||||||||||||||||||||||",COUNTIF(G72:J72,TRUE)) -> |||||||||||||||||||||||||||||||||||||||||||||||||||||||||||||||||||||||||||||||||||||||||||| | L72: =TEXT(COUNTIF(G72:J72,TRUE)/COLUMNS(G72:J72),"0%") -> 100% | M72: 45961 | N72: 71813 | O72: 71813 | P72: =IFERROR(O72/N72,0) -> 1 | Q72: =N72-(IF(ISBLANK(O72),N72,O72)) -> 0 | R72: =IFERROR(Q72/N72,0) -> 0
A73: 72 | B73: Pros | C73: Master Data | D73: Material/Product | E73: Onity APAC | G73: TRUE | H73: TRUE | I73: TRUE | J73: TRUE | K73: =REPT("|||||||||||||||||||||||",COUNTIF(G73:J73,TRUE)) -> |||||||||||||||||||||||||||||||||||||||||||||||||||||||||||||||||||||||||||||||||||||||||||| | L73: =TEXT(COUNTIF(G73:J73,TRUE)/COLUMNS(G73:J73),"0%") -> 100% | M73: 45961 | N73: 1623 | O73: 1623 | P73: =IFERROR(O73/N73,0) -> 1 | Q73: =N73-(IF(ISBLANK(O73),N73,O73)) -> 0 | R73: =IFERROR(Q73/N73,0) -> 0
A74: 73 | B74: Pros | C74: Master Data | D74: Price | E74: Onity APAC | G74: TRUE | H74: TRUE | I74: TRUE | J74: TRUE | K74: =REPT("|||||||||||||||||||||||",COUNTIF(G74:J74,TRUE)) -> |||||||||||||||||||||||||||||||||||||||||||||||||||||||||||||||||||||||||||||||||||||||||||| | L74: =TEXT(COUNTIF(G74:J74,TRUE)/COLUMNS(G74:J74),"0%") -> 100% | M74: 45961 | N74: 2248 | O74: 2248 | P74: =IFERROR(O74/N74,0) -> 1 | Q74: =N74-(IF(ISBLANK(O74),N74,O74)) -> 0 | R74: =IFERROR(Q74/N74,0) -> 0
A75: 74 | B75: eCommerce | C75: Master Data | D75: Contact | E75: Onity NA | F75: Anne Kelly - CS | G75: TRUE | H75: TRUE | I75: TRUE | J75: TRUE | K75: =REPT("|||||||||||||||||||||||",COUNTIF(G75:J75,TRUE)) -> |||||||||||||||||||||||||||||||||||||||||||||||||||||||||||||||||||||||||||||||||||||||||||| | L75: =TEXT(COUNTIF(G75:J75,TRUE)/COLUMNS(G75:J75),"0%") -> 100% | M75: 45968 | N75: 3614 | O75: 3614 | P75: =IFERROR(O75/N75,0) -> 1 | Q75: =N75-(IF(ISBLANK(O75),N75,O75)) -> 0 | R75: =IFERROR(Q75/N75,0) -> 0
A76: 75 | B76: Portal | C76: Master Data | D76: Contact (Portal) - WPHID | E76: Onity NA | G76: TRUE | H76: TRUE | I76: TRUE | J76: TRUE | K76: =REPT("|||||||||||||||||||||||",COUNTIF(G76:J76,TRUE)) -> |||||||||||||||||||||||||||||||||||||||||||||||||||||||||||||||||||||||||||||||||||||||||||| | L76: =TEXT(COUNTIF(G76:J76,TRUE)/COLUMNS(G76:J76),"0%") -> 100% | M76: 45968 | N76: 3614 | O76: 3614 | P76: =IFERROR(O76/N76,0) -> 1 | Q76: =N76-(IF(ISBLANK(O76),N76,O76)) -> 0 | R76: =IFERROR(Q76/N76,0) -> 0
A77: 76 | B77: Portal | C77: Master Data | D77: Contact (Portal) - PURID | E77: Onity NA | G77: TRUE | H77: TRUE | I77: TRUE | J77: TRUE | K77: =REPT("|||||||||||||||||||||||",COUNTIF(G77:J77,TRUE)) -> |||||||||||||||||||||||||||||||||||||||||||||||||||||||||||||||||||||||||||||||||||||||||||| | L77: =TEXT(COUNTIF(G77:J77,TRUE)/COLUMNS(G77:J77),"0%") -> 100% | M77: 45968 | N77: 3614 | O77: 3614 | P77: =IFERROR(O77/N77,0) -> 1 | Q77: =N77-(IF(ISBLANK(O77),N77,O77)) -> 0 | R77: =IFERROR(Q77/N77,0) -> 0
A78: 77 | B78: Portal | C78: Transactional Data | D78: Orders | E78: Onity NA | G78: TRUE | H78: TRUE | I78: TRUE | J78: TRUE | K78: =REPT("|||||||||||||||||||||||",COUNTIF(G78:J78,TRUE)) -> |||||||||||||||||||||||||||||||||||||||||||||||||||||||||||||||||||||||||||||||||||||||||||| | L78: =TEXT(COUNTIF(G78:J78,TRUE)/COLUMNS(G78:J78),"0%") -> 100% | M78: 45968 | N78: 3118 | O78: 3100 | P78: =IFERROR(O78/N78,0) -> 0.99422707 | Q78: =N78-(IF(ISBLANK(O78),N78,O78)) -> 18 | R78: =IFERROR(Q78/N78,0) -> 0.0057729314
A79: 78 | B79: ELMS | C79: Master Data | D79: Material/Product | E79: Lenel APAC | F79: John H Debora Simson | G79: TRUE | H79: TRUE | I79: TRUE | J79: TRUE | K79: =REPT("|||||||||||||||||||||||",COUNTIF(G79:J79,TRUE)) -> |||||||||||||||||||||||||||||||||||||||||||||||||||||||||||||||||||||||||||||||||||||||||||| | L79: =TEXT(COUNTIF(G79:J79,TRUE)/COLUMNS(G79:J79),"0%") -> 100% | M79: 45961 | N79: 17 | O79: 17 | P79: =IFERROR(O79/N79,0) -> 1 | Q79: =N79-(IF(ISBLANK(O79),N79,O79)) -> 0 | R79: =IFERROR(Q79/N79,0) -> 0
A80: 79 | B80: ELMS | C80: Master Data | D80: Price | E80: Lenel APAC | G80: TRUE | H80: TRUE | I80: TRUE | J80: TRUE | K80: =REPT("|||||||||||||||||||||||",COUNTIF(G80:J80,TRUE)) -> |||||||||||||||||||||||||||||||||||||||||||||||||||||||||||||||||||||||||||||||||||||||||||| | L80: =TEXT(COUNTIF(G80:J80,TRUE)/COLUMNS(G80:J80),"0%") -> 100% | M80: 45961 | N80: 17 | O80: 17 | P80: =IFERROR(O80/N80,0) -> 1 | Q80: =N80-(IF(ISBLANK(O80),N80,O80)) -> 0 | R80: =IFERROR(Q80/N80,0) -> 0
A81: 80 | B81: ELMS | C81: Master Data | D81: Contact (Portal) | E81: Lenel APAC | G81: TRUE | H81: TRUE | I81: TRUE | J81: TRUE | K81: =REPT("|||||||||||||||||||||||",COUNTIF(G81:J81,TRUE)) -> |||||||||||||||||||||||||||||||||||||||||||||||||||||||||||||||||||||||||||||||||||||||||||| | L81: =TEXT(COUNTIF(G81:J81,TRUE)/COLUMNS(G81:J81),"0%") -> 100% | M81: 45961 | N81: 19 | O81: 19 | P81: =IFERROR(O81/N81,0) -> 1 | Q81: =N81-(IF(ISBLANK(O81),N81,O81)) -> 0 | R81: =IFERROR(Q81/N81,0) -> 0
A82: 81 | B82: Contact Center | C82: Master Data | D82: Contact | E82: Onity NA | F82: Anne Kelly | G82: TRUE | H82: TRUE | I82: TRUE | J82: TRUE | K82: =REPT("|||||||||||||||||||||||",COUNTIF(G82:J82,TRUE)) -> |||||||||||||||||||||||||||||||||||||||||||||||||||||||||||||||||||||||||||||||||||||||||||| | L82: =TEXT(COUNTIF(G82:J82,TRUE)/COLUMNS(G82:J82),"0%") -> 100% | M82: 45961 | N82: 152942 | O82: 152942 | P82: =IFERROR(O82/N82,0) -> 1 | Q82: =N82-(IF(ISBLANK(O82),N82,O82)) -> 0 | R82: =IFERROR(Q82/N82,0) -> 0

Sheet Dashboard_Data Upload Count
A1: # | B1: Key Data Objects | C1: Source | D1: Target | E1: Master Data / Transactional Data | F1: Ent. IT Focal (Migration) | G1: BA IT Focal (Validation) | H1: Business Focal Name (Validation) Onity NA | I1: Business Focal Name (Validation) Onity EMEA | J1: Business Focal Name (Validation) Onity APAC | K1: Business Focal Name (Validation) Lenel APAC | L1: Production Load Progress | M1: Data Extract, upload Link path | N1: Expected Records in PROD Onity NA | O1: Expected Records in PROD Onity EMEA | P1: Expected Records in PROD Onity APAC | Q1: Expected Records in PROD Lenel APAC | R1: Loaded Records in PROD Onity NA | S1: Loaded Records in PROD Onity EMEA | T1: Loaded Records in PROD Onity APAC | U1: Loaded Records in PROD Lenel APAC | V1: % Loaded | W1: % Problem | X1: Remarks
A2: 1 | B2: Contacts | C2: GDM SFDC | D2: Contact Center | E2: Master Data | F2: Nagendra | G2: Chris Taylor Czerwinski, Ron | H2: Anne Kelly | I2: NA | J2: NA | K2: NA | L2: Not Started | N2: 124402 | O2: NA | P2: NA | Q2: NA | R2: 124402 | S2: NA | T2: NA | U2: NA
A3: 2 | B3: Material | C3: ERP | D3: CPQ | E3: Master Data | F3: Ashutosh Mishra | G3: Amit / Ambresh | H3: Shedd, Nicole Bevins, Brian | I3: Piorno, Abelardo | J3: Aggarwal, Dhruv Ganta, Manoj Kumar | K3: Aggarwal, Dhruv Ganta, Manoj Kumar | L3: Not Started | N3: 5450 | O3: 5969 | Q3: 5000 | R3: 5450 | S3: 5969
A4: 3 | B4: Price | C4: ERP | D4: CPQ | E4: Master Data | G4: Amit / Ambresh | L4: Not Started | N4: 5450 | O4: 5969 | Q4: 5000 | R4: 5450 | S4: 5969
A5: 4 | B5: Region Mapping (CT_OGC_REGION_MAPPING) | C5: Business/ Manual | D5: CPQ | E5: Master Data | G5: Amit / Ambresh | L5: Not Started
A6: 5 | B6: Contract (CT_AS_CONTRACT_ZA_ZL) | C6: Business/ Manual | D6: CPQ | E6: Master Data | G6: Amit / Ambresh | L6: Not Started
A7: 6 | B7: Material | C7: ERP / EPIM | D7: E-Commerce | E7: Master Data | F7: Sunny Pachnanda | G7: Saquib Imam | H7: Anne Kelly | I7: NA | J7: NA | K7: NA | L7: Not Started | N7: 18 | O7: NA | P7: NA | Q7: NA | S7: NA | T7: NA | U7: NA
A8: 7 | B8: Accounts (Buying) | C8: ERP | D8: E-Commerce | E8: Master Data | F8: Saquib Imam | G8: Saquib Imam | L8: Not Started | N8: 18 | O8: NA | P8: NA | Q8: NA | S8: NA | T8: NA | U8: NA
A9: 8 | B9: Credit Card MID | C9: NA | D9: E-Commerce | E9: Master Data | L9: Not Started | N9: 18
A10: 9 | B10: Price | C10: ERP | D10: E-Commerce | E10: Master Data | F10: Saquib Imam | G10: Saquib Imam | L10: Not Started | N10: 18 | O10: NA | P10: NA | Q10: NA | S10: NA | T10: NA | U10: NA
A11: 10 | B11: Leads | C11: HubSpot | D11: GDM Marketo | E11: Transactional Data | F11: Rawat Devendra Singh | G11: Amandeep | H11: Kendall Simich | I11: Kendall Simich | J11: NA | K11: NA | L11: Not Started
A12: 11 | B12: Accounts (Buying) | C12: Source SFDC | D12: GDM SFDC | E12: Master Data | F12: Yaswanth\Divya | G12: Amit / Ambresh | H12: Brain Bevins - Sales Kelly Anne - CS Chris Taylor - TC | I12: Piorno Abelardo Sonia Estrada | J12: Chin Edmond- RoA Suriati Nur- GC, RoA David Carran- Ken Ong - ANZ James Eapen- Ind | K12: Suriati Nur- RoA, GC Ken Ong - ANZ James Eapen- Ind | L12: Not Started | N12: 6603 | O12: 8281 | P12: 26 | Q12: 1160 | R12: 6603 | S12: 8281 | T12: 26 | U12: 1160
A13: 12 | B13: Accounts (Non-Buying) | C13: Source SFDC | D13: GDM SFDC | E13: Master Data | G13: Amit / Ambresh | L13: Not Started | N13: 113845 | O13: 25901 | P13: NA | Q13: 9832 | R13: 113039 | S13: 25901 | T13: NA | U13: 9832
A14: 13 | B14: Source systems | C14: Source SFDC | D14: GDM SFDC | E14: Master Data | G14: Amit / Ambresh | L14: Not Started | N14: 19884 | O14: 29328 | P14: 13741 | Q14: 13741 | R14: 19884 | S14: 29328 | T14: 13741 | U14: 13741
A15: 14 | B15: Contact | C15: Source SFDC | D15: GDM SFDC | E15: Master Data | G15: Amit / Ambresh | L15: Not Started | N15: 199001 | O15: 25223 | P15: 25 | Q15: 4936 | R15: 191540 | S15: 12918 | T15: 25 | U15: 4936
A16: 15 | B16: Account contact relationship | C16: Source SFDC | D16: GDM SFDC | E16: Transactional Data | G16: Amit / Ambresh | L16: Not Started | N16: 2927 | O16: NA | P16: 25 | R16: 2783 | S16: NA | T16: 25
A17: 16 | B17: Account Team | C17: Source SFDC | D17: GDM SFDC | E17: Master Data | G17: Amit / Ambresh | L17: Not Started | N17: 268394 | O17: 103900 | P17: NA | R17: 78810 | S17: 54996 | T17: NA
A18: 17 | B18: Lead | C18: Source SFDC | D18: GDM SFDC | E18: Transactional Data | G18: Amit / Ambresh | L18: Not Started | N18: 352 | O18: 3085 | P18: NA | Q18: NA | R18: 352 | T18: NA | U18: NA
A19: 18 | B19: Opportunity | C19: Source SFDC | D19: GDM SFDC | E19: Transactional Data | G19: Amit / Ambresh | L19: Not Started | N19: 10810 | O19: 31701 | P19: NA | Q19: 1544 | R19: 10810 | S19: 5652 | T19: NA | U19: 1168
A20: 19 | B20: Opportunity team member | C20: Source SFDC | D20: GDM SFDC | E20: Transactional Data | G20: Amit / Ambresh | L20: Not Started | N20: NA | O20: NA | P20: NA | Q20: NA | R20: NA | S20: NA | T20: NA | U20: NA
A21: 20 | B21: Contract | C21: Source SFDC | D21: GDM SFDC | E21: Transactional Data | G21: Amit / Ambresh | L21: Not Started | N21: 5491 | O21: 11764 | P21: NA | Q21: 34 | R21: 5491 | T21: NA | U21: 34
A22: 21 | B22: Product | C22: Source SFDC | D22: GDM SFDC | E22: Master Data | G22: Amit / Ambresh | L22: Not Started | N22: NA | O22: 8000 | P22: NA | Q22: NA | R22: NA | S22: 8000 | T22: NA | U22: NA
A23: 22 | B23: Cases | C23: Source SFDC | D23: GDM SFDC | E23: Transactional Data | G23: Amit /Ron | L23: Not Started | N23: 102614 | O23: 1726 | P23: NA | Q23: NA | R23: 77558 | S23: 26 | T23: NA | U23: NA
A24: 23 | B24: Account Configuration | C24: Source SFDC | D24: GDM SFDC | E24: Transactional Data | L24: Not Started | N24: 113554 | O24: NA | P24: NA | Q24: NA | R24: 86642 | S24: NA | T24: NA | U24: NA
A25: 24 | B25: Knowledge articles | C25: Source SFDC | D25: GDM SFDC | E25: Transactional Data | G25: Amit /Ron | L25: Not Started | N25: 344 | O25: NA | P25: NA | Q25: NA | R25: 344 | S25: NA | T25: NA | U25: NA
A26: 25 | B26: Accounts (Buying & Non-Buying) | C26: GDM SFDC | D26: Portal | E26: Master Data | F26: Kaustav | G26: Saquib Imam | H26: Anne Kelly Brain Bevins - Sales Kelly Anne - CS | I26: NA | J26: NA | K26: NA | L26: Not Started | N26: 3016 | O26: NA | P26: NA | Q26: NA | S26: NA | T26: NA | U26: NA
A27: 26 | B27: Contact | C27: GDM SFDC | D27: Portal | E27: Master Data | L27: Not Started | N27: 3646 | O27: NA | P27: NA | Q27: NA | S27: NA | T27: NA | U27: NA
A28: 27 | B28: Contact (Portal) - WPHID | C28: GDM SFDC | D28: Portal | E28: Master Data | L28: Not Started | N28: 3646 | O28: NA | P28: NA | Q28: NA | S28: NA | T28: NA | U28: NA
A29: 28 | B29: Contact (Portal) - PURID | C29: GDM SFDC | D29: Portal | E29: Master Data | L29: Not Started | N29: 3646 | O29: NA | P29: NA | Q29: NA | S29: NA | T29: NA | U29: NA
A30: 29 | B30: Var Agreements | C30: GDM SFDC | D30: Portal | E30: Transactional Data | F30: Sunny Pachnanda | G30: Saquib Imam | H30: Anne Kelly / Brain Bevins - Sales Kelly Anne - CS | I30: NA | J30: NA | K30: NA | L30: Not Started | N30: 18 | O30: NA | P30: NA | Q30: NA | S30: NA | T30: NA | U30: NA
A31: 30 | B31: Material/Product | C31: EPIM | D31: Portal | E31: Master Data | L31: Not Started | O31: NA | P31: NA | Q31: NA | S31: NA | T31: NA | U31: NA
A32: 31 | B32: Cases | C32: GDM SFDC | D32: Portal | E32: Transactional Data | L32: Not Started | O32: NA | P32: NA | Q32: NA | S32: NA | T32: NA | U32: NA
A33: 32 | B33: Software Metadata | C33: Azure Blob | D33: Portal | E33: Master Data | L33: Not Started | O33: NA | P33: NA | Q33: NA | S33: NA | T33: NA | U33: NA
A34: 33 | B34: Orders | C34: ERP | D34: Portal | E34: Transactional Data | L34: Not Started | O34: NA | P34: NA | Q34: NA | S34: NA | T34: NA | U34: NA
A35: 34 | B35: Material/Product | C35: ERP | D35: Pros | E35: Master Data | F35: Vimal Kumar | G35: Amit Choudhry | H35: Nicole Shedd | I35: Julian Nieto | J35: Edmond Chin | K35: Ken Ong James Eapen Michael Xu | L35: Not Started | N35: 5022 | O35: 5569 | P35: 4656 | Q35: 2066 | R35: 5052 | S35: 5569 | T35: 4656 | U35: 2066
A36: 35 | B36: Price | C36: Business/ Manual | D36: Pros | E36: Master Data | G36: Amit Choudhry | L36: Not Started | N36: 4943 | O36: 130000 | P36: 1092 | Q36: 5538 | T36: 329 | U36: 3551
A37: 36 | B37: Material/Product | C37: ERP | D37: Zuora | E37: Master Data | F37: Mahesh K/ Channa Bassava / Dumpala, Sudhakar/ | H37: Anne Kelly | I37: Piorno, Abelardo Sonia Estracia | J37: Chin Edmond- RoA Suriati Nur- GC, RoA David Carran- Ken Ong - ANZ James Eapen- Ind | K37: James Eapen | L37: Not Started | N37: 19 | O37: 19 | P37: 19 | Q37: 0 | R37: 19 | S37: 19 | T37: 19
A38: 37 | B38: Price | C38: ERP | D38: Zuora | E38: Master Data | L38: Not Started | N38: NA | O38: NA | P38: NA | Q38: NA
A39: 38 | B39: Accounts (Buying) | C39: ERP | D39: Zuora | E39: Master Data | G39: Saquib Imam | L39: Not Started
A40: 39 | B40: End user accounts | C40: SFDC | D40: Zuora | E40: Master Data | G40: Saquib Imam | L40: Not Started | N40: NA | O40: NA | P40: NA
A41: 40 | B41: Subscriptions (Assets) - Blue Diamond | C41: GDM SFDC (AMS) | D41: Zuora (LS2 APAC) | E41: Transactional Data | L41: Not Started
A42: 41 | B42: Subscriptions - OnPortal Renewal Subscriptions(EMEA) | C42: OnityNet - Report from Business | D42: Zuora | E42: Transactional Data | G42: Saquib Imam | L42: Not Started | N42: 1000 | P42: 0
A43: 42 | B43: Subscriptions - OnPortal Renewal Subscriptions(APAC) | C43: OnityNet - Report from Business | D43: Zuora | E43: Transactional Data | L43: Not Started | P43: 0
A44: 43 | B44: Subscriptions - Direct Key (NA Region) | C44: CoreAPI & OnityNet - Report from Business | D44: Zuora | E44: Transactional Data | L44: Not Started
A45: 44 | B45: Subscriptions - Direct Key (EMEA Region) | C45: CoreAPI & OnityNet - Report from Business | D45: Zuora | E45: Transactional Data | L45: Not Started
A46: 45 | B46: Subscriptions - Direct Key (APAC Region) | C46: CoreAPI & OnityNet - Report from Business | D46: Zuora | E46: Transactional Data | G46: Saquib Imam | L46: Not Started
A47: 46 | B47: Material/Product | C47: ERP | D47: ELMS | E47: Master Data | F47: Sreeram Girish | G47: Karl Vondrak/Steve | H47: NA | I47: NA | J47: NA | K47: ALL- John H and Debora Simson | L47: Not Started | M47: ELMS - Data Validation | N47: NA | O47: NA | P47: NA | Q47: 17 | R47: NA | S47: NA | T47: NA | U47: 17
A48: 47 | B48: Price | C48: ERP | D48: ELMS | E48: Master Data | L48: Not Started | N48: NA | O48: NA | P48: NA | Q48: 17 | R48: NA | S48: NA | T48: NA | U48: 17
A49: 48 | B49: Contacts (Portal) | C49: GDM SFDC | D49: ELMS | E49: Master Data | L49: Not Started | N49: NA | O49: NA | P49: NA | R49: NA | S49: NA | T49: NA
A50: 49 | B50: Training | C50: GDM SFDC | D50: ELMS | E50: Transactional Data | L50: Not Started | N50: NA | O50: NA | P50: NA | R50: NA | S50: NA | T50: NA
A51: 50 | B51: SMS - Price Book Entry | C51: SAP | D51: SMS SFDC | E51: Transactional Data | F51: Geethanjali | G51: Bhanu | H51: Brain Bevins - Sales Kelly Anne - CS Chris Taylor - TC | I51: Piorno Abelardo Sonia Estrada | J51: Chin Edmond- RoA Suriati Nur- GC, RoA David Carran- Ken Ong - ANZ James Eapen- Ind | K51: Chin Edmond- RoA Suriati Nur- GC, RoA David Carran- Ken Ong - ANZ James Eapen- Ind | L51: Not Started
A52: 51 | B52: SMS - Skill | C52: SFDC | D52: SMS SFDC | E52: Transactional Data | L52: Not Started
A53: 52 | B53: SMS - Subcontractor Contacts | C53: SFDC | D53: SMS SFDC | E53: Transactional Data | L53: Not Started
A54: 53 | B54: SMS - Service Resources (Subcontractors and internal) | C54: SFDC | D54: SMS SFDC | E54: Transactional Data | L54: Not Started
A55: 54 | B55: SMS - Work Type | C55: SFDC | D55: SMS SFDC | E55: Transactional Data | L55: Not Started
A56: 55 | B56: SMS - Skill Requirmenet | C56: SFDC | D56: SMS SFDC | E56: Transactional Data | L56: Not Started
A57: 56 | B57: SMS - Discipline | C57: SFDC | D57: SMS SFDC | E57: Master Data | L57: Not Started
A58: 57 | B58: SMS - Work Type GAR | C58: SFDC | D58: SMS SFDC | E58: Master Data | L58: Not Started
A59: 58 | B59: SMS - Maintenance Template GAR | C59: SFDC | D59: SMS SFDC | E59: Transactional Data | L59: Not Started
A60: 59 | B60: SMS - Work Plan Template GAR | C60: SFDC | D60: SMS SFDC | E60: Master Data | L60: Not Started
A61: 60 | B61: SMS - Work Step Template GAR | C61: SFDC | D61: SMS SFDC | E61: Master Data | L61: Not Started
A62: 61 | B62: SMS - WorkPlan TemplateEntry GAR | C62: SFDC | D62: SMS SFDC | E62: Master Data | L62: Not Started
A63: 62 | B63: SMS - Work Plan Selection Rule GAR | C63: SFDC | D63: SMS SFDC | E63: Transactional Data | L63: Not Started
... A76: 75 | B76: SMS - Agreement Level | C76: SFDC | D76: SMS SFDC | E76: Transactional Data | L76: Not Started

Sheet ERP Data Score Card - UAT
A1: S.No | B1: System | C1: Data Object Type | D1: Data Object | E1: Region | F1: Business Focal | G1: Identify CDE | H1: Prep Data | I1: Load | J1: Validation | K1: Status % | L1: Progress | M1: ETA for Load | N1: Expected Records (UAT) | O1: Loaded Records (UAT) | P1: % Loaded (UAT) | Q1: Missed Records (UAT) | R1: % Problem (UAT) | S1: Remarks / Comments during UAT
A2: 1 | B2: SAP BRV | C2: ='ERP UAT Tracker'!A2 -> Master | D2: ='ERP UAT Tracker'!B2 -> Customers - External (w/Credit Limits) and Internal | E2: All | G2: TRUE | H2: TRUE | I2: TRUE | J2: FALSE | K2: =REPT("|||||||||||||||||||||||",COUNTIF(G2:J2,TRUE)) -> ||||||||||||||||||||||||||||||||||||||||||||||||||||||||||||||||||||| | L2: =TEXT(COUNTIF(G2:J2,TRUE)/COLUMNS(G2:J2),"0%") -> 75% | N2: ='ERP UAT Tracker'!D2 -> 41829 | O2: ='ERP UAT Tracker'!E2 -> 41819 | P2: =IFERROR(O2/N2,0) -> 0.99976093 | Q2: =N2-O2 -> 10 | R2: =IFERROR(Q2/N2,0) -> 0.00023906859
A3: 2 | B3: SAP BRV | C3: ='ERP UAT Tracker'!A3 -> Master | D3: ='ERP UAT Tracker'!B3 -> Customers - POSO | E3: All | G3: TRUE | H3: TRUE | I3: TRUE | J3: FALSE | K3: =REPT("|||||||||||||||||||||||",COUNTIF(G3:J3,TRUE)) -> ||||||||||||||||||||||||||||||||||||||||||||||||||||||||||||||||||||| | L3: =TEXT(COUNTIF(G3:J3,TRUE)/COLUMNS(G3:J3),"0%") -> 75% | N3: ='ERP UAT Tracker'!D3 -> 0 | O3: ='ERP UAT Tracker'!E3 -> 0 | P3: =IFERROR(O3/N3,0) -> 0 | Q3: =N3-O3 -> 0 | R3: =IFERROR(Q3/N3,0) -> 0
A4: 3 | B4: SAP BRV | C4: ='ERP UAT Tracker'!A4 -> Master | D4: ='ERP UAT Tracker'!B4 -> HR Records | E4: All | G4: TRUE | H4: TRUE | I4: TRUE | J4: FALSE | K4: =REPT("|||||||||||||||||||||||",COUNTIF(G4:J4,TRUE)) -> ||||||||||||||||||||||||||||||||||||||||||||||||||||||||||||||||||||| | L4: =TEXT(COUNTIF(G4:J4,TRUE)/COLUMNS(G4:J4),"0%") -> 75% | N4: ='ERP UAT Tracker'!D4 -> 411 | O4: ='ERP UAT Tracker'!E4 -> 270 | P4: =IFERROR(O4/N4,0) -> 0.65693431 | Q4: =N4-O4 -> 141 | R4: =IFERROR(Q4/N4,0) -> 0.34306569
A5: 4 | B5: SAP BRV | C5: ='ERP UAT Tracker'!A5 -> Master | D5: ='ERP UAT Tracker'!B5 -> Material Master | E5: All | G5: TRUE | H5: TRUE | I5: TRUE | J5: FALSE | K5: =REPT("|||||||||||||||||||||||",COUNTIF(G5:J5,TRUE)) -> ||||||||||||||||||||||||||||||||||||||||||||||||||||||||||||||||||||| | L5: =TEXT(COUNTIF(G5:J5,TRUE)/COLUMNS(G5:J5),"0%") -> 75% | N5: ='ERP UAT Tracker'!D5 -> 70745 | O5: ='ERP UAT Tracker'!E5 -> 70245 | P5: =IFERROR(O5/N5,0) -> 0.99293236 | Q5: =N5-O5 -> 500 | R5: =IFERROR(Q5/N5,0) -> 0.0070676373
A6: 5 | B6: SAP BRV | C6: ='ERP UAT Tracker'!A6 -> Master | D6: ='ERP UAT Tracker'!B6 -> Service Materials | E6: All | G6: TRUE | H6: TRUE | I6: TRUE | J6: FALSE | K6: =REPT("|||||||||||||||||||||||",COUNTIF(G6:J6,TRUE)) -> ||||||||||||||||||||||||||||||||||||||||||||||||||||||||||||||||||||| | L6: =TEXT(COUNTIF(G6:J6,TRUE)/COLUMNS(G6:J6),"0%") -> 75% | N6: ='ERP UAT Tracker'!D6 -> 482 | O6: ='ERP UAT Tracker'!E6 -> 449 | P6: =IFERROR(O6/N6,0) -> 0.93153527 | Q6: =N6-O6 -> 33 | R6: =IFERROR(Q6/N6,0) -> 0.06846473
A7: 6 | B7: SAP BRV | C7: ='ERP UAT Tracker'!A7 -> Master | D7: ='ERP UAT Tracker'!B7 -> Vendor - POSO | E7: All | G7: TRUE | H7: TRUE | I7: TRUE | J7: FALSE | K7: =REPT("|||||||||||||||||||||||",COUNTIF(G7:J7,TRUE)) -> ||||||||||||||||||||||||||||||||||||||||||||||||||||||||||||||||||||| | L7: =TEXT(COUNTIF(G7:J7,TRUE)/COLUMNS(G7:J7),"0%") -> 75% | N7: ='ERP UAT Tracker'!D7 -> 0 | O7: ='ERP UAT Tracker'!E7 -> 0 | P7: =IFERROR(O7/N7,0) -> 0 | Q7: =N7-O7 -> 0 | R7: =IFERROR(Q7/N7,0) -> 0
A8: 7 | B8: SAP BRV | C8: ='ERP UAT Tracker'!A8 -> Master | D8: ='ERP UAT Tracker'!B8 -> Vendors - External and Internal | E8: All | G8: TRUE | H8: TRUE | I8: TRUE | J8: FALSE | K8: =REPT("|||||||||||||||||||||||",COUNTIF(G8:J8,TRUE)) -> ||||||||||||||||||||||||||||||||||||||||||||||||||||||||||||||||||||| | L8: =TEXT(COUNTIF(G8:J8,TRUE)/COLUMNS(G8:J8),"0%") -> 75% | N8: ='ERP UAT Tracker'!D8 -> 1947 | O8: ='ERP UAT Tracker'!E8 -> 1483 | P8: =IFERROR(O8/N8,0) -> 0.76168464 | Q8: =N8-O8 -> 464 | R8: =IFERROR(Q8/N8,0) -> 0.23831536
A9: 8 | B9: SAP BRV | C9: ='ERP UAT Tracker'!A9 -> Sub-master | D9: ='ERP UAT Tracker'!B9 -> Bill of Materials | E9: All | G9: TRUE | H9: TRUE | I9: TRUE | J9: FALSE | K9: =REPT("|||||||||||||||||||||||",COUNTIF(G9:J9,TRUE)) -> ||||||||||||||||||||||||||||||||||||||||||||||||||||||||||||||||||||| | L9: =TEXT(COUNTIF(G9:J9,TRUE)/COLUMNS(G9:J9),"0%") -> 75% | N9: ='ERP UAT Tracker'!D9 -> 134193 | O9: ='ERP UAT Tracker'!E9 -> 134059 | P9: =IFERROR(O9/N9,0) -> 0.99900144 | Q9: =N9-O9 -> 134 | R9: =IFERROR(Q9/N9,0) -> 0.00099856177
A10: 9 | B10: SAP BRV | C10: ='ERP UAT Tracker'!A10 -> Sub-master | D10: ='ERP UAT Tracker'!B10 -> Contact Person | E10: All | G10: TRUE | H10: TRUE | I10: TRUE | J10: FALSE | K10: =REPT("|||||||||||||||||||||||",COUNTIF(G10:J10,TRUE)) -> ||||||||||||||||||||||||||||||||||||||||||||||||||||||||||||||||||||| | L10: =TEXT(COUNTIF(G10:J10,TRUE)/COLUMNS(G10:J10),"0%") -> 75% | N10: ='ERP UAT Tracker'!D10 -> 21030 | O10: ='ERP UAT Tracker'!E10 -> 21014 | P10: =IFERROR(O10/N10,0) -> 0.99923918 | Q10: =N10-O10 -> 16 | R10: =IFERROR(Q10/N10,0) -> 0.00076081788
A11: 10 | B11: SAP BRV | C11: ='ERP UAT Tracker'!A11 -> Sub-master | D11: ='ERP UAT Tracker'!B11 -> Customer - International Versions | E11: All | G11: TRUE | H11: TRUE | I11: TRUE | J11: TRUE | K11: =REPT("|||||||||||||||||||||||",COUNTIF(G11:J11,TRUE)) -> |||||||||||||||||||||||||||||||||||||||||||||||||||||||||||||||||||||||||||||||||||||||||||| | L11: =TEXT(COUNTIF(G11:J11,TRUE)/COLUMNS(G11:J11),"0%") -> 100% | N11: ='ERP UAT Tracker'!D11 -> 50 | O11: ='ERP UAT Tracker'!E11 -> 50 | P11: =IFERROR(O11/N11,0) -> 1 | Q11: =N11-O11 -> 0 | R11: =IFERROR(Q11/N11,0) -> 0
A12: 11 | B12: SAP BRV | C12: ='ERP UAT Tracker'!A12 -> Sub-master | D12: ='ERP UAT Tracker'!B12 -> Discounts and Surcharges | E12: All | G12: TRUE | H12: TRUE | I12: TRUE | J12: FALSE | K12: =REPT("|||||||||||||||||||||||",COUNTIF(G12:J12,TRUE)) -> ||||||||||||||||||||||||||||||||||||||||||||||||||||||||||||||||||||| | L12: =TEXT(COUNTIF(G12:J12,TRUE)/COLUMNS(G12:J12),"0%") -> 75% | N12: ='ERP UAT Tracker'!D12 -> 0 | O12: ='ERP UAT Tracker'!E12 -> 0 | P12: =IFERROR(O12/N12,0) -> 0 | Q12: =N12-O12 -> 0 | R12: =IFERROR(Q12/N12,0) -> 0
A13: 12 | B13: SAP BRV | C13: ='ERP UAT Tracker'!A13 -> Sub-master | D13: ='ERP UAT Tracker'!B13 -> Production Versions | E13: All | G13: TRUE | H13: FALSE | I13: FALSE | J13: FALSE | K13: =REPT("|||||||||||||||||||||||",COUNTIF(G13:J13,TRUE)) -> ||||||||||||||||||||||| | L13: =TEXT(COUNTIF(G13:J13,TRUE)/COLUMNS(G13:J13),"0%") -> 25% | N13: ='ERP UAT Tracker'!D13 -> 0 | O13: ='ERP UAT Tracker'!E13 -> 0 | P13: =IFERROR(O13/N13,0) -> 0 | Q13: =N13-O13 -> 0 | R13: =IFERROR(Q13/N13,0) -> 0
... A43: 42 | B43: SAP BRV | C43: ='ERP UAT Tracker'!A43 -> Transactional | D43: ='ERP UAT Tracker'!B43 -> Service Orders | E43: All | G43: TRUE | H43: FALSE | I43: FALSE | J43: FALSE | K43: =REPT("|||||||||||||||||||||||",COUNTIF(G43:J43,TRUE)) -> ||||||||||||||||||||||| | L43: =TEXT(COUNTIF(G43:J43,TRUE)/COLUMNS(G43:J43),"0%") -> 25% | N43: ='ERP UAT Tracker'!D43 -> 0 | O43: ='ERP UAT Tracker'!E43 -> 0 | P43: =IFERROR(O43/N43,0) -> 0 | Q43: =N43-O43 -> 0 | R43: =IFERROR(Q43/N43,0) -> 0

Sheet ERP UAT Tracker
A1: Object Type | B1: Data Object | C1: Load Type | D1: Total # in Scope | E1: Loaded in SAP | F1: Score (%) | G1: SC Defect Count | H1: SC Failing Rules | I1: Scorecard Completion | J1: Load Approval | K1: Load | L1: Validation | M1: JIRA Data Defects
A2: Master | B2: Customers - External (w/Credit Limits) and Internal | C2: Automated | D2: 41829 | E2: 41819 | F2: 0.99976093 | G2: 20 | H2: 2 | I2: Complete | J2: Complete | K2: Complete | L2: 31-Mar-25 | M2: 55
A3: Master | B3: Customers - POSO | C3: Manual | J3: Complete | K3: Complete | L3: 27-Mar-25
A4: Master | B4: HR Records | C4: Automated | D4: 411 | E4: 270 | F4: 0.65693431 | G4: 148 | H4: 3 | I4: Complete | J4: Complete | K4: Complete | L4: 12-Mar-25
A5: Master | B5: Material Master | C5: Automated | D5: 70745 | E5: 70245 | F5: 0.99293236 | G5: 502 | H5: 10 | I5: Complete | J5: Complete | K5: Complete | L5: 04-Apr-25 | M5: 46
A6: Master | B6: Service Materials | C6: Automated | D6: 482 | E6: 449 | F6: 0.93153527 | G6: 33 | H6: 7 | I6: Complete | J6: Complete | K6: Complete | L6: 04-Apr-25 | M6: 2
A7: Master | B7: Vendor - POSO | C7: Manual | J7: Complete | K7: Complete | L7: 27-Mar-25
A8: Master | B8: Vendors - External and Internal | C8: Automated | D8: 1947 | E8: 1483 | F8: 0.76168464 | G8: 1220 | H8: 16 | I8: Complete | J8: Complete | K8: Complete | L8: 07-Apr-25 | M8: 121
A9: Sub-master | B9: Bill of Materials | C9: Automated | D9: 134193 | E9: 134059 | F9: 0.99900144 | G9: 134 | H9: 2 | I9: Complete | J9: Complete | K9: Complete | L9: 05-May-25
A10: Sub-master | B10: Contact Person | C10: Automated | D10: 21030 | E10: 21014 | F10: 0.99923918 | G10: 969 | H10: 4 | I10: Complete | J10: Complete | K10: Complete | L10: 07-May-25 | M10: 1
A11: Sub-master | B11: Customer - International Versions | C11: Automated | D11: 50 | E11: 50 | F11: 1 | G11: 0 | H11: 0 | I11: Complete | J11: Complete | K11: Complete | L11: Complete
A12: Sub-master | B12: Discounts and Surcharges | C12: Manual | J12: Complete | K12: Complete | L12: 06-Aug-25
A13: Sub-master | B13: Production Versions | C13: Manual | J13: 23-Aug-25 | K13: 23-Aug-25 | L13: 25-Aug-25
A14: Sub-master | B14: Project Structures | C14: Automated | D14: 1796 | E14: 1796 | F14: 1 | G14: 0 | H14: 0 | I14: 08-Aug-25 | J14: 11-Aug-25 | K14: 11-Aug-25 | L14: 14-Aug-25 | M14: 1
A15: Sub-master | B15: Purchasing Information Records | C15: Automated | D15: 23794 | E15: 23268 | F15: 0.97789359 | G15: 1427 | H15: 6 | I15: Complete | J15: Complete | K15: Complete | L15: 08-Aug-25 | M15: 24
A16: Sub-master | B16: Routings | C16: Automated | D16: 5041 | E16: 5036 | F16: 0.99900813 | G16: 5 | H16: 1 | I16: Complete | J16: Complete | K16: Complete | L16: Complete | M16: 1
A17: Sub-master | B17: Sales Reps | C17: Automated | D17: 103 | E17: 103 | F17: 1 | G17: 0 | H17: 0 | I17: Complete | J17: Complete | K17: Complete | L17: Complete
A18: Sub-master | B18: Sales Reps Assignments | C18: Automated | D18: 44255 | E18: 23320 | F18: 0.52694611 | G18: 41648 | H18: 14 | I18: Complete | J18: Complete | K18: 02-May-25 | L18: 07-May-25
A19: Sub-master | B19: Source List | C19: Manual | J19: 15-Aug-25 | K19: 15-Aug-25 | L19: 19-Aug-25
A20: Sub-master | B20: Storage Bins | C20: Manual,Automated | I20: Complete | J20: Complete | K20: Complete | L20: 28-Apr-25
A21: Sub-master | B21: Vendors - International Versions | C21: Automated | D21: 18 | E21: 17 | F21: 0.94444444 | G21: 3 | H21: 3 | I21: Complete | J21: Complete | K21: Complete | L21: Complete
A22: Sub-master | B22: Work Centers | C22: Manual | K22: Complete | L22: Complete
A23: Sub-master | B23: ZI01 Interco Transfer Pricing | C23: Manual | J23: Complete | K23: Complete | L23: 13-Aug-25
A24: Sub-master | B24: ZI02 Interco Customer Specific Pricing | C24: Manual | J24: Complete | K24: Complete | L24: 13-Aug-25
A25: Sub-master | B25: ZID1 Transfer Discount | C25: Manual | J25: Complete | K25: Complete | L25: 13-Aug-25
A26: Sub-master | B26: ZX07 Volume Discount | C26: Manual | J26: Complete | K26: Complete | L26: 13-Aug-25
A27: Sub-master | B27: ZX09 Customer Volume Discount | C27: Manual | J27: Complete | K27: Complete | L27: 13-Aug-25
A28: Sub-master | B28: ZX10 Promo Volume Disc % | C28: Manual | J28: Complete | K28: Complete | L28: 13-Aug-25
A29: Sub-master | B29: ZXPR Country Price | C29: Manual | J29: Complete | K29: Complete | L29: 13-Aug-25
A30: Transactional | B30: Fixed Assets | C30: Manual | J30: 22-Aug-25 | K30: 22-Aug-25 | L30: 27-Aug-25
A31: Transactional | B31: General Ledger Balances | C31: Manual | I31: Complete | J31: 22-Aug-25 | K31: 22-Aug-25 | L31: 27-Aug-25
A32: Transactional | B32: Goods Receipt/Invoice Receipt (GR/IR) | C32: Manual | I32: Complete | J32: 18-Aug-25 | K32: 18-Aug-25 | L32: 21-Aug-25
A33: Transactional | B33: Inventory Balance_IM | C33: Automated | D33: 3475 | E33: 3109 | F33: 0.89467626 | G33: 481 | H33: 12 | I33: Complete | J33: 21-Aug-25 | K33: 21-Aug-25 | L33: 25-Aug-25
A34: Transactional | B34: Open Accounts Payables | C34: Automated | D34: 3536 | E34: 3213 | F34: 0.90865385 | G34: 327 | H34: 6 | I34: Complete | J34: 15-Aug-25 | K34: 15-Aug-25 | L34: 18-Aug-25 | M34: 4
A35: Transactional | B35: Open Accounts Receivables | C35: Automated | D35: 16135 | E35: 10060 | F35: 0.62348931 | G35: 11554 | H35: 17 | I35: Complete | J35: 18-Aug-25 | K35: 18-Aug-25 | L35: 21-Aug-25 | M35: 1
A36: Transactional | B36: Open Purchase Orders | C36: Automated | D36: 1124 | E36: 378 | F36: 0.33629893 | G36: 2415 | H36: 16 | I36: 21-Aug-25 | J36: 25-Aug-25 | K36: 25-Aug-25 | L36: 28-Aug-25 | M36: 18
A37: Transactional | B37: Product Sales Orders | C37: Automated | D37: 5691 | E37: 4533 | F37: 0.79652082 | G37: 3179 | H37: 12 | I37: 18-Aug-25 | J37: 23-Aug-25 | K37: 23-Aug-25 | L37: 25-Aug-25 | M37: 8
A38: Transactional | B38: Project Sales Orders | C38: Automated | D38: 2986 | E38: 1349 | F38: 0.45177495 | G38: 11659 | H38: 12 | I38: 13-Aug-25 | J38: 20-Aug-25 | K38: 20-Aug-25 | L38: 22-Aug-25
A39: Transactional | B39: Sales Order History | C39: Automated | I39: 07-May-25 | J39: 08-Aug-25 | K39: 08-Aug-25 | L39: 12-Aug-25
A40: Transactional | B40: Service Contracts | C40: Automated | D40: 1131 | E40: 1126 | F40: 0.99557913 | G40: 36 | H40: 12 | I40: 12-Aug-25 | J40: 29-Aug-25 | K40: 29-Aug-25 | L40: 02-Sep-25
A41: Transactional | B41: Service Financials | C41: Manual | J41: Complete | K41: Complete | L41: 09-May-25
A42: Transactional | B42: Service Orders (Quoted Reactive) | C42: Automated | D42: 258 | E42: 222 | F42: 0.86046512 | G42: 450 | H42: 7 | I42: 13-May-25 | J42: 22-May-25 | K42: 23-May-25 | L42: 28-May-25
A43: Transactional | B43: Service Orders | C43: Automated | I43: 12-Aug-25 | J43: 15-Aug-25 | K43: 15-Aug-25 | L43: 20-Aug-25
A46: Oct 9 data

Sheet ERP Super Users
A1: Client | B1: Object Type | C1: Site | D1: Object | E1: Super User
A2: BRP | B2: Master Object | C2: Onity_JDE_HK | D2: Customer Master | E2: Irene Lau
A3: BRP | B3: Master Object | C3: Onity_JDE_MX | D3: Customer Master | E3: Castrejon Candy Joaly
A4: BRP | B4: Master Object | C4: Onity_JDE_TW | D4: Customer Master | E4: Irene Lau
A5: BRP | B5: Master Object | C5: Onity_JDE_SH | D5: Customer Master | E5: Irene Lau
A6: BRP | B6: Master Object | C6: Onity_MSD_FR | D6: Customer Master | E6: Sonia Estrada
A7: BRP | B7: Master Object | C7: Onity_MSD_SL | D7: Customer Master | E7: Sonia Estrada
A8: BRP | B8: Master Object | C8: Onity_MSD_UK | D8: Customer Master | E8: Sonia Estrada
A9: BRP | B9: Master Object | C9: Onity_Oracle_US | D9: Customer Master | E9: Tracy Gassaway
A10: BRP | B10: Master Object | C10: Onity_SAP_AU | D10: Customer Master | E10: Mylee Baston, Tracey Fox
A11: BRP | B11: Master Object | C11: Onity_SAP_IN | D11: Customer Master | E11: Manoj Ganta
A12: BRP | B12: Master Object | C12: Onity_SAP_SG | D12: Customer Master | E12: Mike Lee
... A99: BRP | B99: Submaster | C99: Onity_SAP_SG | D99: Source List | E99: Rita Chan

Sheet Onity Sales Org 
A3: 1130 | B3: US | C3: 19284
A4: 551G | B4: MX | C4: 0
A5: 3051 | B5: CH | C5: 61 | D5: APAC
A6: 588G | B6: Taiwan | C6: 0 | D6: APAC
A7: 410G | B7: HK | C7: 0
A8: 2056
A9: 253G

Sheet  Validation Readiness Status
A1: S.No | B1: Key Data Objects | C1: Source | D1: Destination | E1: Master Data / Transactional Data | F1: Ready for Validation (Y/N) | G1: Validation Readiness Date | I1: Architect Focal (Setup) | J1: BA IT Focal (Validation) | K1: Business Focal (Validation) | L1: Critical Data Elements (To be loaded into Target System
A2: 1 | B2: Material/Product | C2: ERP | D2: CPQ | E2: Master Data | F2: Y | I2: Ashutosh | J2: Amit / Ambresh | L2: SKU | M2: Description | N2: Product Catalogue | O2: Product Hierarchy | P2: Catalogue Hierarchy | Q2: Labor Cost | R2: Material Cost | S2: Sales Text | T2: Inclusion Exclusion List
A3: 2 | B3: Material/Product | C3: GDM SFDC (AMS) | D3: CPQ | E3: Master Data | F3: Y | I3: Ashutosh | J3: Amit / Ambresh | L3: Product Version | M3: Promo code | N3: Renewal SKU | O3: Product Action | P3: License Metadata
A4: 3 | B4: Price | C4: Zuora | D4: CPQ | E4: Master Data | F4: N | G4: 45827 | I4: Ashutosh | J4: Amit / Ambresh | L4: Rate Plan
A5: 4 | B5: Price | C5: ERP | D5: CPQ | E5: Master Data | F5: N | G5: 45827 | I5: Ashutosh | J5: Amit / Ambresh | L5: List Price
A6: 5 | B6: License | C6: License Editor | D6: CPQ | E6: Master Data | F6: N | G6: ? | I6: Ashutosh | J6: Amit / Ambresh | L6: Template ID & Default Version
A7: 6 | B7: Material/Product | C7: ERP | D7: Zuora | E7: Master Data | F7: Y | G7: 45833 | I7: Dumpala, Sudhakar | J7: Saquib Imam | L7: SKU | M7: Description | N7: Product Category | O7: Product Line | P7: Billing Plan
A8: 7 | B8: Price | C8: ERP | D8: Zuora | E8: Master Data | F8: N | G8: 45827 | I8: Dumpala, Sudhakar | J8: Saquib Imam | L8: Customer Price (Automated Renewal Billing)
A9: 8 | B9: Accounts (Buying) | C9: ERP | D9: Zuora | E9: Master Data | F9: Y | I9: Dumpala, Sudhakar | J9: Saquib Imam | L9: Sold-To | M9: Ship-To
A10: 9 | B10: Assets | C10: GDM SFDC (AMS) | D10: Zuora | E10: Master Data | F10: N | G10: 45837 | I10: Dumpala, Sudhakar | J10: Saquib Imam | K10: Chris Branch | Dilon | L10: Transactional - BlueDiamond Subscription Data | M10: OnGuard Subscription | N10: OnGuard Cloud Subscription | O10: BlueDiamond subscription
A11: 10 | B11: Assets | C11: Elements Portal | D11: Zuora | E11: Master Data | F11: N | G11: ? | I11: Dumpala, Sudhakar | J11: Saquib Imam | K11: Chris Branch | Dilon | L11: Transactional Elements - Subscription data
A12: 11 | B12: Entitlements | C12: Source Flexera | D12: GDM Flexera | E12: Transactional Data | F12: N | G12: ? | I12: Abhishek Singh | J12: Steve / Saquib | L12: License Metadata | M12: Entitlements | N12: Licenses Fullfilment ID | O12: Product, Features & License Model | P12: Transaction Key | Q12: Template Id
A13: 12 | B13: License | C13: CPQ/Zuora | D13: GDM Flexera | E13: Transactional Data | F13: N | G13: ? | I13: Abhishek Singh | J13: Steve / Saquib | L13: License Metadata (KeyType / Finger Print Type) | M13: License Version
A14: 13 | B14: System ID | C14: GDM SFDC (AMS) | D14: GDM Flexera | E14: Transactional Data | F14: N | G14: 45829 | I14: Abhishek Singh | J14: Steve / Saquib | L14: Sync System Id | M14: Parent System ID
A15: 14 | B15: Leads | C15: HubSpot | D15: GDM Marketo | E15: Transactional Data | F15: N | G15: ? | I15: Rawat Devendra Singh | J15: Amandeep | K15: Jacob.Jackson | Patti Delano | L15: HubSpot Marketable Leads | M15: Email address field | N15: Opt-in field
A16: 15 | B16: Leads | C16: MyEmma | D16: GDM Marketo | E16: Transactional Data | F16: N | G16: ? | I16: Rawat Devendra Singh | J16: Amandeep | K16: Jacob.Jackson | Patti Delano | L16: MyEmma Marketable Leads | M16: Email address field | N16: Opt-in field
A17: 16 | B17: Material/Product | C17: ERP | D17: Pros | E17: Master Data | F17: Y | I17: Sourav Garg | J17: Amit Choudhry | K17: Park, Ohsoon|Hoffman, Hanneke|Lynch, Patrick | L17: SKU | M17: Sales Org | N17: Plant
A18: 17 | B18: Accounts (Buying) | C18: ERP | D18: Pros | E18: Master Data | F18: Y | I18: Sourav Garg | J18: Amit Choudhry | K18: Park, Ohsoon|Hoffman, Hanneke|Lynch, Patrick | L18: Customer
A19: 18 | B19: Price | C19: Business/ Manual | D19: Pros | E19: Master Data | F19: N | G19: 45827 | I19: Sourav Garg | J19: Amit Choudhry | K19: Park, Ohsoon|Hoffman, Hanneke|Lynch, Patrick | L19: MSRP | M19: List price | N19: Standard Discount | O19: Negotiated Disc Net Price | P19: Negotiated Discount % | Q19: Promotional Discounts % | R19: Volume Discounts % | S19: Transfer Prices
A20: 19 | B20: Material/Product | C20: ERP | D20: MDM | E20: Master Data | F20: Y | I20: Manish Singh | J20: Jay Smith / Ritma | L20: SKU | M20: Product Hierarchy
A21: 20 | B21: Service Contracts | C21: ERP | D21: GDM SFDC (AMS) | E21: Transactional Data | F21: N | G21: 45829 | I21: Ritesh Shetty/Gerard | L21: Service Contracts
A22: 21 | B22: Material/Product | C22: ERP | D22: PIM | E22: Master Data | F22: Y | I22: Manish Singh | J22: Jay Smith / Ritma | L22: SKU | M22: Product Taxonomy | N22: Product Catalogue
A23: 22 | B23: Assets | C23: Source SFDC | D23: GDM SFDC (AMS) | E23: Transactional Data | F23: N | G23: 45837 | I23: Ritesh Shetty/Gerard | L23: Assets
A24: 23 | B24: Material/Product | C24: ERP | D24: ERP,CPQ | E24: Master Data | F24: Y | I24: Gayatri Tarane | J24: Saquib | K24: John H and Debora Simson | L24: Training SKU
A25: 24 | B25: Material/Product | C25: ERP | D25: CPQ,Zuora | E25: Master Data | F25: Y | I25: Gayatri Tarane | J25: Saquib | K25: John H and Debora Simson | L25: Training SKU
A26: 25 | B26: Price | C26: ERP | D26: CPQ,Zuora | E26: Master Data | F26: N | G26: 45827 | I26: Gayatri Tarane | J26: Saquib | K26: John H and Debora Simson | L26: List Price | M26: Currency
A27: 26 | B27: Accounts (Buying) | C27: ERP | D27: SFDC | E27: Master Data | F27: Y | I27: Gayatri Tarane | J27: Saquib | K27: John H and Debora Simson | L27: Customer | M27: Product lines | N27: Account-Contact Relationship
A28: 27 | B28: Contacts (Portal) | C28: GDM SFDC | D28: ELMS | E28: Master Data | F28: Y | I28: Gayatri Tarane | J28: Saquib | K28: John H and Debora Simson | L28: Portal Contact (ELMS Users) | M28: SFDC Contact ID ( Onguard/Netbox User) | N28: Training ID for Netbox users | O28: Follow portal Contacts and Subitems
A29: 28 | B29: Training Object Migration | C29: GDM SFDC | D29: SFDC | E29: Transactional Data | F29: N | G29: 45830 | I29: Gayatri Tarane | J29: Saquib | K29: John H and Debora Simson | L29: All the Training Certification should be synced to SFDC for OG, Elements and Netbox.
A30: 29 | B30: Portal Registration & Training Tools | C30: GDM SFDC | D30: ELMS | E30: Master Data | F30: Y | I30: Gayatri Tarane | J30: Saquib | K30: John H and Debora Simson | L30: Training Tools | M30: Training ID
A31: 30 | B31: Validate SFDC ContactID in AXIS LMS | C31: GDM SFDC | D31: ELMS | E31: Master Data | F31: Y | I31: Gayatri Tarane | J31: Saquib | K31: John H and Debora Simson | L31: SFDC Contact ID in AXIS LMS users records.
A32: 31 | B32: Validate TrainingID in NetBox LMS | C32: GDM SFDC | D32: ELMS | E32: Master Data | F32: N | G32: 45830 | I32: Gayatri Tarane | J32: Saquib | K32: John H and Debora Simson | L32: Training ID update for Netbox LMS users in SFDC and LMS records.
A33: 32 | B33: Accounts (Buying) | C33: GDM SFDC | D33: Portal | E33: Master Data | F33: Y | I33: Sateesh Chandala | J33: Saquib | L33: Sold To | M33: Var Account | N33: Cumulus Sync | O33: Relationship of Buying & Non Buying Account
A34: 33 | B34: Listing & Exclusion | C34: ERP | D34: CPQ | E34: Master Data | F34: Y | I34: Gayatri Tarane | J34: Saquib | K34: John H and Debora Simson | L34: Validate Customers and SKU mapping for L&E in SAP
A35: 34 | B35: Accounts (Non-Buying) | C35: GDM SFDC | D35: Portal | E35: Master Data | F35: Y | I35: Sateesh Chandala | J35: Saquib | L35: End User Account
A36: 35 | B36: Contact (Buying) | C36: GDM SFDC | D36: Portal | E36: Master Data | F36: Y | G36: 45824 | I36: Sateesh Chandala | J36: Saquib | L36: Buying Contact | M36: Honeywell_ID | N36: WPHID | O36: PURID | P36: Titan Portal Status | Q36: ACR-Ecomm flag | R36: Email
A37: 36 | B37: Contact (Non-Buying) | C37: GDM SFDC | D37: Portal | E37: Master Data | F37: N | G37: ? | I37: Sateesh Chandala | J37: Saquib | L37: Non-Buying Contact | M37: Honeywell_ID | N37: WPHID | O37: PURID | P37: Titan Portal Status | Q37: ACR-Ecomm flag | R37: Email
A38: 37 | B38: Contact (Portal) - WPHID | C38: GDM SFDC | D38: Portal | E38: Master Data | F38: Y | I38: Sateesh Chandala | J38: Saquib | L38: Web Portal Honeywell Id | M38: Email Address | N38: Portal Status | O38: Portal Status
A39: 38 | B39: Contact (Portal) - PURID | C39: GDM SFDC | D39: Portal | E39: Master Data | F39: Y | I39: Sateesh Chandala | J39: Saquib | L39: Portal User Registration | M39: Portal User Name | N39: EmailAddress | O39: Honeywell ID
A40: 39 | B40: Training Certifications | C40: GDM SFDC | D40: Portal | E40: Master Data | F40: N | G40: 45827 | I40: Sateesh Chandala | J40: Saquib | L40: OnGuard & Netbox Certifications | N40: Training Id
A41: 40 | B41: Var Agreements | C41: GDM SFDC | D41: Portal | E41: Master Data | F41: N | G41: ? | I41: Sateesh Chandala | J41: Saquib | L41: VAR Agreement
A42: 41 | B42: Asset | C42: GDM SFDC | D42: Portal | E42: Transactional Data | F42: N | G42: 45837 | I42: Karan Sharma | J42: Saquib | L42: Asset Data (System & System License) | M42: GDMFSL_System_Id__c SVMX_HBS_SBU_GBE__c Parent.Name, Parent.GDMFSL_System_Id__c RootAsset.Name, RootAsset.GDMFSL_System_Id__c | N42: Name Product_Line__c, Product_Version__c, | O42: GDMFSL_Pattern_Name__c License_Id__c, GDMFSL_Pattern_Id__c, GDMFSL_License_Product_Type__c, GDMFSL_Region__c, | P42: Asset_Type__c RecordType.Name, GDMFSL_Class__c, Status, | Q42: GDMFSL_Fingerprint_Type__c, GDMFSL_Activation_Key__c, GDMFSL_Product_Key__c, GDMFSL_Net_VR_Key__c | R42: CreatedDate, Expiration_Date_Time__c, LastModifiedDate, | S42: AccountId, Account.Name
A43: 42 | B43: Entitlements | C43: GDM SFDC | D43: Portal | E43: Transactional Data | F43: N | G43: 45830 | I43: Karan Sharma | J43: Saquib | L43: Service Contracts/ License Feature | M43: AssetId, Asset.name, Asset.Asset_Type__c, License_Feature_External_ID__c, GDMFSL_Feature_String_Value__c, | N43: Name, Type, RecordType.Name, ServiceContract.Name, ServiceContract.ContractNumber, ServiceContract.GDMFSL_Contract_Type__c, | O43: status, StartDate, EndDate, Asset.GDMFSL_System_Id__c, | P43: ServiceContract.GDMFSL_End_User__r.name, ServiceContract.GDMFSL_End_User__c, ServiceContract.Owner__c | Q43: Account.Brand2__c
A44: 43 | B44: Product Version | C44: GDM SFDC | D44: Portal | E44: Transactional Data | F44: Y | I44: Karan Sharma | J44: Saquib | L44: Product Version | M44: Product | N44: VersionId | O44: Version Name
A45: 44 | B45: Cases | C45: GDM SFDC | D45: Portal | E45: Transactional Data | F45: N | G45: 45843 | I45: Karan Sharma | J45: Saquib | L45: Cases | M45: Case Number Case Type Case Origin | N45: End User System | O45: Case Owner
A46: 45 | B46: Software Metadata | C46: GDM SFDC | D46: Portal | E46: Transactional Data | F46: N | G46: ? | I46: Karan Sharma | J46: Saquib | L46: Software file Metadata | M46: target_audience business_unit searchable sha1 sha2 part_number region software_subcategory_level1 | N46: id country sbu language compatible_hardware file_type software_name brand blob_url visible | O46: blob_id description title prerequisites document_type product software_group_id file_name file_size product_group_id | P46: parent_doctype updated_date created_date software_category md5
A47: 46 | B47: SFDC Account Sync to CUMULUS | C47: GDM SFDC | D47: Portal | E47: Master Data | F47: Y | I47: Karan Sharma | J47: Saquib | L47: SFDC Account Sync to CUMULUS | M47: SFDC Account Id's
A48: 47 | B48: Knowledge Articles | C48: GDM SFDC | D48: Portal | E48: Master Data | F48: N | G48: ? | I48: Karan Sharma | J48: Saquib | L48: Knowledge Articles | M48: id summary article_number is_video_available product_family country | N48: article_type target_audience question_problem title modified_date environment | O48: last_published_date article_number_nonzeros parent_doctype answer_solution region | P48: published_date brand product_category document_type
A49: 48 | B49: Technical Publication | C49: EDAM | D49: Portal | E49: Transactional Data | F49: N | G49: ? | I49: Karan Sharma | J49: Saquib | L49: Technical Publications | M49: Standard GDM fields
A50: 49 | B50: Orders | C50: ERP | D50: Portal | E50: Transactional Data | F50: N | G50: 45843 | I50: Karan Sharma | J50: Saquib | L50: Order & Invoices | M50: HBT Order Status Data Dictionary
A51: 50 | B51: Material/Product | C51: EPIM | D51: Portal | F51: Y | I51: Sateesh Chandala | J51: Saquib | L51: PDP Pages | M51: AEM Catalog Rollout | N51: Elastic Product | O51: Elastic SKU
A52: 51 | B52: Material/Product | C52: ERP / EPIM | D52: E-Commerce | E52: Master Data | F52: Y | I52: Sonam Kumari | J52: Saquib | L52: Products | M52: SKU | N52: Channel Status | O52: Category | P52: Item Plant | Q52: Images | R52: Media / Documents | S52: Product Reference | T52: Classification | U52: UOM
A53: 52 | B53: Accounts (Buying) | C53: ERP | D53: E-Commerce | E53: Master Data | F53: Y | I53: Sonam Kumari | J53: Saquib | L53: Customer | M53: Address | N53: Sales Org | O53: Partner
A54: 53 | B54: Price | C54: ERP | D54: E-Commerce | E54: Master Data | F54: N | G54: 45827 | I54: Sonam Kumari | J54: Saquib | L54: List Price
A55: 54 | B55: Contacts (E-Commerce) | C55: GDM SFDC | D55: E-Commerce | E55: Master Data | F55: Y | I55: Sonam Kumari | J55: Saquib | L55: Contact (E-commerce Enablement) | M55: Persona
A56: 55 | B56: Listing & Exclusion | C56: ERP | D56: E-Commerce | E56: Master Data | F56: Y | I56: Sonam Kumari | J56: Saquib | L56: SalesAreaSoldToMaterialPriceGroup | M56: SalesAreaSoldToMaterial
A57: 56 | B57: Assets / Entitlements | C57: GDM SFDC (AMS) | D57: Contact Center | F57: N | G57: 45837 | I57: Divya HV /Chandra Bose (Architect) | J57: Mike Reed - BA IT/ Czerwinski, Ron - PO BA Org | L57: Assets | M57: Entitlements
A58: 57 | B58: Cases | C58: GDM SFDC (AMS) | D58: Contact Center | E58: Transactional Data | F58: N | G58: 45843 | I58: Divya HV /Chandra Bose (Architect) | J58: Mike Reed - BA IT/ Czerwinski, Ron - PO BA Org | L58: Cases
A59: 58 | B59: Accounts (Buying) | C59: GDM SFDC | D59: Contact Center | E59: Master Data | F59: Y | I59: Divya HV /Chandra Bose (Architect) | J59: Mike Reed - BA IT/ Czerwinski, Ron - PO BA Org | L59: Accounts
A60: 59 | B60: Contacts | C60: GDM SFDC | D60: Contact Center | F60: Y | I60: Divya HV /Chandra Bose (Architect) | J60: Mike Reed - BA IT/ Czerwinski, Ron - PO BA Org | L60: Contacts
A61: 60 | B61: Contacts | C61: GDM SFDC | D61: Contact Center
A62: 61 | B62: Training | C62: GDM SFDC | D62: Contact Center

Sheet Prod - Data Mig. for Non-SFDC
A1: MetaData (of Data Elements) | H1: Data Preparation | L1: Data Load | Q1: Validate (BA IT)
A2: LOB | B2: Track | C2: Data Destination | D2: Data Element | E2: Data Source | F2: Status | G2: No of Records | H2: Data Enrichment/ Business Intervention - Required (Y/N) | I2: Data Enrichment Owner (BA CCEX IT Team, BA IT, ERP, etc) | J2: Power Center / IICS | K2: Enrichment Deadline | L2: Corp IT Focal - Data Owner (SPOC) | M2: Corp IT Focal - Responsibility to Load | N2: Data Quality check by? | O2: Data Loading - Start Date | P2: Data Loading - End Date | Q2: BA IT Focal - Reponsibility to Validate | R2: Data Validation - Start Date | S2: Data Validation - End Date | T2: Comments | U2: Comments for Production
B3: Commercial | C3: CPQ | D3: Material SKU and Description || | E3: MDM/SAP | F3: Pending | H3: N | I3: NA | J3: Power Center | K3: NA | L3: Ajay Tamhane/Kumar Kunjathaya, Nithin | M3: Ashutoush/Anuhya | N3: Ajay/Nithin | O3: June 30th, 2025 | P3: July 04th, 2025 | Q3: Amit | T3: Pending: Two types materials needs to be loaded Services and IPC. Service materials loaded by Ajay IPC materials are the ones we need tagging (SAP Material type, Service materials ZSRV - Should be Inventory ZINV). But sample materials have been tagged correctly. Larger set won't be tagged until it goes in Production.
B4: Commercial | C4: CPQ | D4: Material Master : Product Catalogue | E4: MDM/SAP | F4: Pending | H4: Y | I4: Ritma | J4: Power Center | K4: June 25th, 2025 | L4: Ajay Tamhane/Kumar Kunjathaya, Nithin | M4: Ashutoush/Anuhya | N4: Ajay/Nithin | O4: June 30th, 2025 | P4: July 04th, 2025 | Q4: Ambresh | U4: ERP -MDM - EPIM - CPQ || Enrichment was required intially, but now the approach is changed,hence its not required
B5: Commercial | C5: CPQ | D5: Material Master : Product Hierarchy | E5: MDM/SAP | F5: Pending | H5: Y | I5: Ritma | J5: Power Center | K5: June 25th, 2025 | L5: Ajay Tamhane/Kumar Kunjathaya, Nithin | M5: Ashutoush/Anuhya | N5: Ajay/Nithin | O5: June 30th, 2025 | P5: July 04th, 2025 | Q5: Ambresh | T5: Pending: Product Hierarchy determines whether material is SW or Service etc. Manual tagging is performed in CPQ for UAT to avoid the blocker. | U5: SAP - ETL - CPQ Migration Date : June 30th - July 04th SAP POC - TBC by Ashutous ETL POC - Anu CPQ - Ajay/Nithin/Ashutoush/Chirag
B6: Commercial | C6: CPQ | D6: Catalogue Hierarchy | E6: MDM/SAP | F6: Pending | H6: Y | I6: Ritma | J6: Power Center | K6: June 25th, 2025 | L6: Ajay Tamhane/Kumar Kunjathaya, Nithin | M6: Ashutoush/Anuhya | N6: Ajay/Nithin | O6: June 30th, 2025 | P6: July 04th, 2025 | Q6: Ambresh | T6: Approval from legal final draft document. Ajay Tamhane to provide the templates for review and approval - Business Legal (Thomas/ Penny) 5/9 - Proposals sent to legal for approval on 5/8 | U6: Load Existing Quotes from the Previous System(Access Solutions Legacy) - Pending Migration of Quotes - ERP - Chirag| BA IT - Sashi, Lutz || Decision Need by 05/22 Migration of Active warranty Contracts - ERP - Chirag, Sachin, Ritesh| BA IT - Sashi, Lutz || Decision Need by 05/22
B7: Commercial | C7: CPQ | D7: Proposal template (Code Load) | E7: CPQ | F7: Pending | H7: N | I7: NA | K7: NA | L7: Ajay Tamhane/Kumar Kunjathaya, Nithin | M7: Ashutoush | N7: June 30th, 2025 | O7: June 30th, 2025 | P7: July 04th, 2025 | Q7: Ambresh | U7: Received the Tempate in UAT and same can be used in PROD - Part of Code Deployment
B8: Commercial | C8: CPQ | D8: Labor Cost (Code Load) | E8: MDM/SAP | F8: Pending | H8: N | I8: NA | J8: Power Center | K8: NA | L8: Ajay Tamhane/Kumar Kunjathaya, Nithin | M8: Ashutoush/Anuhya | N8: Ajay/Nithin | O8: June 30th, 2025 | P8: July 04th, 2025 | Q8: Ambresh | T8: Regarding Labour cost, Subrata Paul has confirmed that it has been loaded to BRV already. Forwarding the mail for your reference. Tamhane, Ajay Please confirm. | U8: Post SAP ERP Labor Cost data load in BRP, it flow to CPQ Automatically via interface. Needs CPQ Configuration change to be covered as part of code deployment.
B9: Commercial | C9: CPQ | D9: Material Cost (Code Load) | E9: MDM/SAP | F9: Pending | H9: N | I9: NA | J9: Power Center | K9: NA | L9: Ajay Tamhane/Kumar Kunjathaya, Nithin | M9: Ashutoush/Anuhya | O9: June 30th, 2025 | P9: July 04th, 2025 | Q9: Ambresh | U9: Post SAP ERP Material Cost data load in BRP, it flow to CPQ Automatically via interface. Needs CPQ Configuration change to be covered as part of code deployment.
B10: Commercial | C10: CPQ | D10: Rate Plan (Manual load from Zuora) | E10: Zuora | F10: Pending | H10: N | I10: NA | K10: NA | L10: Ajay Tamhane/Kumar Kunjathaya, Nithin | M10: Ashutoush | O10: June 30th, 2025 | P10: July 04th, 2025 | Q10: Ambresh
B11: Commercial | C11: CPQ | D11: Price Data | E11: SAP ERP | F11: Pending | H11: N | I11: NA | K11: NA | L11: Ajay Tamhane/Kumar Kunjathaya, Nithin | M11: Ashutoush | O11: June 30th, 2025 | P11: July 04th, 2025 | Q11: Ambresh | U11: Real Time API Call - Prices should be loaded in ERP from PROS (Vimal can confirm)
B12: Commercial | C12: CPQ | D12: Product Dependency Rules | E12: Data Configuration | F12: Pending | L12: Ajay Tamhane/Kumar Kunjathaya, Nithin | M12: Ashutoush | N12: Ajay/Nithin | O12: June 30th, 2025 | P12: July 04th, 2025 | Q12: Ambresh | T12: Reviewing the file shared by Shashi. Most of them requirements seem to be on CSR instructions which are already completed in CPQ as part of CSR Sales Text requirement | U12: Chirag : Existing rules are in place || Its not part of data Migration activity
A13: Lenel S2 NA | B13: Commercial | C13: CPQ | D13: Product Version | E13: SFDC | F13: Pending | L13: Ajay Tamhane/Kumar Kunjathaya, Nithin | N13: Ajay/Nithin | Q13: Ambresh | T13: Product version is completed by Data migration team, please check and confirm. | U13: Data comes a part of SFDC Migration. Shivani and team to confirm
B14: Commercial | C14: CPQ | D14: Promo code | E14: SFDC /SAP | F14: Pending | L14: Ajay Tamhane/Kumar Kunjathaya, Nithin | U14: Data comes a part of SFDC Migration. Shivani and team to confirm
B15: Commercial | C15: CPQ | D15: Renewal SKU | E15: SFDC (AMS) /SAP | F15: Pending | L15: Ajay Tamhane/Kumar Kunjathaya, Nithin | U15: Data comes a part of AMS Data Migration
B16: Commercial | C16: CPQ | D16: Product Action | E16: SFDC (AMS) /SAP | F16: Pending | L16: Ajay Tamhane/Kumar Kunjathaya, Nithin | U16: Data comes a part of AMS Data Migration
B17: Commercial | C17: CPQ | D17: License Metadata | E17: SFDC | F17: Pending | L17: Ajay Tamhane/Kumar Kunjathaya, Nithin | N17: Ajay/Nithin | Q17: Steve | T17: CPQ will receive version data from SFDC (auto synch from SF). Template ID mapping completed against SKU in CPQ. Completed Saquib can perform the validation SFDC, CPQ & Zuora. | U17: Ashutosh to check and confirm
A18: Lenel | B18: Digital | C18: Zuora | D18: Product SKU and Description Category - Perpetual OneTime, Recurring/Software, Milestone 3rd Party,Bundled Kit(HW+SW) Billing Plan for Subs SKU - Recurring SKUs(Annual,Monthly) Milestone 3rd Pary Software SKU | E18: SAP ERP | H18: Y | I18: Channa Basva | K18: July 07th, 2025 | L18: Kondraganti, Mahesh Babu | M18: ChannaBasava | N18: Mahesh | O18: July 04th, 2025 | P18: July 07th,2025 | Q18: Saquib | T18: Final list for PROD yet to be received. Data Source MDM. Tagging should be done in CPQ and from CPQ it flows down to Zuora. Action : Shashi to share the tagging details . MDM team is working on it. Saquib to provide complete list of SKU's (S/W& Training) for US & EMEA
A19: Lenel | B19: Digital | C19: Zuora | D19: Material Master : Product Category and Product Line Per SKU Perpetual Software only (One-Time Charge) Subscription Software (Billing Plan - Annual/Monthly/Quarterly etc.) , Milestone 3rd Party Software, Bundled KIT(HW+SW) Training One Time , Training Subscription | E19: SAP ERP | H19: Y | I19: Channa Basva | K19: July 07th, 2025 | L19: Kondraganti, Mahesh Babu | M19: ChannaBasava | N19: Mahesh | O19: July 04th, 2025 | P19: July 07th,2025 | Q19: Saquib
A20: Lenel | B20: Digital | C20: Zuora | D20: Material Master : Billing Plan for Subscription/Recurring SKU Annual/Monthly/Quarterly etc | E20: SAP ERP | H20: Y | I20: Channa Basva | K20: July 07th, 2025 | L20: Kondraganti, Mahesh Babu | M20: ChannaBasava | N20: July 04th, 2025 | O20: July 04th, 2025 | P20: July 07th,2025 | Q20: Saquib | T20: Mahesh to provide the template so BA can provide the data in the format required
A21: Lenel | B21: Digital | C21: Zuora | D21: Material Master :: Milestone 3rd Party Software SKU's | E21: SAP ERP | H21: Y | I21: Channa Basva | K21: July 07th, 2025 | L21: Kondraganti, Mahesh Babu | M21: ChannaBasava | N21: Mahesh | O21: July 04th, 2025 | P21: July 07th,2025 | Q21: Saquib | T21: Mahesh to provide the template so BA can provide the data in the format required
B22: Digital | C22: Zuora | D22: Final Price as part of Order creation - (Not Required as price comes as part of the order from CPQ) | E22: CPQ | I22: Channa Basva | K22: July 07th, 2025 | L22: Kondraganti, Mahesh Babu | M22: Mahesh | N22: Mahesh | Q22: Saquib | T22: Bassava to test and confirm. Tested for SIT scenarios.
B23: Digital | C23: Zuora | D23: Material Master : Customer Price for Automated Renewal Billing - BlueDiamond/Elements | E23: SAP ERP | L23: Kondraganti, Mahesh Babu | M23: Mahesh | N23: Mahesh | Q23: Saquib | T23: SIT Data is good. Final list for PROD yet to be received. Data Source MDM. Tagging should be done in CPQ and from CPQ it flows down to Zuora. | U23: Real Time call to ERP
B24: Digital | C24: Zuora | D24: Renewal Notification Templates | E24: Data Configuration | H24: N | I24: Mahesh | K24: July 01st, 2025 | L24: Kondraganti, Mahesh Babu | M24: ChannaBasava | N24: Mahesh | O24: July 05th, 2025 | P24: July 06th, 2025 | Q24: Saquib | U24: Templates are provided already for UAT Same will be used for Production | V24: Fully Loaded- DQ Complete
B25: Digital | C25: Zuora | D25: BD Order Acknowledgment Notification Templates | E25: Data Configuration | H25: N | I25: Mahesh | K25: July 01st, 2025 | L25: Kondraganti, Mahesh Babu | M25: ChannaBasava | N25: Mahesh | O25: July 05th, 2025 | P25: July 06th, 2025 | Q25: Saquib | U25: Templates are provided already for UAT Same will be used for Production | V25: Partially Loaded or DQ-NOT complete
B26: Digital | C26: Zuora | D26: Customer Master - Sold To & Ship To Accounts (Requires Informatica code change) | E26: SAP ERP | H26: N | I26: N | K26: NA | L26: Kondraganti, Mahesh Babu | M26: ChannaBasava | N26: Mahesh | O26: July 04th, 2025 | P26: July 06th, 2025 | Q26: Saquib | T26: Automated sync between ERP and Zuora. What needs to be validated? | U26: Involves Informatica Changes - ETL Jobs should be Triggered for this Data Load || ETL PROD ENV should be Monitered post this data load by channa | V26: Data NOT Loaded/Available
B27: Digital | C27: Zuora | D27: BlueDiamond Subscription (Assets in AMS) | E27: SFDC (AMS) | H27: Y(Transformation of data) | I27: Channa Basva | K27: July 07th, 2025 | L27: Kondraganti, Mahesh Babu | M27: ChannaBasava | N27: Geetanjali | O27: July 06th,2025 | P27: July 07th, 2025 | Q27: Chris Branch | T27: Transaction data validation checkpoint. This is covered as part of the SIT test cases, assets are getting created in AMS. Basaava to cross check and confirm. | U27: Data Transformation is part of Data load - After the load is completed Asset ID mapping of SFDC needs to provided to Blue Diamond from their legacy ID to new SFDC ID.
B28: Digital | C28: Zuora | D28: Transactional Elements - Subscription data (to be loaded manually) | E28: Elements Management Portal | H28: Y(Transformation of data) | I28: Channa Basva | K28: July 07th, 2025 | L28: Kondraganti, Mahesh Babu | M28: ChannaBasava | N28: Mahesh | O28: July 06th,2025 | P28: July 07th, 2025 | Q28: Dilon | T28: Mahesh to work with Elements engineering team for Subscription data. 10th May - Sending a communication to get the Data | U28: Need to pass new Asset Id mapping from ERP to Elements portal once the load is completed manually on Zuora end.
B29: Digital | C29: Zuora | D29: OnGuard Subscription Data (System Asset in AMS) | E29: SFDC (AMS) | H29: Y(Transformation of data) | I29: Channa Basva | K29: July 07th, 2025
B30: Digital | C30: Zuora | D30: OnGuard Cloud Subscription Data (System Asset in AMS) | E30: SFDC (AMS) | H30: Y(Transformation of data) | I30: Channa Basva | K30: July 07th, 2025 | L30: Kondraganti, Mahesh Babu | M30: ChannaBasava | N30: Geetanjali | O30: July 06th,2025 | P30: July 07th, 2025 | Q30: Jacob | T30: Transaction data validation checkpoint. This is covered as part of the SIT test cases, assets are getting created in AMS. | U30: Data Transformation is part of Data load - After the load is completed Asset ID mapping of SFDC needs to provided to Onguard from their legacy ID to new SFDC ID.
B31: Digital | C31: Flexera | D31: License Metadata | E31: Data Configuration | L31: Ramesh Sadanaboina/Kondraganti, Mahesh Babu | M31: Mahesh | O31: July 01st, 2025 | P31: July 02nd, 2025 | T31: This has been completed. BA IT to check and confirm. | U31: Need to check with Abhishek
A32: Lenel S2 | B32: Commercial | C32: Marketo | D32: HubSpot Marketable Leads | E32: HubSpot | F32: Pending | H32: Y | I32: Amandeep / Langston | K32: 20th June | L32: Devendra Singh | M32: Mohit | N32: Devendra | Q32: Amandeep | U32: SFDC Contact Data Shouldn't be in Sync with Marketo PROD System|| Jacob.Jackson AS Hubspot POC
A33: Supra | B33: Commercial | C33: Marketo | D33: MyEmma Marketable Leads | E33: MyEmma | F33: Pending | H33: Y | I33: Amandeep / Langston | K33: 20th June | L33: Devendra Singh | M33: Mohit | N33: Devendra | Q33: Amandeep | U33: SFDC Contact Data Shouldn't be in Sync with Marketo PROD System || Patti Delano AS MyEmma POC
A34: Lenel S2 NA/EMEA / Supra | B34: Commercial | C34: Pricing (PROS) | D34: Master Data ( Material, Customer, Sales-org) | E34: SAP ERP / MDM | F34: pending | H34: N | I34: N | J34: Power Center | K34: NA | L34: Vimal Kumar | M34: Mallikarjun Kothmeer/Vimal | N34: Vimal | O34: June 12th, 2025 | P34: June 16th, 2025 | Q34: Amit Choudhry|| AS PO's - Park, Ohsoon||Hoffman, Hanneke||Lynch, Patrick | R34: June 17th, 2025 | S34: June 19th, 2025 | T34: Vimal to work with AS Pricing team, customer specific, discounts etc. Tentative June 11 | U34: ETL Developer doesn't have access to load PROS data in ETL Amit Choudhry Does't have access to validate data in PROS, hence it should be done by AS PO's
A35: Lenel S2 NA/EMEA / Supra | B35: Commercial | C35: Pricing (PROS) | D35: User list for Onboarding to PROS | E35: Business | F35: Pending | G35: ~15 | H35: N | I35: Becker, Matthew/ BA Org PO | K35: NA | L35: Vimal Kumar | M35: Vimal /Julio | N35: Vimal | O35: June 17th, 2025 | P35: June 24th,2025 | Q35: Becker, Matthew/ BA Org PO | R35: June 25th, 2025 | S35: June 27th, 2025 | T35: Vimal to work with AS Pricing team, customer specific, discounts etc. | U35: Becker, Matthew - Over all pricing ops Manager/PROS Product Owner for Honeywell BA Org
A36: Lenel S2 NA/EMEA / Supra | B36: Commercial | C36: Pricing (PROS) | D36: MSRP - Manufracture's Suggested Retail Price | E36: Business | F36: pending | G36: ~10000 | H36: N | I36: AS PO's - Park, Ohsoon||Hoffman, Hanneke||Lynch, Patrick | K36: NA | L36: Vimal Kumar | M36: Vimal / Ramya | N36: Ajay/Nithin | O36: June 23rd, 2025 | P36: July 04th, 2025 | Q36: AS PO's - Park, Ohsoon||Hoffman, Hanneke||Lynch, Patrick | R36: June 25th, 2025 | S36: June 27th, 2025 | T36: All are approximate numbers based on the data we have received from AS Business and loaded into PROS. Numbers could vary based on, - Additional SKUs created/extended in SAP BRP - NPIs and SKU status (active, obsolete etc.) - Change in Customer contracts/agreements for a negoatiated price/discount
A37: Lenel S2 NA/EMEA / Supra | B37: Commercial | C37: Pricing (PROS) | D37: List price | E37: Business | F37: pending | G37: ~24000 | H37: N | I37: AS PO's - Park, Ohsoon||Hoffman, Hanneke||Lynch, Patrick | K37: NA | L37: Vimal Kumar | M37: Vimal / Ramya | N37: Ajay/Nithin | O37: June 23rd, 2025 | P37: July 04th, 2025 | Q37: AS PO's - Park, Ohsoon||Hoffman, Hanneke||Lynch, Patrick | R37: June 25th, 2025 | S37: June 27th, 2025
A38: Lenel S2 NA/EMEA / Supra | B38: Commercial | C38: Pricing (PROS) | D38: Standard Discount | E38: Business | F38: pending | G38: 78 | H38: N | I38: AS PO's - Park, Ohsoon||Hoffman, Hanneke||Lynch, Patrick | K38: NA | L38: Vimal Kumar | M38: Vimal / Ramya | N38: Ajay/Nithin | O38: June 23rd, 2025 | P38: July 04th, 2025 | Q38: AS PO's - Park, Ohsoon||Hoffman, Hanneke||Lynch, Patrick | R38: June 25th, 2025 | S38: June 27th, 2025
A39: Lenel S2 NA/EMEA / Supra | B39: Commercial | C39: Pricing (PROS) | D39: Negotiated Disc Net Price | E39: Business | F39: pending | G39: ~1800 | H39: N | I39: AS PO's - Park, Ohsoon||Hoffman, Hanneke||Lynch, Patrick | K39: NA | L39: Vimal Kumar | M39: Vimal / Ramya | N39: Ajay/Nithin | O39: June 23rd, 2025 | P39: July 04th, 2025 | Q39: AS PO's - Park, Ohsoon||Hoffman, Hanneke||Lynch, Patrick | R39: June 25th, 2025 | S39: June 27th, 2025
A40: Lenel S2 NA/EMEA / Supra | B40: Commercial | C40: Pricing (PROS) | D40: Negotiated Discount % | E40: Business | F40: pending | G40: ~10000 | H40: N | I40: AS PO's - Park, Ohsoon||Hoffman, Hanneke||Lynch, Patrick | K40: NA | L40: Vimal Kumar | M40: Vimal / Ramya | N40: Ajay/Nithin | O40: June 23rd, 2025 | P40: July 04th, 2025 | Q40: AS PO's - Park, Ohsoon||Hoffman, Hanneke||Lynch, Patrick | R40: June 25th, 2025 | S40: June 27th, 2025
A41: Lenel S2 NA/EMEA / Supra | B41: Commercial | C41: Pricing (PROS) | D41: Promotional Discounts % | E41: Business | F41: pending | G41: ~28000 | H41: N | I41: AS PO's - Park, Ohsoon||Hoffman, Hanneke||Lynch, Patrick | K41: NA | L41: Vimal Kumar | M41: Vimal / Ramya | N41: Ajay/Nithin | O41: June 23rd, 2025 | P41: July 04th, 2025 | Q41: AS PO's - Park, Ohsoon||Hoffman, Hanneke||Lynch, Patrick | R41: June 25th, 2025 | S41: June 27th, 2025
A42: Lenel S2 NA/EMEA / Supra | B42: Commercial | C42: Pricing (PROS) | D42: Volume Discounts % | E42: Business | F42: pending | G42: 70 | H42: N | I42: AS PO's - Park, Ohsoon||Hoffman, Hanneke||Lynch, Patrick | K42: NA | L42: Vimal Kumar | M42: Vimal / Ramya | N42: Ajay/Nithin | O42: June 23rd, 2025 | P42: July 04th, 2025 | Q42: AS PO's - Park, Ohsoon||Hoffman, Hanneke||Lynch, Patrick | R42: June 25th, 2025 | S42: June 27th, 2025
A43: Lenel S2 NA/EMEA / Supra | B43: Commercial | C43: Pricing (PROS) | D43: Transfer Prices | E43: Business | F43: pending | G43: ~14000 | H43: N | I43: AS PO's - Park, Ohsoon||Hoffman, Hanneke||Lynch, Patrick | K43: NA | L43: Vimal Kumar | M43: Vimal / Ramya | N43: Ajay/Nithin | O43: June 23rd, 2025 | P43: July 04th, 2025 | Q43: AS PO's - Park, Ohsoon||Hoffman, Hanneke||Lynch, Patrick | R43: June 25th, 2025 | S43: June 27th, 2025
B44: Digital | C44: Flexera | D44: Loading existing Entitlements | E44: Data Migration/Flexera | G44: 40K | H44: Y | I44: Abhishek Singh | K44: June 27th, 2025 | L44: Abhishek Singh | M44: Abhishek Singh | N44: Steve | O44: July 01st, 2025 | P44: July 02nd, 2025 | Q44: Steve | R44: July 04th, 2025 | S44: July 10th, 2025 | T44: BA IT review pending, Abhishek to follow up
B45: Digital | C45: Flexera | D45: Loading existing Licenses Fullfilment ID | E45: Data Migration/Flexera | G45: 30K | H45: Y | I45: Abhishek Singh | K45: June 27th, 2025 | L45: Abhishek Singh | M45: Abhishek Singh | N45: Steve | O45: July 01st, 2025 | P45: July 02nd, 2025 | Q45: Steve | R45: July 04th, 2025 | S45: July 10th, 2025 | T45: BA IT review pending, Abhishek to follow up
B46: 10K | C46: Flexera | D46: Loading Product, Features & License Model | E46: Data Migration/Flexera | G46: 10 | H46: Y | I46: Abhishek Singh | K46: June 27th, 2025 | L46: Abhishek Singh | M46: Abhishek Singh | N46: Steve | O46: July 01st, 2025 | P46: July 02nd, 2025 | Q46: Steve | R46: July 04th, 2025 | S46: July 10th, 2025 | T46: BA IT review pending, Abhishek to follow up
B47: Digital | C47: Flexera | D47: Load Transaction Key | E47: Data Migration/Flexera | G47: 1 | H47: Y | I47: Abhishek Singh | K47: June 27th, 2025 | L47: Abhishek Singh | M47: Abhishek Singh | N47: Abhishek | O47: July 01st, 2025 | P47: July 02nd, 2025 | Q47: Steve | R47: July 04th, 2025 | S47: July 10th, 2025
B48: Digital | C48: Flexera | D48: Load Template Id (master data) | E48: Data Configuration | G48: 150 | H48: N | I48: NA | K48: NA | L48: Abhishek Singh | M48: Ajay | O48: June 23rd, 2025 | P48: June 27th, 2025 | Q48: Steve | R48: July 01st, 2025 | S48: July 01st, 2025 | T48: Abhishek will work with Ajay/CPQ and confirm the Data Load and Validation Date | U48: Abhishek will work with Ajay/CPQ and confirm the Data Load and Validation Date
B49: Digital | C49: Flexera | D49: Sync System Id (Master & transactional)/ Parent System ID (Master & transactional) | E49: SFDC (AMS) | G49: 40K | H49: N | I49: NA | K49: NA | L49: Abhishek Singh | M49: Ritesh Shetty/Shivani | N49: Abhishek | O49: June 30th, 2025 | P49: July 01st, 2025 | Q49: Steve, Saquib | R49: July 02nd, 2025 | S49: July 02nd, 2025 | U49: Pre-requiste for Flexera Data Load|| No Enrichment is not required
B50: Digital | C50: Flexera | D50: License Version (master data) | E50: CPQ | G50: 8 | H50: N | I50: NA | K50: NA | L50: Abhishek Singh | M50: Ajay | O50: June 23rd, 2025 | P50: June 27th, 2025 | Q50: Steve | R50: July 01st, 2025 | S50: July 01st, 2025 | T50: SIT no blocker. 8 Versiona to be loaded (UAT), out of that we have loaded 2-3. | U50: Abhishek will work with Ajay/CPQ and confirm the Data Load and Validation Date
B51: Digital | C51: Flexera | D51: License Metadata (KeyType/Finger Print Type) | E51: Zuora / CPQ | G51: 2 | H51: N | I51: NA | K51: NA | L51: Abhishek Singh | M51: Mahesh/Sudhakar/Ajay | O51: June 23rd, 2025 | P51: June 27th, 2025 | Q51: Steve | R51: July 01st, 2025 | S51: July 01st, 2025 | U51: CPQ is required || For Zuora Abhishek/Sudhakar will work with Ajay and confirm 5/17
B52: Digital | C52: MDM | D52: Product and Hierarchy | E52: SAP ERP | L52: Dattaji Desai / Rajesh Garudamagiri | M52: Manish Singh | Q52: Jay Smith | T52: Get the SKU Tagging from Manish /Jay Smith. 5/9 - per Manish PH is now loaded in BRV for most materials.
B53: Digital | C53: PIM | D53: Product Data (Taxanomy and Catlogue) | E53: SAP ERP | L53: Dattaji Desai / Rajesh Garudamagiri | M53: Manish Singh | N53: Ritma | Q53: Saquib | T53: Get the SKU Tagging from Manish /Jay Smith. 5/9 - Monday 5/12 session to detail timeline for 14k SKUs to be tagged with PIM Taxonomy
B54: Commercial | C54: AMS | D54: NetBox Integration | E54: SFDC | L54: Ritesh Shetty/Geetanjali Sharma | M54: Ritesh Shetty | T54: Business has provided the data, data is loaded by Kote and team. Loaded through Informatica and SFDC. Kote is waiting on mapping logic from Ritesh
B55: Commercial | C55: AMS | D55: Asset Migration | E55: SFDC | L55: Ritesh Shetty/Geetanjali Sharma | M55: Ritesh Shetty | T55: Standard SFDC - SFDC migration, from Lennel S2.
B56: Commercial | C56: AMS | D56: Service Contract | E56: SFDC/ERP | L56: Ritesh Shetty/Geetanjali Sharma | M56: Ritesh Shetty | T56: Awaiting the logic to map legacy SFDC Contract references
A57: Lenel 2 | B57: Digital | C57: ELMS | D57: Training SKU setup in SAP - Material Master | E57: SAP ERP | F57: Pending | H57: TBD | I57: TBD | K57: TBD | L57: Girish Sreeram / Gayatri Tarane | M57: MDM/Sandeep | N57: Girish | O57: June 11th, 2025 | P57: June 13th, 2025 | Q57: Saquib/ John H and Debora Simson | R57: July 07th, 2025 | S57: July 09th, 2025 | T57: 7 SKUs for SIT and UAT have been identified
A58: Lenel 2 | B58: Digital | C58: ELMS | D58: Training SKU Pricing setup in SAP - Price | E58: SAP ERP | F58: Pending | H58: TBD | I58: TBD | K58: TBD | L58: Girish Sreeram / Gayatri Tarane | M58: Vimal | O58: June 23rd, 2025 | P58: July 04th, 2025 | Q58: Saquib/ John H and Debora Simson | R58: July 07th, 2025 | S58: July 09th, 2025
A59: Lenel 2 | B59: Digital | C59: ELMS | D59: Training SKU Availibility in CPQ - Material Master | E59: CPQ | F59: Pending | H59: Y | I59: Ashutosh Mishra, Ajay T | K59: 20th June | L59: Girish Sreeram / Gayatri Tarane | M59: MDM/Ajay /Nithin Kumar | N59: Girish | O59: June 30th, 2025 | P59: July 04th, 2025 | Q59: Saquib/ John H and Debora Simson | R59: July 07th, 2025 | S59: July 09th, 2025 | T59: Connected with the business and confirrmed on the finalized SKUs for golden data
A60: Lenel 2 | B60: Digital | C60: ELMS | D60: Training SKU Pricing setup in SAP - Price | E60: CPQ | F60: Pending | H60: TBD | I60: TBD | K60: TBD | L60: Girish Sreeram / Gayatri Tarane | M60: MDM/Ajay /Nithin Kumar | O60: June 30th, 2025 | P60: July 04th, 2025 | Q60: Saquib/ John H and Debora Simson | R60: July 07th, 2025 | S60: July 09th, 2025
A61: Lenel 2 | B61: Digital | C61: ELMS | D61: Training SKU setup in Zuora | E61: Zuora | F61: Pending | H61: Y | I61: Channabasava | K61: 20th June | L61: Girish Sreeram / Gayatri Tarane | M61: Kondraganti, Mahesh Babu / Sudhakar | N61: Girish | O61: July 06th, 2025 | P61: July 07th,2025 | Q61: Saquib/ John H and Debora Simson | R61: July 07th, 2025 | S61: July 09th, 2025 | T61: 5 SKUs for SIT and UAT have been identified and loaded. Elements and Netbox is completed. Onguard training system SKUs to be received from Business.
A62: Lenel 2 | B62: Digital | C62: ELMS | D62: Customer Master Set up in SAP | E62: SAP ERP | F62: Pending | H62: TBD | I62: TBD | K62: TBD | L62: Girish Sreeram / Gayatri Tarane | M62: MDM/Sachin | O62: June 11th, 2025 | P62: June 13th, 2025 | Q62: Saquib/ John H and Debora Simson | R62: July 07th, 2025 | S62: July 09th, 2025 | U62: Girish has to Sync with Gayathri for the final list and send to Business for Final validation, Due 5/20
A63: Lenel 2 | B63: Digital | C63: ELMS | D63: Portal User Registration for ELMS Users | E63: Portal | F63: Pending | H63: TBD | I63: TBD | K63: TBD | L63: Girish Sreeram / Gayatri Tarane | M63: Karan/Neeraj/Sateesh | O63: TBD | P63: TBD | Q63: Saquib/ John H and Debora Simson | R63: TBD | S63: TBD
A64: Lenel 2 | B64: Digital | C64: ELMS | D64: Update Training Id in AXIS LMS for Existing Netbox User | E64: SFDC | F64: Pending | L64: Girish Sreeram / Gayatri Tarane | M64: Steve Margason / John Carlos | N64: Girish | Q64: Saquib | T64: Girish to update | U64: OnGuard & Elements Training ID's are part of the existing AxisLMS System, No need to Migrate
A65: Lenel 2 | B65: Digital | C65: ELMS | D65: Update SFDC Contact Id in AXIS LMS for all Onguard/Netbox User | E65: SFDC | F65: Pending | L65: Girish Sreeram / Gayatri Tarane | M65: LMS Team | N65: Girish | Q65: Saquib
B66: Digital | C66: Portal | D66: Load Buying Account (with ERP Sold To ID / Var Acc) | E66: SFDC | L66: Shivani | M66: Manish Singh | N66: Neeraj | O66: June 8th, 2025 | P66: June 8th, 2025 | Q66: Saquib | R66: July 1st, 2025 | S66: July 2nd, 2025
B67: Digital | C67: Portal | D67: Load Non-Buying Account (End User) | E67: SFDC | L67: Shivani | M67: Kote | N67: Neeraj | O67: June 12th, 2025 | P67: June 12th, 2025 | Q67: Saquib | R67: July 1st, 2025 | S67: July 2nd, 2025
B68: Digital | C68: Portal | D68: Load Buying Contact | E68: SFDC | L68: Shivani | M68: Kote | N68: Neeraj | O68: June 14th, 2025 | P68: June 15th, 2025 | Q68: Saquib | R68: July 1st, 2025 | S68: July 2nd, 2025
B69: Digital | C69: Portal | D69: Load Non - Buying Contact | E69: SFDC | L69: Shivani | M69: Kote | N69: Neeraj | O69: June 14th, 2025 | P69: June 15th, 2025 | Q69: Saquib | R69: July 1st, 2025 | S69: July 2nd, 2025
B70: Digital | C70: Portal | D70: Cumulus (SFDC-Cumulus Sync) | E70: SFDC | L70: Shivani | M70: Kote | Q70: Saquib
B71: Digital | C71: Portal | D71: Asset Data, License, Contracts, License Features | E71: SFDC (AMS) | L71: Shivani | M71: Kote | O71: June 27th 2025 | P71: June 29th, 2025 | Q71: Saquib | R71: July 1st, 2025 | S71: July 4th, 2025
B72: Digital | C72: Portal | D72: Portal Object -(WPID, Persona, Registration object, ACR-Ecomm flag)) | E72: SFDC | H72: Y | I72: Saquib | K72: June 30th, 2025 | L72: Shivani | M72: Kote | N72: Neeraj | O72: June 27th, 2025 | P72: June 29th, 2025 | Q72: Saquib | R72: July 1st, 2025 | S72: July 2nd, 2025
B73: Digital | C73: Portal | D73: Load existing case | E73: SFDC | L73: Shivani | M73: Kote | N73: Karan | O73: July 4th, 2025 | P73: July 5th, 2025 | Q73: Saquib | R73: July 9th, 2025 | S73: July 10th, 2025
B74: Digital | C74: Ecommerce | D74: Material Master-Products | E74: ERP/EPIM | F74: Pending | G74: 28(istore) | H74: Y | I74: Ritma | J74: Power Center | K74: July 02nd | L74: Susmita Raut/Sonam Kumari | M74: Preethi Xavier | N74: Susmita Raut | O74: July 05th, 2025 | P74: July 06th, 2025 | Q74: Saquib | R74: July 06th, 2025 | S74: July 08th, 2025 | T74: 20SKUs Images load for SIT(blocked in Hybris due o QA env issue)/UAT environment in progress ETA : 5/12 | U74: 5 Video Designer Product will be taken care by the GFD team; Not included in the istore Product
B75: Digital | C75: Ecommerce | D75: Material Master-SKUS | E75: ERP/EPIM | F75: Pending | G75: 87(istore) | H75: Y | I75: Ritma | J75: Power Center | K75: July 02nd | L75: Susmita Raut/Sonam Kumari | M75: Preethi Xavier | N75: Susmita Raut | O75: July 05th, 2025 | P75: July 06th, 2025 | Q75: Saquib | R75: July 06th, 2025 | S75: July 08th, 2025 | T75: 20SKUs Images load for SIT(blocked in hybris due to QA env issue) UAT environment in progress ETA : 5/12 | U75: 21 Video Designer SKU will be taken care by the GFD team; Not included in istore SKU
B76: Digital | C76: Ecommerce | D76: Material Master-Channel Status | E76: ERP | F76: Pending | H76: N | I76: NA | J76: Power Center | K76: NA | L76: Susmita Raut/Sonam Kumari | M76: Preethi Xavier | N76: Susmita Raut | O76: July 05th, 2025 | P76: July 06th, 2025 | Q76: Saquib | R76: July 06th, 2025 | S76: July 08th, 2025
B77: Digital | C77: Ecommerce | D77: Material Master-Category | E77: EPIM | F77: Pending | G77: Category:5(istore) Brand: 5(istore) | H77: Y | I77: Ritma | J77: Power Center | K77: July 02nd | L77: Susmita Raut/Sonam Kumari | M77: Preethi Xavier | N77: Susmita Raut | O77: July 05th, 2025 | P77: July 06th, 2025 | Q77: Saquib | R77: July 06th, 2025 | S77: July 08th, 2025 | U77: The number provided might change by 1 or 2 in Production as stated by Rithma Category: 3(Video Designer) Brand: 1(Video Designer); Video Designe will be taken care by the GFD team; Not included in istore SKU
B78: Digital | C78: Ecommerce | D78: Material Master-Item Plant | E78: ERP | F78: Pending | H78: N | I78: NA | J78: Power Center | K78: NA | L78: Susmita Raut/Sonam Kumari | M78: Preethi Xavier | N78: Susmita Raut | O78: July 05th, 2025 | P78: July 06th, 2025 | Q78: Saquib | R78: July 06th, 2025 | S78: July 08th, 2025
B79: Digital | C79: Ecommerce | D79: Customer Master-ADDRESS | E79: SAP ERP | F79: Pending | G79: NA | H79: N | I79: NA | J79: Power Center | K79: NA | L79: Susmita Raut/Sonam Kumari | M79: Preethi Xavier | N79: Susmita Raut | O79: July 05th, 2025 | P79: July 06th, 2025 | Q79: Saquib | R79: July 06th, 2025 | S79: July 08th, 2025
B80: Digital | C80: Ecommerce | D80: Customer Master-SALESORG | E80: SAP ERP | F80: Pending | G80: 1 | H80: N | I80: NA | J80: Power Center | K80: NA | L80: Susmita Raut/Sonam Kumari | M80: Preethi Xavier | N80: Susmita Raut | O80: July 05th, 2025 | P80: July 06th, 2025 | Q80: Saquib | R80: July 06th, 2025 | S80: July 08th, 2025
B81: Digital | C81: Ecommerce | D81: Customer Master-PARTNER | E81: SAP ERP | F81: Pending | G81: TBD | H81: N | I81: NA | J81: Power Center | K81: NA | L81: Susmita Raut/Sonam Kumari | M81: Preethi Xavier | N81: Susmita Raut | O81: July 05th, 2025 | P81: July 06th, 2025 | Q81: Saquib | R81: July 06th, 2025 | S81: July 08th, 2025
B82: Digital | C82: Ecommerce | D82: Customer Master-HIERARCHY | E82: SAP ERP | F82: Pending | G82: TBD | H82: N | I82: NA | J82: Power Center | K82: NA | L82: Susmita Raut/Sonam Kumari | M82: Preethi Xavier | N82: Susmita Raut | O82: July 05th, 2025 | P82: July 06th, 2025 | Q82: Saquib | R82: July 06th, 2025 | S82: July 08th, 2025
B83: Digital | C83: Ecommerce | D83: ​Customer Master-Y1PARTNER | E83: SAP ERP | F83: Pending | G83: TBD | H83: N | I83: NA | J83: Power Center | K83: NA | L83: Susmita Raut/Sonam Kumari | M83: Preethi Xavier | N83: Susmita Raut | O83: July 05th, 2025 | P83: July 06th, 2025 | Q83: Saquib | R83: July 06th, 2025 | S83: July 08th, 2025
B84: Digital | C84: Ecommerce | D84: Material Master:Material_List Price | E84: SAP ERP | F84: Pending | G84: 101 | H84: N | J84: Power Center | L84: Susmita Raut/Sonam Kumari | M84: Preethi Xavier | N84: Susmita Raut | O84: July 05th, 2025 | P84: July 06th, 2025 | Q84: Saquib | R84: July 06th, 2025 | S84: July 08th, 2025
B85: Digital | C85: Ecommerce | D85: Material Master:,Material_Listing and Exclusion | E85: SAP ERP | F85: Pending | G85: 101 | H85: N | I85: Sachin Shelar | J85: Power Center | K85: July 02nd | L85: Susmita Raut/Sonam Kumari | M85: Preethi Xavier | N85: Susmita Raut | O85: July 05th, 2025 | P85: July 06th, 2025 | Q85: Saquib | R85: July 06th, 2025 | S85: July 08th, 2025
B86: Digital | C86: Ecommerce | D86: PDP & PLP content & pages | E86: ERP/EPIM | F86: Pending | G86: 28(istore) | H86: Y | I86: Ritma | J86: Power Center | K86: July 02nd | L86: Susmita Raut/Sonam Kumari | M86: Preethi Xavier | N86: Susmita Raut | O86: July 05th, 2025 | P86: July 06th, 2025 | Q86: Saquib | R86: July 06th, 2025 | S86: July 08th, 2025 | T86: Product Listing and Description page-these are AEM content page-source system is EPIM but in AEM this is blocked because AEM QA cannot take data from EPIM Dev; can take data from EPIM QA only. For Hybris there is no such limitation. | U86: /5 (Video designer)
B87: Digital | C87: Ecommerce | D87: Contact Sync | E87: SFDC | F87: Pending
A88: LenelS2 | B88: Digital | C88: Nice CXOne(Contact Center) | D88: Training Certification Data (Lenel S2) | E88: SFDC (Sales & Service) | F88: Pending | H88: N | I88: Divya M / Kote | L88: Chandra Bose / Nagendra Kumar / Vijay Illa | M88: Divya M/Devan/Dhanakoteshwar | N88: Vijay/Nagendra | Q88: Mike Reed - BA IT/ Czerwinski, Ron - PO BA Org | T88: NetBox data is not as expected. (Two fields data need to be corrected Course Name and Certification Level). Informed to Gayatri No "OnGuard Cloud" data available. | U88: Contact Center PROD Data Migration will be covered as part of SFDC Data Migration Czerwinski, Ron - PO for Over all Contact Center BA Honeywell
A89: LenelS2 | B89: Digital | C89: Nice CXOne(Contact Center) | D89: Entitlement Data ( Lenel S2) | E89: SFDC (AMS) | F89: Pending | H89: N | I89: Ritesh Shetty / Kote | L89: Chandra Bose / Nagendra Kumar / Vijay Illa | M89: Divya M/Devan/Dhanakoteshwar | N89: Vijay/Nagendra | Q89: Mike Reed - BA IT/ Czerwinski, Ron - PO BA Org | T89: Data not available for Product Line "OnGaurd Cloud", "Netbox"
A90: LenelS2 | B90: Digital | C90: Nice CXOne(Contact Center) | D90: Case Data (Lenel S2) | E90: SFDC (Sales & Service) | F90: Pending | H90: N | I90: Divya M / Kote | L90: Chandra Bose / Nagendra Kumar / Vijay Illa | M90: Divya M/Devan/Dhanakoteshwar | N90: Vijay/Nagendra | Q90: Mike Reed - BA IT/ Czerwinski, Ron - PO BA Org | T90: Case Data not available for "OnGaurd Cloud", "Netbox"
A91: LenelS2 | B91: Digital | C91: Nice CXOne(Contact Center) | D91: Asset Data( LenelS2) | E91: SFDC (AMS) | F91: Pending | H91: N | I91: Ritesh Shetty / Kote | L91: Chandra Bose / Nagendra Kumar / Vijay Illa | M91: Divya M/Devan/Dhanakoteshwar | N91: Vijay/Nagendra | Q91: Mike Reed - BA IT/ Czerwinski, Ron - PO BA Org | T91: Data not available for Product Line "OnGaurd Cloud", "Netbox"
A92: Supra | B92: Digital | C92: Nice CXOne(Contact Center) | D92: Asset Data(Supra) | E92: SFDC (AMS) | F92: Pending | H92: N | I92: Ritesh Shetty / Kote | L92: Chandra Bose / Nagendra Kumar / Vijay Illa | M92: Divya M/Devan/Dhanakoteshwar | Q92: Mike Reed - BA IT/ Czerwinski, Ron - PO BA Org
A93: Supra | B93: Digital | C93: Nice CXOne(Contact Center) | D93: Account Data(Supra) | E93: SFDC (Sales & Service) | F93: Pending | H93: N | I93: Divya M / Kote | L93: Chandra Bose / Nagendra Kumar / Vijay Illa | M93: Divya M/Devan/Dhanakoteshwar | N93: Vijay/Nagendra | Q93: Mike Reed - BA IT/ Czerwinski, Ron - PO BA Org | T93: Field Account.SUPRA_OfficeStat__c data needs to be Populated.
A94: Supra | B94: Digital | C94: Nice CXOne(Contact Center) | D94: Contact Data (Lenel S2) | E94: SFDC (Sales & Service) | F94: Pending | H94: N | I94: Divya M / Kote | L94: Chandra Bose / Nagendra Kumar / Vijay Illa | M94: Divya M/Devan/Dhanakoteshwar
A95: Supra | B95: Digital | C95: Nice CXOne(Contact Center) | D95: Contact Data (Supra) | E95: SFDC (Sales & Service) | F95: Pending | H95: N | I95: Divya M / Kote | L95: Chandra Bose / Nagendra Kumar / Vijay Illa | M95: Divya M/Devan/Dhanakoteshwar | N95: Vijay/Nagendra | Q95: Mike Reed - BA IT/ Czerwinski, Ron - PO BA Org | T95: Data not Populated for the Field Contact.SUPRA_UserStat__c
B96: Digital | C96: Portal | D96: Software Download - (Data Enrichment & Migration) - Lenel S2 NA & EMEA | E96: Azure Blob | H96: Y | I96: Ritma | K96: July 02nd, 2025 | L96: Reshma/Karan | M96: @Singh, Prabhat & @Lakra, Sufal Subir | N96: Karan | O96: July 07th, 2025 | P96: July 08th, 2025 | Q96: Saquib | R96: July 09th, 2025 | S96: July 10th, 2025 | T96: For Production this has to be part of the Portal Cutover plan. Data Load for Softwares(Azure Blob) - Bulk Migration from Access AWS instance Migration to Honeywell Azure. 1. Export of all the Software MetaData and Binaries from Lenel Systems - Sandhay Suru 2. Loading the Meta data to Honeywell RDS data Base - Sufal/Prabhat 3.Indexing the Meta data to Elastic - Devops/Arun A 4. Loading the binary to honeywell Blob storage - Sufal | U96: Karan working with @Singh, Prabhat & @Lakra, Sufal Subir for software download
B97: Digital | C97: Portal | D97: ERP Orders : Order mgmt(Order and invoice MGMT) - Lenel S2 NA & EMEA | E97: SAP ERP ( SAP-> HANA -> ETL -> Elastic - > AEM ) | H97: N | I97: NA | K97: NA | L97: Reshma/Karan | M97: Sachin Hirlekar | N97: Karan | O97: July 04th, 2025 | P97: July 05th, 2025 | Q97: Saquib | R97: July 09th, 2025 | S97: July 13th, 2025 | T97: Order Management and Invoice || SAP/ERP - HANA (Sales Org -1131, 2576) - ETL - Elastic Update HANA with Sales Org(1131, 2576) ETL Data Load for HANA sales org | U97: SAP Focal needs to be confirmed - Karan/Reshma
A98: LenelS2 | B98: Digital | C98: Portal | D98: AEM PDP Pages - Enrichment for Materials | E98: SAP ->EPIM->ETL->AEM | H98: Y | I98: Ritma/Collin | K98: July 02nd, 2025 | L98: Reshma/Karan | M98: Reshma/Karan | O98: July 04th, 2025 | P98: July 05th, 2025 | Q98: Ritma | R98: July 09th, 2025 | S98: July 13th, 2025
B99: Digital | C99: Portal | D99: EDAM- Technical Publication | E99: EDAM | H99: Y | I99: Ritma/BA IT | K99: July 02nd, 2025 | L99: Reshma/Karan | M99: Deb Mal | N99: Karan | O99: July 04th, 2025 | P99: July 06th, 2025 | Q99: Saquib | R99: July 07th, 2025 | S99: July 10th, 2025 | T99: Not Part of July Scope | U99: For Tech Pubs Saquib has asked business to provide the requested details
B100: Digital | C100: Portal | D100: Knowledge Articles | E100: SFDC (Sales & Service) | H100: N | I100: Shivani | K100: July 02nd, 2025 | L100: Reshma/Karan | M100: Divya/Kote | N100: Karan | O100: July 07th, 2025 | P100: July 10th, 2025 | Q100: Saquib | R100: July 12th, 2025 | S100: July 13th, 2025 | T100: Not Part of July Scope

Sheet CPQ
B2: Application | C2: Region | D2: Data Object | E2: Data Elements | F2: Environment | G2: Loaded Records | H2: Completed Records | I2: Valid Records | J2: Exception Records | K2: % Complete | L2: % Valid | M2: Remarks
B3: CPQ | C3: Lenel EMEA | D3: Material/Product | E3: SKU | F3: PROD
E4: Description | F4: PROD
E5: Product Catalogue | F5: PROD
E6: Product Hierarchy | F6: PROD
E7: Catalogue Hierarchy | F7: PROD
E8: Labor Cost | F8: PROD
E9: Material Cost | F9: PROD
E10: Product Version | F10: PROD
E11: Promo code | F11: PROD
E12: Renewal SKU | F12: PROD
E13: Product Action | F13: PROD
E14: License Metadata | F14: PROD
E15: Rate Plan | F15: PROD
D16: Price | E16: List Price | F16: PROD
C17: Lenel NA | F17: PROD
F18: PROD
F19: PROD
F20: PROD
F21: PROD
F22: PROD
F23: PROD
F24: PROD
F25: PROD
F26: PROD
F27: PROD
F28: PROD
F29: PROD

Sheet Zuora
B2: Application | C2: Region | D2: Data Object | E2: Data Elements | F2: Environment | G2: Loaded Records | H2: Completed Records | I2: Valid Records | J2: Exception Records | K2: % Complete | L2: % Valid | M2: Remarks
B3: Zoura | C3: Lenel EMEA | D3: Material/Product | E3: SKU | F3: PROD
E4: Description | F4: PROD
E5: Product Category | F5: PROD
E6: Product Line | F6: PROD
E7: Billing Plan | F7: PROD
E8: Milestone | F8: PROD
D9: Price | E9: Customer Price (Automated Renewal Billing) | F9: PROD
D10: Accounts (Buying) | E10: Sold-To | F10: PROD
E11: Ship-To | F11: PROD
D12: Assets | E12: BlueDiamond Subscription | F12: PROD
E13: OnGuard Subscription | F13: PROD
E14: OnGuard Cloud Subscription | F14: PROD
E15: Transactional Elements - Subscription data | F15: PROD
F16: PROD
F17: PROD

Sheet Flexera
B2: Application | C2: Region | D2: Data Object | E2: Data Elements | F2: Environment | G2: Loaded Records | H2: Completed Records | I2: Valid Records | J2: Exception Records | K2: % Complete | L2: % Valid | M2: Remarks
B3: Flexera | C3: Lenel EMEA | D3: Entitlements | E3: License Metadata | F3: PROD
E4: Entitlements | F4: PROD
E5: Licenses Fullfilment ID | F5: PROD
E6: Product, Features & License Model | F6: PROD
E7: Transaction Key | F7: PROD
E8: Template Id | F8: PROD
D9: License | E9: License Metadata (KeyType / Finger Print Type) | F9: PROD
E10: License Version | F10: PROD
D11: System ID | E11: Sync System Id | F11: PROD
E12: Parent System ID | F12: PROD
F13: PROD
F14: PROD

Sheet ELMS
B2: Application | C2: Region | D2: Data Object | E2: Data Elements | F2: Environment | G2: Loaded Records | H2: Completed Records | I2: Valid Records | J2: Exception Records | K2: % Complete | L2: % Valid | M2: Remarks
B3: ELMS | C3: Lenel EMEA/NA | D3: Material/Product | E3: Training SKU | F3: PROD
D4: Price | E4: List Price | F4: PROD
D5: Accounts (Buying) | E5: Customer | F5: PROD
D6: Contacts (Portal) | E6: Portal Contact (ELMS Users) | F6: PROD
E7: Training Tools(ELMS Users) | F7: PROD
E8: SFDC Contact ID ( Onguard/Netbox User) | F8: PROD
D9: Contact(SFDC,LMS) | E9: Training ID | F9: PROD
E10: Training Object Migration | F10: PROD
F11: PROD

Sheet E-commerce
B2: Application | C2: Region | D2: Data Object | E2: Data Elements | F2: Environment | G2: Loaded Records | H2: Completed Records | I2: Valid Records | J2: Exception Records | K2: % Complete | L2: % Valid | M2: Remarks
B3: Ecommerce | C3: Lenel EMEA | F3: PROD
F4: PROD
F5: PROD
F6: PROD
F7: PROD
F8: PROD
F9: PROD
F10: PROD
F11: PROD
F12: PROD
F13: PROD
F14: PROD
F15: PROD
C16: Lenel NA | D16: Material/Product | E16: Products | F16: PROD
E17: SKU | F17: PROD
E18: Channel Status | F18: PROD
E19: Category | F19: PROD
E20: Item Plant | F20: PROD
D21: Accounts (Buying) | E21: Customer | F21: PROD
E22: Sales Org | F22: PROD
E23: Partner | F23: PROD
E24: Hierarchy | F24: PROD
E25: Y1 Partner | F25: PROD
D26: Price | E26: Material List Price | F26: PROD
E27: Material_Listing and Exclusion | F27: PROD
D28: Contacts (E-Commerce) | E28: Contact (E-commerce Enablement) | F28: PROD

Sheet SFDC (AMS)
B2: Application | C2: Region | D2: Data Object | E2: Data Elements | F2: Environment | G2: Loaded Records | H2: Completed Records | I2: Valid Records | J2: Exception Records | K2: % Complete | L2: % Valid | M2: Remarks
B3: SFDC (AMS) | C3: Lenel EMEA | D3: Assets | E3: Assets | F3: PROD
F4: PROD
F5: PROD
F6: PROD
F7: PROD
F8: PROD
F9: PROD
F10: PROD
D11: Service Contracts | E11: Service Contracts

Sheet PROS
B2: Application | C2: Region | D2: Data Object | E2: Data Elements | F2: Environment | G2: Loaded Records | H2: Completed Records | I2: Valid Records | J2: Exception Records | K2: % Complete | L2: % Valid | M2: Remarks
B3: PROS | C3: Lenel EMEA | D3: Material/Product | E3: SKU | F3: PROD
E4: Sales Org | F4: PROD
D5: Accounts (Buying) | E5: Customer | F5: PROD
D6: Price | E6: MSRP | F6: PROD
E7: List price | F7: PROD
E8: Standard Discount | F8: PROD
E9: Negotiated Disc Net Price | F9: PROD
E10: Negotiated Discount % | F10: PROD
E11: Promotional Discounts % | F11: PROD
E12: Volume Discounts % | F12: PROD
E13: Transfer Prices | F13: PROD
F14: PROD
F15: PROD
F16: PROD
F17: PROD

Sheet Portal
B2: Application | C2: Region | D2: Data Object | E2: Data Elements | F2: Environment | G2: Loaded Records | H2: Completed Records | I2: Valid Records | J2: Exception Records | K2: % Complete | L2: % Valid | M2: Remarks
B3: Portal | C3: Lenel EMEA | D3: Accounts (Buying) | E3: Sold To | F3: PROD
E4: Var Account | F4: PROD
E5: Cumulus Sync | F5: PROD
D6: Accounts (Non-Buying) | E6: End User Account | F6: PROD
D7: Contact (Buying) | E7: Buying Contact | F7: PROD
D8: Contact (Non-Buying) | E8: Non-Buying Contact | F8: PROD
D9: Contact (Portal) | E9: WPID | F9: PROD
E10: Persona | F10: PROD
E11: Registration object | F11: PROD
E12: ACR-Ecomm flag | F12: PROD
D13: Assets | E13: Asset Data | F13: PROD
E14: License | F14: PROD
E15: Contracts | F15: PROD
E16: License Features | F16: PROD
D17: Cases | E17: Cases | F17: PROD
D18: Knowledge Articles | E18: Knowledge Articles | F18: PROD
D19: Technical Publication | E19: Technical Publications | F19: PROD
D20: Orders | E20: Order | F20: PROD
E21: Invoice | F21: PROD
D22: Material/Product | E22: PDP Pages | F22: PROD
F23: PROD
F24: PROD

Sheet PIM
B2: Application | C2: Region | D2: Data Object | E2: Data Elements | F2: Environment | G2: Loaded Records | H2: Completed Records | I2: Valid Records | J2: Exception Records | K2: % Complete | L2: % Valid | M2: Remarks
B3: PIM | C3: Lenel EMEA | D3: Material/Product | E3: SKU | F3: PROD
E4: Product Taxonomy | F4: PROD
E5: Product Catalogue | F5: PROD
F6: PROD
F7: PROD
F8: PROD
F9: PROD
F10: PROD

Sheet MDM
B2: Application | C2: Region | D2: Data Object | E2: Data Elements | F2: Environment | G2: Loaded Records | H2: Completed Records | I2: Valid Records | J2: Exception Records | K2: % Complete | L2: % Valid | M2: Remarks
B3: MDM | C3: Lenel EMEA | D3: Material/Product | E3: SKU | F3: PROD
E4: Product Hierarchy | F4: PROD
F5: PROD
F6: PROD
F7: PROD
F8: PROD
F9: PROD
F10: PROD

Sheet Marketo
B2: Application | C2: Region | D2: Data Object | E2: Data Elements | F2: Environment | G2: Loaded Records | H2: Completed Records | I2: Valid Records | J2: Exception Records | K2: % Complete | L2: % Valid | M2: Remarks
B3: Marketo | C3: Lenel NA and EMEA | D3: Marketable Records/Leads | E3: HubSpot Marketable Leads | F3: PROD
B4: Marketo | C4: Supra | D4: Marketable Records/Leads | E4: MyEmma Marketable Leads | F4: PROD
F5: PROD
F6: PROD
F7: PROD
F8: PROD
F9: PROD
F10: PROD
F11: PROD
F12: PROD
F13: PROD
F14: PROD

Sheet Contact Center
B2: Application | C2: Region | D2: Data Object | E2: Data Elements | F2: Environment | G2: Loaded Records | H2: Completed Records | I2: Valid Records | J2: Exception Records | K2: % Complete | L2: % Valid | M2: Remarks
B3: Contact Center | C3: Lenel EMEA | D3: Assets / Entitlements | E3: Assets | F3: PROD
E4: Entitlements | F4: PROD
D5: Cases | E5: Cases | F5: PROD
D6: Accounts (Buying) | E6: Accounts | F6: PROD
D7: Contacts | E7: Contacts | F7: PROD
C8: Lenel NA | F8: PROD
F9: PROD
F10: PROD
F11: PROD
F12: PROD
F13: PROD
F14: PROD
F15: PROD
F16: PROD
F17: PROD

Sheet Prod-Open Txn Mig. Non-SFDC
A1: Systems | B1: LOB | C1: Data Element | D1: Source Record Count | E1: Transaction Status | F1: Corp IT Focal | G1: BA IT Focal | H1: Primary Load Date | I1: Delta Load date | J1: Status | K1: Migration Plan | L1: Comments
A2: ERP | C2: Orders | E2: Open Sales Order | F2: Sachin and Abid | L2: Communication about the orders which need to be closed in Legacy system
E3: Partial Orders (Few lineitems are shipped)
E4: Open Purchase Order
E5: On-hold (Credit block, delivery block etc..)
E6: Open Returns
E7: Orders on desk
A8: CPQ | C8: Quotes | D8: 442 | E8: Quotes in draft | F8: Ajay, Chirag | K8: Step-1: IT team will create quote Header, sales user will need to add SKUs the the quote in NEW system in 'Preparing' status | L8: SAP - ETL - CPQ Migration Date : June 30th - July 04th SAP POC - TBC by Ashutous ETL POC - Anu CPQ - Chirag
D9: 13 | E9: Quotes submitted for Internal approval | K9: Step-1: IT team will create quote Header, sales/Service user willadd SKUs the the quote in NEW system Step-2: Business user will seek offline approval for the quotes submitted for approval in OLD system Step 3: IT team will change the quote status to Approved once approved in Old system
D10: TBD | E10: Quotes partially approved | K10: Step-1: IT team will create quote Header, sales/Service user willadd SKUs the the quote in NEW system Step-2: Business user will seek offline approval for partially approved quotes in OLD system Step 3: IT team will change the quote status to Approved if approved in Old system
D11: 4647 | E11: Quotes Submitted to Customer | K11: Step-1: IT team will create quote Header, sales/Service user willadd SKUs the the quote in NEW system Step-2: Business user will seek offline approval from customer for the quotes in OLD system Step 3: IT team will make necessary changes to skip the approval process and change the quote status to "Submitted To customer" if approved in Old system Step 4: Business users will manually change teh status to "Accepted by Customer" , enter PO deatails and proceed with booking steps
D12: 4647 | E12: Quotes Accepted by Customer
A13: SFDC | E13: PO received | F13: Divya Mohanraj (Shivani)
C14: Opportunities | E14: Draft (Open) opportunities | K14: Part of existing data migration scope. | L14: Part of existing data migration scope.
E15: Approved Opportunities | K15: Part of the DM scope - Opp created after 2023 | L15: Approved meaning (Closed) Opp already part of the DM scope from 2023. Need more details.
C16: Quotes- SFDC
L19: Opportunity Closedate>=”2024-01-01” and ApprovalStatus__c in ('Approved') and Opportunity Stagename not in ('Lost','Lost - Auto Expired','Closed Lost','On Hold') or Opportunity Closedate>=” 2025-06-01” and ApprovalStatus__c in ('Draft','Pending','Rejected','Recalled') and Opportunity Stagename not in ('Lost','Lost - Auto Expired','Closed Lost','On Hold')
A20: Zuora | F20: Mahesh / Channa Basava
A22: Zuora
A24: PROS | C24: Transactions | D24: TBD | E24: Transactions | F24: Vimal | L24: SAP/EDW integration is not done for AS , pending with EDW. It's a Blocker || Not Mandatory for Day 1
A25: Portal | C25: Open Orders | F25: Reshma / Karan | G25: Saquib | J25: Pending
A27: Portal
A29: ELMS | F29: Girish / Gayatri Tarane
A31: ELMS
A33: Flexera | F33: Abhishek Singh | H33: July 01st - 02nd | I33: July 13th - 14th | L33: Data will be given by Steve and Ab
L34: Steve will confirm, if Transactional Data is required or Not - 6/4
A40: E-commerce | C40: NA | F40: Susmita/Sonam | L40: Raut, Susmita , Please check with Sateesh and Sachin Shelar and confirm - 5/22 For Ecommerce, we don't receive any transactional Objects as confirmed by Sateesh
F41: Sonam/Sateesh
A44: Marketo | C44: NA | F44: Devendra Singh
F45: Sonam/Sateesh
A48: AMS | F48: Ritesh Shetty
F49: Sonam/Sateesh

Sheet Comments
E1: Date | F1: Comment
A2: 1 | B2: Products | C2: EPIM (QA/DEV) | D2: What has been loaded in PIM?
A3: 2 | B3: Products | C3: EPIM (Production) | D3: 102 Products need enrichment | E3: 45805
A4: 3 | B4: Products | C4: CPQ | D4: What data we have in CPQ | F4: Shashi shared the list with Ajay
A5: 4 | B5: Contacts/Accounts | C5: SAP-SFDC | D5: Tie up Accounts from ERP to SFDC and deliver the accounts. | F5: No relation with var and end-user it is not critical for UAT, but for Production we need to get the data
A6: 5 | B6: Contacts/Accounts | C6: SAP-SFDC | D6: Var and End-User Relation mapping
A7: 6 | B7: Contacts/Accounts | D7: Portal E-commerce access, map access to all the contacts Shivani to extract the list of contacts, cross check if persona is mapped already from source.
A8: 7 | B8: Pricing | C8: EPIM | D8: List price to come in EPIM (NA)
C9: CPQ | D9: Customer price is set in ERP

Sheet Plan
A1: SNo | B1: Env | C1: Region | D1: Status | E1: Due Date | F1: Status | G1: Owner
A2: 1 | B2: BTFULL | C2: Lenel EMEA - List of Objects Finalization | D2: Completed | E2: 45775 | F2: Addl objects list shared with Data migration team | G2: Full Team
A3: 2 | B3: BTFULL | C3: Lenel NA - List of Objects Finalization | D3: Completed | E3: 45775 | F3: Addl objects list shared with Data migration team | G3: Full Team
A4: 3 | B4: BTFULL | C4: Supra NA - List of Objects Finalization | D4: Completed | E4: 45776 | F4: Addl objects list shared with Data migration team | G4: Full Team
